Workbook
Name JobList_JOBID: #REF!
Name JobList_JOBID: #REF!
Name JobList_SID: #REF!
Name JobList_SID: #REF!
Name TECHNICIAN: #REF!
Name JobList_JOBID: #REF!
Name JobList_SID: #REF!
Name JobList_JOBID: #REF!
Name JobList_SID: #REF!

Sheet stg_contract_values
A1: Contract # | B1: Contract Status | C1: Contract Execution Date | D1: Contract Expiration Date | E1: Contract Home Multiplier | F1: Contract Field Multiplier | G1: Contract Value
A2: C000015869 | B2: Closed | C2: 44621 | D2: 45716 | E2: 2.75 | F2: 2.54 | G2: 6000000
A3: C000015128 | B3: Closed | C3: 43424 | D3: 44519 | E3: 2.51 | F3: 2.41 | G3: 6000000
A4: C000016435 | B4: Open | C4: 45728 | D4: 46823 | E4: 3 | F4: 2.93 | G4: 5000000

Sheet stg_sca_rfp
A1: BuildingID | B1: Project _D | C1: Project Descriptio | D1: ServiceID | E1: ServiceName | F1: InitiationDate | G1: PrimaryHygienist | H1: WA_Number | I1: ContractNo | J1: RFPNo | K1: IsFinal | L1: RFP_Status | M1: RFP_Status_Date | N1: eRFP_Status | O1: eRFP_Status_Date | P1: RFPDate
A2: M180 | B2: 141149 | C2: PO18-ABATEMENT OF PIPE INSULATION ENTRANCE OF BOILER RM WE ARE GOING TO NEED APPROXIMATELY 10' OF CO | D2: 93632 | E2: PO 18 Asbestos Service | F2: 45573 | G2: Lazicki, Rafal | H2: 1315970 | I2: C000015869 | J2: 202 | K2: Y | L2: Check Issued | M2: 45888 | N2: Closed | O2: 45888 | P2: =DATE(YEAR(O2),MONTH(O2),DAY(O2)) -> 45888
A3: R455 | B3: 135678 | C3: PO18-ASSIST PLUMBERS: OPEN A 3FT X 8FT CIELING SPRAYED IN RED. ALSO REMOVE ALL LOOSE ACM IN CIELING | D3: 88731 | E3: PO 18 Asbestos Service | F3: 45120 | G3: Bracamonte, Jesus | H3: 1187909 | I3: C000015869 | J3: 224 | K3: Y | L3: Check Issued | M3: 45888 | N3: Closed | O3: 45888 | P3: =DATE(YEAR(O3),MONTH(O3),DAY(O3)) -> 45888
A4: K014 | B4: P026159 | C4: RESO A AUDITORIUM UPGRADE | D4: 85451 | E4: LAP Construction Phase Services | F4: 44741 | G4: Clyne, Sean | H4: 1129904 | I4: C000015869 | J4: 305 | K4: Y | L4: Check Issued | M4: 46018 | N4: Closed | O4: 46018 | P4: =DATE(YEAR(O4),MONTH(O4),DAY(O4)) -> 46018
A5: Q189 | B5: 133460 | C5: PO18-05/25Q189/ BOILER #3 ABATE 1 SQUARE FOOT OF ACM, SPRAYED IN GREEN | D5: 86933 | E5: PO 18 Asbestos Service | F5: 44910 | G5: Kondilis, Milton | H5: 1157908 | I5: C000015869 | J5: 312 | K5: Y | L5: Check Issued | M5: 46100 | N5: Closed | O5: 46100 | P5: =DATE(YEAR(O5),MONTH(O5),DAY(O5)) -> 46100
A6: X107 | B6: 141770 | C6: PO18-ABATE AND REPAIR DAMAGED PIPE INSULATION 1000, 3218 ABATE AND REPLACE FLOOR TILES 1001S, 2106, | D6: 94758 | E6: PO 18 Asbestos Service | F6: 45695 | G6: Bracamonte, Jesus | H6: 1334935 | I6: C000015869 | J6: 319 | K6: Y | L6: Check Issued | M6: 46165 | N6: Closed | O6: 46165 | P6: =DATE(YEAR(O6),MONTH(O6),DAY(O6)) -> 46165

Sheet stg_sca_fixed_prices
A1: Contract No | B1: Work Type Code | C1: Work Type Desc | D1: Fixed Price | E1: Status Date
A2: C000016435 | B2: LAMP48 | C2: Lead Wipe Clearance - CIP & Capacity | D2: 375 | E2: 45126
A3: C000016435 | B3: LAMP19 | C3: Lead Wipe Clearance - PO18 | D3: 375 | E3: 45126
A4: C000016435 | B4: LAMP18 | C4: Project Records Package Review | D4: 375 | E4: 45126
A5: C000016435 | B5: LAMP23 | C5: Emergency Site Visit | D5: 375 | E5: 45126
A6: C000016435 | B6: LAMP20 | C6: PO18 Survey | D6: 750 | E6: 45126
A7: C000016435 | B7: LAMP05 | C7: PO18 Cores | D7: 650 | E7: 45126
A8: C000016435 | B8: LAMP21 | C8: Mold Survey | D8: 750 | E8: 45126
A9: C000016435 | B9: LCS149 | C9: ACP5 Fee | D9: 500 | E9: 45126
A10: C000016435 | B10: LCS152 | C10: CTF/Small Cap/Local Law Asbestos Survey | D10: 750 | E10: 45126
A11: C000016435 | B11: LAMP1000 | C11: No Sampling Required Rate for Service | D11: 750 | E11: 45126
A12: C000015128 | B12: LAMP48 | C12: Lead Wipe Clearance - CIP & Capacity | D12: 250 | E12: 41923
A13: C000015128 | B13: LAMP19 | C13: Lead Wipe Clearance - PO18 | D13: 250 | E13: 41923
... A31: C000015869 | B31: LAMP1000 | C31: No Sampling Required Rate for Service | D31: 500 | E31: 44271

Sheet stg_sca_wa
A1: Building Id | B1: Building Name | C1: Building Address | D1: Project ID | E1: Project Name | F1: Project Type | G1: Service ID | H1: Service Name | I1: Service Initiation Date | J1: Priority | K1: Primary Hygienist | L1: Contract_No | M1: WA_No | N1: WA Type | O1: Date WA Issued | P1: WA Status | Q1: Status Date | R1: Expected Due Date | S1: Original WA Amt | T1: Current Approved Amt | U1: Proposed Amendment Amt | V1: WA_Total_Amt
A2: X107 | B2: P.S. 107 - BRONX | C2: 1695 SEWARD AVENUE | D2: 141770 | E2: PO18-ABATE AND REPAIR DAMAGED PIPE INSULATION 1000, 3218 ABATE AND REPLACE FLOOR TILES 1001S, 2106, | F2: CIP | G2: 94758 | H2: PO 18 Asbestos Service | I2: 45695 | J2: Emergency | K2: Bracamonte, Jesus | L2: C000015869 | M2: 1334935 | N2: RFA | O2: 45695 | P2: Closed | Q2: 46165 | S2: 575 | T2: 39440.45 | U2: 0 | V2: 39440.45
A3: M180 | B3: P.S. 180 - MANHATTAN | C3: 370 WEST 120 STREET | D3: 141149 | E3: PO18-ABATEMENT OF PIPE INSULATION ENTRANCE OF BOILER RM WE ARE GOING TO NEED APPROXIMATELY 10' OF CO | F3: CIP | G3: 93632 | H3: PO 18 Asbestos Service | I3: 45573 | J3: Emergency | K3: Lazicki, Rafal | L3: C000015869 | M3: 1315970 | N3: RFA | O3: 45575 | P3: Closed | Q3: 45888 | S3: 575 | T3: 4759.59 | U3: 0 | V3: 4759.59
A4: R455 | B4: TOTTENVILLE HS - STATEN ISLAND | C4: 100 LUTEN AVENUE | D4: 135678 | E4: PO18-ASSIST PLUMBERS: OPEN A 3FT X 8FT CIELING SPRAYED IN RED. ALSO REMOVE ALL LOOSE ACM IN CIELING | F4: CIP | G4: 88731 | H4: PO 18 Asbestos Service | I4: 45120 | J4: Emergency | K4: Bracamonte, Jesus | L4: C000015869 | M4: 1187909 | N4: RFA | O4: 45120 | P4: Closed | Q4: 45888 | S4: 7875 | T4: 2628.23 | U4: 0 | V4: 2628.23
A5: Q189 | B5: J.H.S. 189 - QUEENS | C5: 144-80 BARCLAY AVENUE | D5: 133460 | E5: PO18-05/25Q189/ BOILER #3 ABATE 1 SQUARE FOOT OF ACM, SPRAYED IN GREEN | F5: CIP | G5: 86933 | H5: PO 18 Asbestos Service | I5: 44910 | J5: Emergency | K5: Kondilis, Milton | L5: C000015869 | M5: 1157908 | N5: RFA | O5: 44910 | P5: Closed | Q5: 46100 | S5: 3200 | T5: 1867.45 | U5: 0 | V5: 1867.45
A6: K014 | B6: I.S. 14 - BROOKLYN | C6: 2424 BATCHELDER STREET | D6: P026159 | E6: RESO A AUDITORIUM UPGRADE | F6: CIP | G6: 85451 | H6: LAP Construction Phase Services | I6: 44741 | J6: Normal | K6: Clyne, Sean | L6: C000015869 | M6: 1129904 | N6: RFA | O6: 44749 | P6: Closed | Q6: 46018 | S6: 9700 | T6: 3108.44 | U6: 0 | V6: 3108.44

Sheet stg_monthly_status
A1: JobID | B1: Contract_No | C1: BuildingID | D1: School_Name | E1: WA_NO | F1: Service_ID | G1: Project Type | H1: Primary_Hygienist | I1: Service_Name | J1: WA Type | K1: WA Status | L1: Initiation_Date | M1: WA_Estimate_Cost | N1: Actual Start Date (RFP) | O1: Actual Date of Completion (RFP) | P1: RFP_No | Q1: RFP_Date | R1: Amount_Invoiced | S1: Amount_Received | T1: Amount Outstanding | U1: Check_No | V1: DATE ON CHECK | W1: DATE CHECK RECEIVED | X1: Billing_Status
A2: 17SD-136 | B2: C000013440 | C2: M470 | D2: LOUIS D. BRANDEIS HS - MANHATTAN | E2: 888431 | F2: 68127 | G2: CIP | H2: Langlois, Bret | I2: LAP Design Review & Specification | J2: Amendment | K2: WIP | L2: 43046 | M2: 3575 | S2: 0 | T2: 0 | X2: NOT BILLED
A3: 21S-100 | B3: C000015128 | C3: K186 | D3: P.S. 186 - BROOKLYN | E3: 1097498 | F3: 82916 | G3: CIP | H3: Scott, Richard | I3: PO 18 Asbestos Service | J3: Amendment | K3: WIP | L3: 44505 | M3: 10700 | S3: 0 | T3: 0 | X3: NOT BILLED
A4: 24S-077 | B4: C000015128 | C4: Q089 | D4: P.S. 89 - QUEENS | E4: 1302817 | F4: 92921 | G4: CIP | H4: Poskrobko, Lukasz | I4: PO 18 Asbestos Service | J4: Initial | K4: Closed | L4: 45513 | M4: 575 | N4: 45514 | O4: 45515 | P4: 327 | Q4: 46175 | R4: 2774.69 | S4: 0 | T4: -2774.69 | X4: UNPAID
A5: 21S-105 | B5: C000015128 | C5: X405 | D5: HERBERT H. LEHMAN HS - BRONX | E5: 1098818 | F5: 83582 | G5: CIP | H5: Alawamleh, Eman | I5: LAP Construction Phase Services | J5: Initial | K5: WIP | L5: 44516 | M5: 500 | S5: 0 | T5: 0 | X5: NOT BILLED
A6: 22S-029 | B6: C000015869 | C6: K014 | D6: I.S. 14 - BROOKLYN | E6: 1129904 | F6: 85451 | G6: CIP | H6: Clyne, Sean | I6: LAP Construction Phase Services | J6: Initial | K6: Closed | L6: 44754 | M6: 9700 | N6: 44749 | O6: 44758 | P6: 305 | Q6: 46000 | R6: 3108.44 | S6: 3108.44 | T6: 0 | U6: 700005330 | V6: 46019 | W6: 46021 | X6: PAID
A7: 24S-128 | B7: C000015869 | C7: K043 | D7: I.S. 98 - BROOKLYN | E7: 1320962 | F7: 93925 | G7: CIP | H7: Bracamonte, Jesus | I7: Special Program | J7: Initial | K7: Initial | L7: 45609 | M7: 4100 | S7: 0 | T7: 0 | X7: NOT BILLED
B8: C000015869 | C8: K102 | D8: P.S. 102 - BROOKLYN | E8: 1306782 | F8: 92043 | G8: CIP | H8: Scott, Richard | I8: PO 18 Asbestos Service | J8: Initial | K8: Initial | L8: 45533 | M8: 575 | S8: 0 | T8: 0 | X8: NOT BILLED
A9: 25S-012 | B9: C000015869 | C9: K138 | D9: P.S. 138 - BROOKLYN | E9: 1335922 | F9: 94843 | G9: CIP | H9: Palermo, Albert | I9: PO 18 Asbestos Service | J9: Initial | K9: Initial | L9: 45701 | M9: 6275 | S9: 0 | T9: 0 | X9: NOT BILLED
A10: 24S-061 | B10: C000015869 | C10: K151 | D10: P.S. 151 - BROOKLYN | E10: 1302568 | F10: 92321 | G10: CIP | H10: Walsh, Joseph | I10: PO 18 Asbestos Service | J10: Initial | K10: Initial | L10: 45509 | M10: 575 | S10: 0 | T10: 0 | X10: NOT BILLED
A11: 24S-014 | B11: C000015869 | C11: K160 | D11: P.S. 160 - BROOKLYN | E11: 1222094 | F11: 90892 | G11: CIP | H11: Scott, Richard | I11: PO 18 Asbestos Service | J11: Initial | K11: Initial | L11: 45350 | M11: 575 | S11: 0 | T11: 0 | X11: NOT BILLED
A12: 24S-054 | B12: C000015869 | C12: K162 | D12: I.S. 162 - BROOKLYN | E12: 1244202 | F12: 92352 | G12: CIP | H12: Walsh, Joseph | I12: PO 18 Asbestos Service | J12: Initial | K12: Initial | L12: 45475 | M12: 575 | S12: 0 | T12: 0 | X12: NOT BILLED
A13: 23S-129 | B13: C000015869 | C13: K163 | D13: P.S. 163 - BROOKLYN | E13: 1209543 | F13: 90141 | G13: CIP | H13: Bracamonte, Jesus | I13: LAP Construction Phase Services | J13: Initial | K13: Closed | L13: 45267 | M13: 11545 | N13: 45274 | O13: 45274 | P13: 326 | Q13: 46170 | R13: 3320.75 | S13: 0 | T13: -3320.75 | X13: UNPAID
A14: 23S-005 | B14: C000015869 | C14: K183 | D14: P.S. 183 - BROOKLYN | E14: 1160059 | F14: 87043 | G14: CIP | H14: Palermo, Albert | I14: PO 18 Asbestos Service | J14: Amendment | K14: WIP | L14: 44936 | M14: 5575 | S14: 0 | T14: 0 | X14: NOT BILLED
A15: 23S-120 | B15: C000015869 | C15: K224 | D15: P.S. 224 - BROOKLYN | E15: 1212815 | F15: 90349 | G15: CIP | H15: Vafiadis, Jon | I15: Special Program | J15: Initial | K15: Closed | L15: 45303 | M15: 1500 | N15: 45289 | O15: 45289 | P15: 329 | Q15: 46182 | R15: 933.13 | S15: 0 | T15: -933.13 | X15: UNPAID
B16: C000015869 | C16: K226 | D16: P.S. 126 - BROOKLYN | E16: 1317417 | G16: CIP | H16: Bracamonte, Jesus | I16: Special Program | J16: Initial | K16: Initial | L16: 45587 | M16: 4100 | S16: 0 | T16: 0 | X16: NOT BILLED
B17: C000015869 | C17: K226 | D17: P.S. 226 - BROOKLYN | E17: 1317422 | G17: CIP | H17: Bracamonte, Jesus | I17: Special Program | J17: Initial | K17: Initial | L17: 45587 | M17: 7800.06 | S17: 0 | T17: 0 | X17: NOT BILLED
A18: 24S-016 | B18: C000015869 | C18: K232 | D18: I.S. 232 - BROOKLYN | E18: 1223724 | F18: 89776 | G18: CIP | H18: Bracamonte, Jesus | I18: LAP Construction Phase Services | J18: Initial | K18: Initial | L18: 45364 | M18: 13900 | S18: 0 | T18: 0 | X18: NOT BILLED
A19: 24S-017 | B19: C000015869 | C19: K232 | D19: I.S. 232 - BROOKLYN | E19: 1223722 | F19: 89766 | G19: CIP | H19: Bracamonte, Jesus | I19: LAP Construction Phase Services | J19: Initial | K19: Initial | L19: 45365 | M19: 13900 | S19: 0 | T19: 0 | X19: NOT BILLED
A20: 24S-018 | B20: C000015869 | C20: K232 | D20: I.S. 232 - BROOKLYN | E20: 1223723 | F20: 89768 | G20: CIP | H20: Bracamonte, Jesus | I20: LAP Construction Phase Services | J20: Initial | K20: Closed | L20: 45365 | M20: 13900 | N20: 45365 | O20: 45887 | P20: 324 | Q20: 46150 | R20: 12493.53 | S20: 0 | T20: -12493.53 | X20: UNPAID
B21: C000015869 | C21: K233 | D21: P.S. 233 - BROOKLYN | E21: 1212811 | F21: 90339 | G21: CIP | H21: Vafiadis, Jon | I21: Special Program | J21: Initial | K21: Initial | L21: 45302 | M21: 1500 | S21: 0 | T21: 0 | X21: NOT BILLED
B22: C000015869 | C22: K244 | D22: P.S. 244 - BROOKLYN | E22: 1212812 | F22: 90338 | G22: CIP | H22: Vafiadis, Jon | I22: Special Program | J22: Initial | K22: Initial | L22: 45302 | M22: 1500 | S22: 0 | T22: 0 | X22: NOT BILLED
B23: C000015869 | C23: K250 | D23: P.S. 250 - BROOKLYN | E23: 1212797 | F23: 90325 | G23: CIP | H23: Vafiadis, Jon | I23: Special Program | J23: Initial | K23: Initial | L23: 45302 | M23: 1500 | S23: 0 | T23: 0 | X23: NOT BILLED
B24: C000015869 | C24: K260 | D24: P.S. 260 - BROOKLYN | E24: 1212816 | F24: 90348 | G24: CIP | H24: Vafiadis, Jon | I24: Special Program | J24: Initial | K24: Initial | L24: 45303 | M24: 1500 | S24: 0 | T24: 0 | X24: NOT BILLED
B25: C000015869 | C25: K273 | D25: P.S. 273 - BROOKLYN | E25: 1212817 | F25: 90347 | G25: CIP | H25: Vafiadis, Jon | I25: Special Program | J25: Initial | K25: Initial | L25: 45303 | M25: 1500 | S25: 0 | T25: 0 | X25: NOT BILLED
B26: C000015869 | C26: K276 | D26: P.S. 276 - BROOKLYN | E26: 1212812 | F26: 90337 | G26: CIP | H26: Vafiadis, Jon | I26: Special Program | J26: Initial | K26: Initial | L26: 45303 | M26: 1500 | S26: 0 | T26: 0 | X26: NOT BILLED
B27: C000015869 | C27: K279 | D27: P.S. 279 - BROOKLYN | E27: 1212814 | F27: 90336 | G27: CIP | H27: Vafiadis, Jon | I27: Special Program | J27: Initial | K27: Initial | L27: 45303 | M27: 1500 | S27: 0 | T27: 0 | X27: NOT BILLED
B28: C000015869 | C28: K287 | D28: P.S. 287 - BROOKLYN | E28: 1212544 | F28: 90316 | G28: CIP | H28: Vafiadis, Jon | I28: Special Program | J28: Initial | K28: Initial | L28: 45302 | M28: 1500 | S28: 0 | T28: 0 | X28: NOT BILLED
A29: 23S-075 | B29: C000015869 | C29: K335 | D29: P.S. 335 - BROOKLYN | E29: 1189823 | F29: 88936 | G29: CIP | H29: Palermo, Albert | I29: PO 18 Asbestos Service | J29: Initial | K29: WIP | L29: 45152 | M29: 575 | S29: 0 | T29: 0 | X29: NOT BILLED
B30: C000015869 | C30: K370 | D30: P.S. 370 - BROOKLYN | E30: 1317423 | G30: CIP | H30: Bracamonte, Jesus | I30: Special Program | J30: Initial | K30: Initial | L30: 45587 | M30: 7800.06 | S30: 0 | T30: 0 | X30: NOT BILLED
B31: C000015869 | C31: K615 | D31: E NY VOC HS OF TRANSIT TECH - BROOKLYN | E31: 1210691 | F31: 90158 | G31: CIP | H31: Palermo, Albert | I31: PO 18 Asbestos Service | J31: Amend 1 | K31: Initial | L31: 45279 | M31: 5375 | S31: 0 | T31: 0 | X31: NOT BILLED
A32: 24S-026 | B32: C000015869 | C32: K620 | D32: WILLIAM E GRADY VOC HS - BROOKLYN | E32: 1224928 | F32: 91352 | G32: CIP | H32: Bracamonte, Jesus | I32: LAP Construction Phase Services | J32: Initial | K32: Initial | L32: 45378 | M32: 12400 | S32: 0 | T32: 0 | X32: NOT BILLED
B33: C000015869 | C33: K851 | D33: P.S. 159 MINI SCHOOL - BROOKLYN | E33: 1320959 | F33: 93959 | G33: CIP | H33: Bracamonte, Jesus | I33: SAFE ACCESS | J33: Initial | K33: Initial | L33: 45609 | M33: 4100 | S33: 0 | T33: 0 | X33: NOT BILLED
A34: 24S-087 | B34: C000015869 | C34: K932 | D34: HIGH SCHOOL SUSPENSION CENTER - BROOKLYN | E34: 1305383 | F34: 92976 | G34: CIP | H34: Bracamonte, Jesus | I34: PO 18 Asbestos Service | J34: Initial | K34: Initial | L34: 45520 | M34: 4000 | S34: 0 | T34: 0 | X34: NOT BILLED
A35: 24S-148 | B35: C000015869 | C35: M061 | D35: P.S. 61 - MANHATTAN | E35: 1301457 | F35: 92654 | G35: CIP | H35: Lazicki, Rafal | I35: PO 18 Asbestos Service | J35: Initial | K35: Closed | L35: 45498 | M35: 575 | N35: 45911 | O35: 45913 | P35: 331 | Q35: 46182 | R35: 6371.31 | S35: 0 | T35: -6371.31 | X35: UNPAID
A36: 23S-117 | B36: C000015869 | C36: M115 | D36: P.S. 115 - MANHATTAN | E36: 1206373 | F36: 90058 | G36: CIP | H36: Alawamleh, Eman | I36: PO 18 Asbestos Service | J36: Initial | K36: WIP | L36: 45259 | M36: 7923.73 | N36: 45267 | O36: 45269 | P36: 320 | Q36: 46125 | R36: 8091.98 | S36: 0 | T36: -8091.98 | X36: UNPAID
A37: 24S-049 | B37: C000015869 | C37: M115 | D37: P.S. 115 - MANHATTAN | E37: 1241224 | F37: 92097 | G37: CIP | H37: Bracamonte, Jesus | I37: LAP Construction Phase Services | J37: Initial | K37: Initial | L37: 45455 | M37: 20200 | S37: 0 | T37: 0 | X37: NOT BILLED
B38: C000015869 | C38: M124 | D38: P.S. 124 (ECF) - MANHATTAN | E38: 1316025 | F38: 93166 | G38: CIP | I38: PO 18 Asbestos Service | J38: Initial | K38: Initial | L38: 45575 | M38: 575 | S38: 0 | T38: 0 | X38: NOT BILLED
B39: C000015869 | C39: M125 | D39: P.S. 125 - MANHATTAN | E39: 1335879 | F39: 94453 | G39: CIP | H39: Bracamonte, Jesus | I39: LAP Construction Phase Services | J39: Initial | K39: Initial | L39: 45708 | M39: 16200 | S39: 0 | T39: 0 | X39: NOT BILLED
A40: 24S-053 | B40: C000015869 | C40: M152 | D40: P.S. 152 - MANHATTAN | E40: 1243709 | F40: 92223 | G40: CIP | H40: Alawamleh, Eman | I40: PO 18 Asbestos Service | J40: Initial | K40: Initial | L40: 45343 | M40: 575 | S40: 0 | T40: 0 | X40: NOT BILLED
A41: 24S-023 | B41: C000015869 | C41: M163 | D41: P.S. 163 - MANHATTAN | E41: 1225180 | F41: 91391 | G41: CIP | H41: Lazicki, Rafal | I41: PO 18 Asbestos Service | J41: Initial | K41: Initial | L41: 45377 | M41: 575 | S41: 0 | T41: 0 | X41: NOT BILLED
A42: 24S-114 | B42: C000015869 | C42: M180 | D42: P.S. 180 - MANHATTAN | E42: 1315970 | F42: 93632 | G42: CIP | H42: Lazicki, Rafal | I42: PO 18 Asbestos Service | J42: Initial | K42: Closed | L42: 45575 | M42: 575 | N42: 45583 | O42: 45584 | P42: 202 | Q42: 45825 | R42: 4759.59 | S42: 4759.59 | T42: 0 | U42: 700000530 | V42: 45876 | X42: PAID
A43: 24S-006 | B43: C000015869 | C43: M192 | D43: P.S. 192 - MANHATTAN | E43: 1218023 | F43: 90701 | G43: CIP | H43: Alawamleh, Eman | I43: PO 18 Asbestos Service | J43: Initial | K43: Closed | L43: 45327 | M43: 575 | N43: 45757 | O43: 45808 | P43: 318 | Q43: 46083 | R43: 15850.89 | S43: 0 | T43: -15850.89 | X43: UNPAID
A44: 24S-002 | B44: C000015869 | C44: M440 | D44: BAYARD RUSTIN EDUCATIONAL COMPLEX - MANHATTAN | E44: 1213594 | F44: 90375 | G44: CIP | H44: Lazicki, Rafal | I44: PO 18 Asbestos Service | J44: Initial | K44: Initial | L44: 45301 | M44: 575 | S44: 0 | T44: 0 | X44: NOT BILLED
A45: 24S-024 | B45: C000015869 | C45: M465 | D45: G. WASHINGTON HS EDUC. CAMPUS - M465 | E45: 1225222 | G45: CIP | I45: PO 18 Asbestos Service | J45: Initial | K45: Initial | L45: 45333 | M45: 575 | S45: 0 | T45: 0 | X45: NOT BILLED
A46: 23S-097 | B46: C000015869 | C46: M470 | D46: LOUIS D. BRANDEIS HS - MANHATTAN | E46: 1198033 | F46: 89608 | G46: CIP | H46: Bracamonte, Jesus | I46: LAP Construction Phase Services | J46: Initial | K46: Closed | L46: 45202 | M46: 19020 | N46: 45202 | O46: 45402 | P46: 315 | Q46: 46052 | R46: 17728.88 | S46: 0 | T46: -17728.88 | X46: UNPAID
A47: 24S-144 | B47: C000015869 | C47: M540 | D47: A. PHILLIP RANDOLPH HS - MANHATTAN | E47: 1329559 | F47: 94412 | G47: CIP | H47: Alawamleh, Eman | I47: PO 18 Asbestos Service | J47: Initial | K47: WIP | L47: 45657 | M47: 575 | S47: 0 | T47: 0 | X47: NOT BILLED
A48: 24S-047 | B48: C000015869 | C48: Q024 | D48: P.S. 24 - QUEENS | E48: 1239285 | F48: 91978 | G48: CIP | I48: PO 18 Asbestos Service | J48: Initial | K48: Initial | L48: 45448 | M48: 575 | S48: 0 | T48: 0 | X48: NOT BILLED
A49: 24S-035 | B49: C000015869 | C49: Q037 | D49: P.S. 37 - QUEENS | E49: 1232764 | F49: 91801 | G49: CIP | I49: LAP Construction Phase Services | J49: Initial | K49: Initial | L49: 45422 | M49: 11700 | S49: 0 | T49: 0 | X49: NOT BILLED
A50: 24S-036 | B50: C000015869 | C50: Q037 | D50: P.S. 37 - QUEENS | E50: 1232763 | F50: 91803 | G50: CIP | H50: Bracamonte, Jesus | I50: LAP Construction Phase Services | J50: Initial | K50: Initial | L50: 45422 | M50: 15400 | S50: 0 | T50: 0 | X50: NOT BILLED
B51: C000015869 | C51: Q061 | D51: I.S. 61 - QUEENS | E51: 1124663 | F51: 85105 | G51: CIP | H51: Poskrobko, Lukasz | I51: PO 18 Asbestos Service | J51: Initial | K51: WIP | L51: 44705 | M51: 575 | S51: 0 | T51: 0 | X51: NOT BILLED
B52: C000015869 | C52: Q122 | D52: P.S. 122 - QUEENS | E52: 1125492 | F52: 85171 | G52: CIP | H52: Poskrobko, Lukasz | I52: PO 18 Asbestos Service | J52: Initial | K52: WIP | L52: 44706 | M52: 575 | S52: 0 | T52: 0 | X52: NOT BILLED
A53: 24S-015 | B53: C000015869 | C53: Q165 | D53: P.S. 165 - QUEENS | E53: 1223510 | F53: 88306 | G53: CIP | H53: Kondilis, Milton | I53: PO 18 Asbestos Service | J53: Initial | K53: Initial | L53: 45359 | M53: 575 | S53: 0 | T53: 0 | X53: NOT BILLED
B54: C000015869 | C54: Q166 | D54: P.S. 166 - QUEENS | E54: 1314909 | F54: 93419 | G54: CIP | I54: PO 18 Asbestos Service | J54: Initial | K54: Initial | L54: 45568 | M54: 575 | S54: 0 | T54: 0 | X54: NOT BILLED
A55: 22S-079 | B55: C000015869 | C55: Q189 | D55: J.H.S. 189 - QUEENS | E55: 1157908 | F55: 86933 | G55: CIP | H55: Kondilis, Milton | I55: PO 18 Asbestos Service | J55: Initial | K55: Closed | L55: 44910 | M55: 3200 | N55: 44910 | O55: 44911 | P55: 312 | Q55: 46038 | R55: 1867.45 | S55: 1867.45 | T55: 0 | U55: 700007076 | V55: 46101 | W55: 46111 | X55: PAID
B56: C000015869 | C56: Q192 | D56: I.S. 192 - QUEENS | E56: 1140015 | F56: 86082 | G56: CIP | H56: Kondilis, Milton | I56: PO 18 Asbestos Service | J56: Initial | K56: WIP | L56: 44811 | M56: 575 | S56: 0 | T56: 0 | X56: NOT BILLED
B57: C000015869 | C57: Q196 | D57: P.S. 196 - QUEENS | E57: 1192028 | F57: 88590 | G57: CIP | H57: Poskrobko, Lukasz | I57: PO 18 Asbestos Service | J57: Initial | K57: WIP | L57: 45161 | M57: 575 | S57: 0 | T57: 0 | X57: NOT BILLED
A58: 24S-019 | B58: C000015869 | C58: Q225 | D58: P.S. 225 - QUEENS | E58: 1223719 | F58: 89359 | G58: CIP | H58: Bracamonte, Jesus | I58: LAP Construction Phase Services | J58: Initial | K58: Initial | L58: 45365 | M58: 13900 | S58: 0 | T58: 0 | X58: NOT BILLED
A59: 24S-020 | B59: C000015869 | C59: Q225 | D59: P.S. 225 - QUEENS | E59: 1223718 | F59: 89963 | G59: CIP | H59: Bracamonte, Jesus | I59: LAP Construction Phase Services | J59: Initial | K59: Initial | L59: 45365 | M59: 13900 | S59: 0 | T59: 0 | X59: NOT BILLED
A60: 25S-006 | B60: C000015869 | C60: Q400 | D60: AUGUST MARTIN HS - QUEENS | E60: 1323411 | F60: 94004 | G60: CIP | H60: Bracamonte, Jesus | I60: LAP Construction Phase Services | J60: Initial | K60: Closed | L60: 45622 | M60: 14100 | N60: 45686 | O60: 45844 | P60: 332 | Q60: 46182 | R60: 21390.66 | S60: 0 | T60: -21390.66 | X60: UNPAID
B61: C000015869 | C61: Q420 | D61: SPRINGFIELD GARDENS HS - QUEENS | E61: 1319456 | F61: 93726 | G61: CIP | H61: Bracamonte, Jesus | I61: LAP Construction Phase Services | J61: Initial | K61: WIP | L61: 45628 | M61: 15400 | S61: 0 | T61: 0 | X61: NOT BILLED
A62: 23S-001 | B62: C000015869 | C62: Q800 | D62: DOE ADMINISTRATIVE / STUDENT SERVICES - QUEENS | E62: 1147905 | F62: 86152 | G62: CIP | H62: Poskrobko, Lukasz | I62: PO 18 Asbestos Service | J62: Initial | K62: WIP | L62: 44929 | M62: 575 | S62: 0 | T62: 0 | X62: NOT BILLED
A63: 24S-008 | B63: C000015869 | C63: R002 | D63: I.S. 2 - STATEN ISLAND | E63: 1224066 | F63: 91184 | G63: CIP | H63: Bracamonte, Jesus | I63: PO 18 Asbestos Service | J63: Initial | K63: Closed | L63: 45352 | M63: 4200 | N63: 45352 | O63: 45353 | P63: 323 | Q63: 46142 | R63: 5166.39 | S63: 0 | T63: -5166.39 | X63: UNPAID
A64: 24S-033 | B64: C000015869 | C64: R013 | D64: P.S. 13 - STATEN ISLAND | E64: 1232533 | F64: 91809 | G64: CIP | I64: LAP Construction Phase Services | J64: Initial | K64: Initial | L64: 45421 | M64: 15400 | S64: 0 | T64: 0 | X64: NOT BILLED
A65: 24S-034 | B65: C000015869 | C65: R013 | D65: P.S. 13 - STATEN ISLAND | E65: 1232548 | F65: 91836 | G65: CIP | I65: LAP Construction Phase Services | J65: Initial | K65: Initial | L65: 45422 | M65: 11200 | S65: 0 | T65: 0 | X65: NOT BILLED
A66: 24S-011 | B66: C000015869 | C66: R022 | D66: P.S. 22 - STATEN ISLAND | E66: 1213407 | F66: 82742 | G66: CIP | H66: Bracamonte, Jesus | I66: LAP Construction Phase Services | J66: Initial | K66: Initial | L66: 45300 | M66: 5500 | S66: 0 | T66: 0 | X66: NOT BILLED
A67: 25S-007 | B67: C000015869 | C67: R024 | D67: I.S. 24 - STATEN ISLAND | E67: 1333354 | F67: 94637 | G67: CIP | H67: Bracamonte, Jesus | I67: PO 18 Asbestos Service | J67: Initial | K67: WIP | L67: 45687 | M67: 10275 | S67: 0 | T67: 0 | X67: NOT BILLED
A68: 24S-089 | B68: C000015869 | C68: R026 | D68: P.S. 26 - STATEN ISLAND | E68: 1310116 | F68: 93264 | G68: CIP | H68: Bracamonte, Jesus | I68: PO 18 Asbestos Service | J68: Initial | K68: Initial | L68: 45541 | M68: 575 | S68: 0 | T68: 0 | X68: NOT BILLED
A69: 22S-032 | B69: C000015869 | C69: R032 | D69: P.S. 32 - STATEN ISLAND | E69: 1132984 | F69: 85600 | G69: CIP | H69: Bracamonte, Jesus | I69: PO 18 Asbestos Service | J69: Initial | K69: Closed | L69: 44762 | M69: 6000 | N69: 44756 | O69: 44757 | P69: 321 | Q69: 46134 | R69: 3451.23 | S69: 0 | T69: -3451.23 | X69: UNPAID
A70: 23S-127 | B70: C000015869 | C70: R049 | D70: I.S. 49 - STATEN ISLAND | E70: 1212835 | F70: 90300 | G70: CIP | H70: Bracamonte, Jesus | I70: PO 18 Asbestos Service | J70: Initial | K70: Initial | L70: 45300 | M70: 3100 | S70: 0 | T70: 0 | X70: NOT BILLED
A71: 23S-074 | B71: C000015869 | C71: R053 | D71: P.S. 53 - STATEN ISLAND | E71: 1189854 | F71: 88746 | G71: CIP | H71: Bracamonte, Jesus | I71: PO 18 Asbestos Service | J71: Initial | K71: Closed | L71: 45145 | M71: 575 | S71: 0 | T71: 0 | X71: NOT BILLED
B72: C000015869 | C72: R055 | D72: P.S. 55 - STATEN ISLAND | E72: 1311249 | F72: 93283 | G72: CIP | H72: Bracamonte, Jesus | I72: PO 18 Asbestos Service | J72: Initial | K72: Initial | L72: 45549 | M72: 4000 | S72: 0 | T72: 0 | X72: NOT BILLED
A73: 23S-056 | B73: C000015869 | C73: R455 | D73: TOTTENVILLE HS - STATEN ISLAND | E73: 1187909 | F73: 88731 | G73: CIP | H73: Bracamonte, Jesus | I73: PO 18 Asbestos Service | J73: Initial | K73: Closed | L73: 45120 | M73: 7875 | N73: 45120 | O73: 45121 | P73: 224 | Q73: 45845 | R73: 2628.23 | S73: 2628.23 | T73: 0 | U73: 700000530 | V73: 45876 | X73: PAID
A74: 24S-077 | B74: C000015869 | C74: R455 | D74: TOTTENVILLE HS - STATEN ISLAND | E74: 1304791 | F74: 92921 | G74: CIP | H74: Bracamonte, Jesus | I74: Special Program | J74: Initial | K74: Closed | L74: 45514 | M74: 4000 | N74: 45514 | O74: 45515 | P74: 327 | Q74: 46175 | R74: 2774.69 | S74: 0 | T74: -2774.69 | X74: UNPAID
A75: 24S-057 | B75: C000015869 | C75: X005 | D75: P.S. 5 - BRONX | E75: 1243687 | F75: 92195 | G75: CIP | H75: Bracamonte, Jesus | I75: LAP Construction Phase Services | J75: Initial | K75: Initial | L75: 45471 | M75: 16700 | S75: 0 | T75: 0 | X75: NOT BILLED
A76: 25S-011 | B76: C000015869 | C76: X030 | D76: P.S. 30 - BRONX | E76: 1335264 | F76: 94772 | G76: CIP | H76: Alawamleh, Eman | I76: PO 18 Asbestos Service | J76: Initial | K76: WIP | L76: 45702 | M76: 575 | S76: 0 | T76: 0 | X76: NOT BILLED
A77: 23S-025 | B77: C000015869 | C77: X041 | D77: P.S. 41 - BRONX | E77: 1174668 | F77: 87890 | G77: CIP | H77: Kowalski, Zbigniew | I77: PO 18 Asbestos Service | J77: Initial | K77: WIP | L77: 45027 | M77: 575 | S77: 0 | T77: 0 | X77: NOT BILLED
A78: 24S-044 | B78: C000015869 | C78: X074 | D78: I.S. 201 - BRONX | E78: 1234316 | F78: 91863 | G78: CIP | I78: LAP Construction Phase Services | J78: Initial | K78: Initial | L78: 45440 | M78: 300 | S78: 0 | T78: 0 | X78: NOT BILLED
B79: C000015869 | C79: X102 | D79: P.S. 102 - BRONX | E79: 1328013 | F79: 93969 | G79: CIP | H79: Bracamonte, Jesus | I79: LAP Construction Phase Services | J79: Initial | K79: Initial | L79: 45652 | M79: 15045 | S79: 0 | T79: 0 | X79: NOT BILLED
A80: 25S-010 | B80: C000015869 | C80: X107 | D80: I.S. 107 - BRONX | E80: 1334935 | F80: 94758 | G80: CIP | H80: Bracamonte, Jesus | I80: PO 18 Asbestos Service | J80: Initial | K80: Closed | L80: 45695 | M80: 39440.45 | N80: 45696 | O80: 45760 | P80: 319 | Q80: 46100 | R80: 39440.45 | S80: 39440.45 | T80: 0 | U80: 700008136 | V80: 46166 | W80: 46177 | X80: PAID
B81: C000015869 | C81: X131 | D81: I.S. 131 - BRONX | E81: 1335358 | F81: 94778 | G81: CIP | H81: Alawamleh, Eman | I81: PO 18 Asbestos Service | J81: Initial | K81: Initial | L81: 45702 | M81: 575 | S81: 0 | T81: 0 | X81: NOT BILLED
A82: 24S-118 | B82: C000015869 | C82: X139 | D82: J.H.S. 222 - BRONX | E82: 1318133 | F82: 93742 | G82: CIP | H82: Alawamleh, Eman | I82: PO 18 Asbestos Service | J82: Initial | K82: WIP | L82: 45590 | M82: 575 | S82: 0 | T82: 0 | X82: NOT BILLED
A83: 24S-058 | B83: C000015869 | C83: X149 | D83: J.H.S. 149 - BRONX | E83: 1243686 | F83: 92199 | G83: CIP | I83: LAP Construction Phase Services | J83: Initial | K83: Initial | L83: 45471 | M83: 16700 | S83: 0 | T83: 0 | X83: NOT BILLED
B84: C000015869 | C84: X161 | D84: P.S. 161 - BRONX | E84: 1335270 | F84: 94786 | G84: CIP | H84: Alawamleh, Eman | I84: PO 18 Asbestos Service | J84: Initial | K84: Initial | L84: 45707 | M84: 575 | S84: 0 | T84: 0 | X84: NOT BILLED
A85: 23S-041 | B85: C000015869 | C85: X807 | D85: DISTRICT OFFICE #7 (OLD 18) - BRONX | E85: 1180607 | F85: 88248 | G85: CIP | H85: Alawamleh, Eman | I85: PO 18 Asbestos Service | J85: Initial | K85: Closed | L85: 45070 | M85: 575 | N85: 46176 | O85: 46176 | P85: 328 | Q85: 46176 | R85: 575 | S85: 0 | T85: -575 | X85: UNPAID
B86: C000016435 | C86: K003 | D86: P.S. 3 - BROOKLYN | E86: 1397879 | F86: 99056 | G86: CIP | H86: Walsh, Joseph | I86: PO 18 Asbestos Service | J86: Initial | K86: Initial WA Pending Receipt | L86: 46108 | M86: 750 | S86: 0 | T86: 0 | X86: NOT BILLED
B87: C000016435 | C87: K017 | D87: P.S. 17 - BROOKLYN | E87: 1396615 | F87: 98657 | G87: CIP | H87: Walsh, Joseph | I87: LAP Construction Phase Services | J87: Initial | K87: Initial WA Pending Receipt | L87: 46098 | M87: 10625 | S87: 0 | T87: 0 | X87: NOT BILLED
B88: C000016435 | C88: K019 | D88: P.S. 19 - BROOKLYN | E88: 1374797 | F88: 89478 | G88: CIP | H88: Walsh, Joseph | I88: LAP Construction Phase Services | J88: Initial | K88: Initial WA Pending Receipt | L88: 45958 | M88: 14000 | S88: 0 | T88: 0 | X88: NOT BILLED
B89: C000016435 | C89: K021 | D89: P.S. 21 - BROOKLYN | E89: 1389071 | F89: 98256 | G89: CIP | H89: Walsh, Joseph | I89: PO 18 Asbestos Service | J89: Initial | K89: WIP | L89: 46050 | M89: 750 | S89: 0 | T89: 0 | X89: NOT BILLED
B90: C000016435 | C90: K035 | D90: I.S. 35 - BROOKLYN | E90: 966244 | F90: 67252 | G90: CIP | H90: Palermo, Albert | I90: LAP Construction Phase Services | J90: Initial | K90: WIP | L90: 43556 | M90: 400 | S90: 0 | T90: 0 | X90: NOT BILLED
B91: C000016435 | C91: K050 | D91: J.H.S. 50 - BROOKLYN | E91: 1384012 | F91: 98005 | G91: CIP | H91: Bracamonte, Jesus | I91: LAP Construction Phase Services | J91: Initial | K91: Initial | L91: 46014 | M91: 16750 | S91: 0 | T91: 0 | X91: NOT BILLED
B92: C000016435 | C92: K073 | D92: P.S. 73 - BROOKLYN | E92: 982504 | F92: 73112 | G92: CIP | H92: Palermo, Albert | I92: LAP Construction Phase Services | J92: Initial | K92: Initial WA Pending Receipt | L92: 43682 | M92: 1500 | S92: 0 | T92: 0 | X92: NOT BILLED
B93: C000016435 | C93: K094 | D93: P.S. 94 - BROOKLYN | E93: 1393069 | F93: 98692 | G93: CIP | I93: LAP Construction Phase Services | J93: Initial | K93: Initial | L93: 46077 | M93: 20000 | S93: 0 | T93: 0 | X93: NOT BILLED
B94: C000016435 | C94: K096 | D94: I.S. 96 - BROOKLYN | E94: 1361937 | F94: 96671 | G94: CIP | H94: Bracamonte, Jesus | I94: LAP Construction Phase Services | J94: Initial | K94: Initial | L94: 45884 | M94: 12175 | S94: 0 | T94: 0 | X94: NOT BILLED
B95: C000016435 | C95: K099 | D95: P.S. 99 - BROOKLYN | E95: 1378091 | F95: 97786 | G95: CIP | H95: Clyne, Sean | I95: PO 18 Asbestos Service | J95: Amendment | K95: Amended WA Pending Receipt | L95: 45993 | M95: 750 | S95: 0 | T95: 0 | X95: NOT BILLED
B96: C000016435 | C96: K102 | D96: P.S. 102 - BROOKLYN | E96: 975973 | F96: 72589 | G96: CIP | H96: Kholodenko, Aleksandr | I96: LAP Scope Review & Survey | J96: Initial | K96: Initial WA Pending Receipt | L96: 43629 | M96: 3800 | S96: 0 | T96: 0 | X96: NOT BILLED
B97: C000016435 | C97: K104 | D97: P.S. 104 - BROOKLYN | E97: 1196914 | F97: 89231 | G97: CIP | H97: Scott, Richard | I97: PO 18 Asbestos Service | J97: Initial | K97: WIP | L97: 45195 | M97: 575 | S97: 0 | T97: 0 | X97: NOT BILLED
A98: 23S-105 | B98: C000016435 | C98: K114 | D98: P.S. 114 - BROOKLYN | E98: 1368511 | F98: 88538 | G98: CIP | H98: Bracamonte, Jesus | I98: LAP Construction Phase Services | J98: Initial | K98: Closed | L98: 45786 | M98: 4500 | N98: 45786 | O98: 45787 | P98: 3 | Q98: 46170 | R98: 2422.5 | S98: 0 | T98: -2422.5 | X98: UNPAID
B99: C000016435 | C99: K116 | D99: P.S. 116 - BROOKLYN | E99: 1400527 | F99: 99254 | G99: CIP | H99: Walsh, Joseph | I99: LAP Construction Phase Services | J99: Initial | K99: Initial WA Pending Receipt | L99: 46126 | M99: 70000 | S99: 0 | T99: 0 | X99: NOT BILLED
B100: C000016435 | C100: K124 | D100: P.S. 124 - BROOKLYN | E100: 1320374 | F100: 93864 | G100: CIP | H100: Bracamonte, Jesus | I100: LAP Construction Phase Services | J100: Initial | K100: WIP | L100: 45604 | M100: 22700 | S100: 0 | T100: 0 | X100: NOT BILLED
...

Sheet stg_job_list
A1: JOBID | B1: BID | C1: Description | D1: ServiceID | E1: Project_ID | F1: ContractNo | G1: SAI_Job_Status
A2: 22S-029 | B2: K014 | C2: LAP Construction Phase Services | D2: 85451 | E2: P026159 | F2: C000015869 | G2: Complete
A3: 22S-079 | B3: Q189 | C3: PO 18 Asbestos Service | D3: 86933 | E3: 133460 | F3: C000015869 | G3: Complete
A4: 23S-056 | B4: R445 | C4: PO 18 Asbestos Service | D4: 88731 | E4: 135678 | F4: C000015869 | G4: Complete
A5: 24S-114 | B5: M180 | C5: PO 18 Asbestos Service | D5: 93632 | E5: 141149 | F5: C000015869 | G5: Complete
A6: 25S-010 | B6: X107 | C6: PO 18 Asbestos Service | D6: 94758 | E6: 141770 | F6: C000015869 | G6: Complete

Sheet stg_payroll
A1: EMPLOYEE_NAME | B1: CODE | C1: HOURLY RATE | D1: DATE ON CHECK | E1: DATE WORKED | F1: WEEK ENDING DATE | G1: HOURS WORKED | H1: JOBID | I1: BUILDING LOCATION | J1: EXPENSES | K1: JOB TYPE | L1: LegacyEmpKey
A2: Igor Groysman | B2: 1 | C2: 38 | D2: 44961 | E2: 44910 | F2: 44912 | G2: 6.5 | H2: 22S-079 | I2: Q089 | K2: SCA | L2: =LOWER(SUBSTITUTE(stg_payroll!$A2," ","") & TEXT(stg_payroll!$B2,"00")) -> igorgroysman01
A3: Igor Groysman | B3: 1 | C3: 38 | D3: 44961 | E3: 44911 | F3: 44912 | G3: 4.5 | H3: 22S-079 | I3: Q089 | K3: SCA | L3: =LOWER(SUBSTITUTE(stg_payroll!$A3," ","") & TEXT(stg_payroll!$B3,"00")) -> igorgroysman01
A4: Ricardo Vilchez | B4: 1 | C4: 38 | D4: 45129 | E4: 45120 | F4: 45122 | G4: 11 | H4: 23S-056 | I4: R455 | J4: 6.55 | K4: SCA | L4: =LOWER(SUBSTITUTE(stg_payroll!$A4," ","") & TEXT(stg_payroll!$B4,"00")) -> ricardovilchez01
A5: Cornel Albu | B5: 1 | C5: 38 | D5: 45597 | E5: 45583 | F5: 45584 | G5: 7.5 | H5: 24S-114 | I5: M180 | K5: SCA | L5: =LOWER(SUBSTITUTE(stg_payroll!$A5," ","") & TEXT(stg_payroll!$B5,"00")) -> cornelalbu01
A6: Cornel Albu | B6: 1 | C6: 38 | D6: 45597 | E6: 45584 | F6: 45584 | G6: 18.5 | H6: 24S-114 | I6: M180 | K6: SCA | L6: =LOWER(SUBSTITUTE(stg_payroll!$A6," ","") & TEXT(stg_payroll!$B6,"00")) -> cornelalbu01
A7: Cornel Albu | B7: 3 | C7: 45 | D7: 45717 | E7: 45698 | F7: 45703 | G7: 9 | H7: 25S-010 | I7: X107 | K7: SCA | L7: =LOWER(SUBSTITUTE(stg_payroll!$A7," ","") & TEXT(stg_payroll!$B7,"00")) -> cornelalbu03
A8: Cornel Albu | B8: 1 | C8: 38 | D8: 45759 | E8: 45743 | F8: 45745 | G8: 5 | H8: 25S-010 | I8: X107 | K8: SCA | L8: =LOWER(SUBSTITUTE(stg_payroll!$A8," ","") & TEXT(stg_payroll!$B8,"00")) -> cornelalbu01
A9: Cornel Albu | B9: 1 | C9: 38 | D9: 45759 | E9: 45744 | F9: 45745 | G9: 6.5 | H9: 25S-010 | I9: X107 | K9: SCA | L9: =LOWER(SUBSTITUTE(stg_payroll!$A9," ","") & TEXT(stg_payroll!$B9,"00")) -> cornelalbu01
A10: Cornel Albu | B10: 1 | C10: 38 | D10: 45759 | E10: 45745 | F10: 45745 | G10: 21 | H10: 25S-010 | I10: X107 | J10: 27.76 | K10: SCA | L10: =LOWER(SUBSTITUTE(stg_payroll!$A10," ","") & TEXT(stg_payroll!$B10,"00")) -> cornelalbu01
A11: Cornel Albu | B11: 1 | C11: 38 | D11: 45759 | E11: 45750 | F11: 45752 | G11: 6 | H11: 25S-010 | I11: X107 | K11: SCA | L11: =LOWER(SUBSTITUTE(stg_payroll!$A11," ","") & TEXT(stg_payroll!$B11,"00")) -> cornelalbu01
A12: Cornel Albu | B12: 1 | C12: 38 | D12: 45759 | E12: 45751 | F12: 45752 | G12: 6.5 | H12: 25S-010 | I12: X107 | K12: SCA | L12: =LOWER(SUBSTITUTE(stg_payroll!$A12," ","") & TEXT(stg_payroll!$B12,"00")) -> cornelalbu01
A13: Cornel Albu | B13: 1 | C13: 38 | D13: 45759 | E13: 45752 | F13: 45752 | G13: 20.5 | H13: 25S-010 | I13: X107 | J13: 34.7 | K13: SCA | L13: =LOWER(SUBSTITUTE(stg_payroll!$A13," ","") & TEXT(stg_payroll!$B13,"00")) -> cornelalbu01
A14: Soslan Lazarov | B14: 1 | C14: 33 | D14: 45780 | E14: 45744 | F14: 45745 | G14: 5 | H14: 25S-010 | I14: X107 | K14: SCA | L14: =LOWER(SUBSTITUTE(stg_payroll!$A14," ","") & TEXT(stg_payroll!$B14,"00")) -> soslanlazarov01
A15: Soslan Lazarov | B15: 1 | C15: 33 | D15: 45780 | E15: 45745 | F15: 45745 | G15: 14 | H15: 25S-010 | I15: X107 | K15: SCA | L15: =LOWER(SUBSTITUTE(stg_payroll!$A15," ","") & TEXT(stg_payroll!$B15,"00")) -> soslanlazarov01
A16: Soslan Lazarov | B16: 1 | C16: 33 | D16: 45780 | E16: 45746 | F16: 45752 | G16: 15 | H16: 25S-010 | I16: X107 | J16: 9 | K16: SCA | L16: =LOWER(SUBSTITUTE(stg_payroll!$A16," ","") & TEXT(stg_payroll!$B16,"00")) -> soslanlazarov01
A17: Soslan Lazarov | B17: 1 | C17: 33 | D17: 45780 | E17: 45752 | F17: 45752 | G17: 14 | H17: 25S-010 | I17: X107 | K17: SCA | L17: =LOWER(SUBSTITUTE(stg_payroll!$A17," ","") & TEXT(stg_payroll!$B17,"00")) -> soslanlazarov01
A18: Soslan Lazarov | B18: 1 | C18: 33 | D18: 45780 | E18: 45753 | F18: 45759 | G18: 15 | H18: 25S-010 | I18: X107 | J18: 9 | K18: SCA | L18: =LOWER(SUBSTITUTE(stg_payroll!$A18," ","") & TEXT(stg_payroll!$B18,"00")) -> soslanlazarov01
A19: Soslan Lazarov | B19: 1 | C19: 33 | D19: 45780 | E19: 45757 | F19: 45759 | G19: 5 | H19: 25S-010 | I19: X107 | K19: SCA | L19: =LOWER(SUBSTITUTE(stg_payroll!$A19," ","") & TEXT(stg_payroll!$B19,"00")) -> soslanlazarov01
A20: Soslan Lazarov | B20: 1 | C20: 33 | D20: 45780 | E20: 45758 | F20: 45759 | G20: 5.5 | H20: 25S-010 | I20: X107 | K20: SCA | L20: =LOWER(SUBSTITUTE(stg_payroll!$A20," ","") & TEXT(stg_payroll!$B20,"00")) -> soslanlazarov01
A21: Soslan Lazarov | B21: 1 | C21: 33 | D21: 45780 | E21: 45759 | F21: 45759 | G21: 16.5 | H21: 25S-010 | I21: X107 | K21: SCA | L21: =LOWER(SUBSTITUTE(stg_payroll!$A21," ","") & TEXT(stg_payroll!$B21,"00")) -> soslanlazarov01
A22: Leon Groysman | B22: 1 | C22: 30 | D22: 45800 | E22: 45696 | F22: 45696 | G22: 7.5 | H22: 25S-010 | I22: X107 | J22: 6.95 | K22: SCA | L22: =LOWER(SUBSTITUTE(stg_payroll!$A22," ","") & TEXT(stg_payroll!$B22,"00")) -> leongroysman01
A23: Leon Groysman | B23: 1 | C23: 30 | D23: 45800 | E23: 45697 | F23: 45703 | G23: 8.5 | H23: 25S-010 | I23: X107 | J23: 6.95 | K23: SCA | L23: =LOWER(SUBSTITUTE(stg_payroll!$A23," ","") & TEXT(stg_payroll!$B23,"00")) -> leongroysman01
A24: Leon Groysman | B24: 1 | C24: 35 | D24: 46073 | E24: 45759 | F24: 45759 | G24: 16.5 | H24: 25S-010 | I24: X107 | J24: 13.9 | K24: SCA | L24: =LOWER(SUBSTITUTE(stg_payroll!$A24," ","") & TEXT(stg_payroll!$B24,"00")) -> leongroysman01
A25: Leon Groysman | B25: 1 | C25: 35 | D25: 46073 | E25: 45760 | F25: 45766 | G25: 16 | H25: 25S-010 | I25: X107 | J25: 13.9 | K25: SCA | L25: =LOWER(SUBSTITUTE(stg_payroll!$A25," ","") & TEXT(stg_payroll!$B25,"00")) -> leongroysman01
A26: Cornel Albu | B26: 1 | C26: 38 | E26: 45675 | G26: 6 | H26: 25S-002 | I26: X475 | K26: SCA | L26: =LOWER(SUBSTITUTE(stg_payroll!$A26," ","") & TEXT(stg_payroll!$B26,"00")) -> cornelalbu01
A27: Cornel Albu | B27: 1 | C27: 38 | E27: 45676 | G27: 6.5 | H27: 25S-002 | I27: X475 | K27: SCA | L27: =LOWER(SUBSTITUTE(stg_payroll!$A27," ","") & TEXT(stg_payroll!$B27,"00")) -> cornelalbu01
A28: Igor Groysman | B28: 1 | C28: 38 | E28: 44757 | G28: 10.5 | H28: 22S-029 | I28: K014 | K28: SCA | L28: =LOWER(SUBSTITUTE(stg_payroll!$A28," ","") & TEXT(stg_payroll!$B28,"00")) -> igorgroysman01
A29: Dimitri Bellos | B29: 3 | C29: 89 | E29: 44749 | G29: 6 | H29: 22S-029 | I29: K014 | K29: SCA | L29: =LOWER(SUBSTITUTE(stg_payroll!$A29," ","") & TEXT(stg_payroll!$B29,"00")) -> dimitribellos03

Sheet stg_employees
A1: EmpKey | B1: Last Name | C1: First Name | D1: Full Name | E1: EmployeeID | F1: EmployeeType | G1: Is_Active
A2: 1 | B2: Bellos | C2: Vasili | D2: =stg_employees!$C2&" "&stg_employees!$B2 -> Vasili Bellos | E2: VBE01 | F2: Salary | G2: 1
A3: 2 | B3: Bellos | C3: Dimitri | D3: =stg_employees!$C3&" "&stg_employees!$B3 -> Dimitri Bellos | E3: DBE01 | F3: Salary | G3: 1
A4: 3 | B4: Dros | C4: Patricia | D4: =stg_employees!$C4&" "&stg_employees!$B4 -> Patricia Dros | E4: PDR01 | F4: Hourly | G4: 1
A5: 4 | B5: Albu | C5: Cornel | D5: =stg_employees!$C5&" "&stg_employees!$B5 -> Cornel Albu | E5: CAL01 | F5: Contracted | G5: 1
A6: 5 | B6: Ablitsova | C6: Marina | D6: =stg_employees!$C6&" "&stg_employees!$B6 -> Marina Ablitsova | E6: MAB01 | F6: Contracted | G6: 1
A7: 6 | B7: Ciobanu | C7: Tatiana | D7: =stg_employees!$C7&" "&stg_employees!$B7 -> Tatiana Ciobanu | E7: TCI01 | F7: Contracted | G7: 1
A8: 7 | B8: Hung | C8: ChiFei | D8: =stg_employees!$C8&" "&stg_employees!$B8 -> ChiFei Hung | E8: CFE01 | F8: Contracted | G8: 1
A9: 8 | B9: Hung | C9: JoiFei | D9: =stg_employees!$C9&" "&stg_employees!$B9 -> JoiFei Hung | E9: JFE01 | F9: Contracted | G9: 1
A10: 9 | B10: Groysman | C10: Leon | D10: =stg_employees!$C10&" "&stg_employees!$B10 -> Leon Groysman | E10: LGR01 | F10: Contracted | G10: 1
A11: 10 | B11: Groysman | C11: Igor | D11: =stg_employees!$C11&" "&stg_employees!$B11 -> Igor Groysman | E11: IGR01 | F11: Contracted | G11: 1
A12: 11 | B12: Vilchez | C12: Ricardo | D12: =stg_employees!$C12&" "&stg_employees!$B12 -> Ricardo Vilchez | E12: RVI01 | F12: Contracted | G12: 0
A13: 12 | B13: Lazarov | C13: Soslan | D13: =stg_employees!$C13&" "&stg_employees!$B13 -> Soslan Lazarov | E13: SLA01 | F13: Contracted | G13: 1
... A23: 22 | B23: Jintchveladze | C23: Avtandil | D23: =stg_employees!$C23&" "&stg_employees!$B23 -> Avtandil Jintchveladze | E23: AJI01 | F23: Contracted | G23: 0

Sheet stg_labor_codes
A1: LaborClassKey | B1: JobCode | C1: JobTitle
A2: 1 | B2: 1 | C2: Asbestos Project Monitor
A3: 2 | B3: 2 | C3: Asbestos Inspector
A4: 3 | B4: 3 | C4: Asbestos Investigator
A5: 4 | B5: 4 | C5: Asbestos Project Designer
A6: 5 | B6: 5 | C6: Asbestos Project Manager
A7: 6 | B7: 6 | C7: Lead Inspector
A8: 7 | B8: 7 | C8: Lead Inspector/Risk Assessor
A9: 8 | B9: 8 | C9: Mold Inspector

Sheet stg_emp_rate_history
A1: LegacyEmpKey | B1: EmpName | C1: JobCode | D1: JobTitle | E1: ExpTier | F1: Rate_StartDate | G1: Rate_EndDate | H1: Rate
A2: adeniyiadeniran01 | B2: Adeniyi Adeniran | C2: 1 | D2: Asbestos Project Monitor | E2: 3 | F2: 45183 | G2: 45207 | H2: 33
A3: aleksandrgasis01 | B3: Aleksandr Gasis | C3: 1 | D3: Asbestos Project Monitor | E3: 3 | F3: 45536 | G3: =TODAY()+1 -> 46208 | H3: 38
A4: aleksandrtsvayg01 | B4: Aleksandr Tsvayg | C4: 1 | D4: Asbestos Project Monitor | E4: 3 | F4: 43466 | G4: 46124 | H4: 33
A5: aleksandrtsvayg01 | B5: Aleksandr Tsvayg | C5: 1 | D5: Asbestos Project Monitor | E5: 3 | F5: 46125 | G5: =TODAY()+1 -> 46208 | H5: 38
A6: chifeihung01 | B6: Chi Fei Hung | C6: 1 | D6: Asbestos Project Monitor | E6: 7 | F6: 43466 | G6: 46124 | H6: 38
A7: chifeihung02 | B7: Chi Fei Hung | C7: 2 | D7: Asbestos On Site Technical Air Testing | E7: 7 | F7: 43466 | G7: 46124 | H7: 38
A8: cornelalbu01 | B8: Cornel Albu | C8: 1 | D8: Asbestos Project Monitor | E8: 7 | F8: 43466 | G8: 46124 | H8: 38
A9: cornelalbu03 | B9: Cornel Albu | C9: 3 | D9: Asbestos Investigator | E9: 7 | F9: 43466 | G9: 46124 | H9: 45
A10: cornelalbu05 | B10: Cornel Albu | C10: 5 | D10: Asbestos Project Manager | E10: 7 | F10: 43466 | G10: =TODAY()+1 -> 46208 | H10: 45
A11: igorgroysman01 | B11: Igor Groysman | C11: 1 | D11: Asbestos Project Monitor | E11: 7 | F11: 43466 | G11: 46124 | H11: 38
A12: igorgroysman03 | B12: Igor Groysman | C12: 3 | D12: Asbestos Investigator | E12: 7 | F12: 43466 | G12: 46124 | H12: 45
A13: igorgroysman02 | B13: Igor Groysman | C13: 2 | D13: Asbestos On Site Technical Air Testing | E13: 7 | F13: 43466 | G13: 46124 | H13: 45
A14: ishahasan03 | B14: Isha Hasan | C14: 3 | D14: Asbestos Investigator | E14: 3 | F14: 43466 | G14: =TODAY()+1 -> 46208 | H14: 35
A15: joifeihung01 | B15: Joi Fei Hung | C15: 1 | D15: Asbestos Project Monitor | E15: 7 | F15: 43466 | G15: 46124 | H15: 38
A16: leongroysman01 | B16: Leon Groysman | C16: 1 | D16: Asbestos Project Monitor | E16: 3 | F16: 43466 | G16: 45864 | H16: 30
A17: leongroysman03 | B17: Leon Groysman | C17: 3 | D17: Asbestos Investigator | E17: 3 | F17: 43466 | G17: 45864 | H17: 30
A18: leongroysman03 | B18: Leon Groysman | C18: 3 | D18: Asbestos Investigator | E18: 3 | F18: 45865 | G18: 46124 | H18: 35
A19: leongroysman01 | B19: Leon Groysman | C19: 1 | D19: Asbestos Project Monitor | E19: 3 | F19: 45865 | G19: 46124 | H19: 35
A20: marinaablitsova01 | B20: Marina Ablitsova | C20: 1 | D20: Asbestos Project Monitor | E20: 3 | F20: 43466 | G20: 46124 | H20: 35
A21: maryanskira01 | B21: Maryan Skira | C21: 1 | D21: Asbestos Project Monitor | E21: 3 | F21: 43466 | G21: 46124 | H21: 35
A22: ricardovilchez06 | B22: Ricardo Vilchez | C22: 6 | D22: Lead Inspector | E22: 7 | F22: 43466 | G22: 45488 | H22: 45
A23: ricardovilchez01 | B23: Ricardo Vilchez | C23: 1 | D23: Asbestos Project Monitor | E23: 7 | F23: 43466 | G23: 45488 | H23: 38
A24: ricardovilchez02 | B24: Ricardo Vilchez | C24: 2 | D24: Asbestos On Site Technical Air Testing | E24: 7 | F24: 43466 | G24: 45488 | H24: 45
A25: ricardovilchez03 | B25: Ricardo Vilchez | C25: 3 | D25: Asbestos Investigator | E25: 7 | F25: 43466 | G25: 45488 | H25: 45
A26: shalvasagihashvili01 | B26: Shalva Sagihashvili | C26: 1 | D26: Asbestos Project Monitor | E26: 3 | F26: 44896 | G26: 45076 | H26: 38
... A28: tatianaciobanu01 | B28: Tatiana Ciobanu | C28: 1 | D28: Asbestos Project Monitor | E28: 3 | F28: 43466 | G28: 46124 | H28: 33
A29: tatianaciobanu01 | B29: Tatiana Ciobanu | C29: 1 | D29: Asbestos Project Monitor | E29: 7 | F29: 46125 | G29: =TODAY()+1 -> 46208 | H29: 38
A30: zviadinebieridze01 | B30: Zviadi Nebieridze | C30: 1 | D30: Asbestos Project Monitor | E30: 3 | F30: 43466 | G30: 46124 | H30: 33
A31: chifeihung01 | B31: Chi Fei Hung | C31: 1 | D31: Asbestos Project Monitor | E31: 7 | F31: 46125 | G31: =TODAY()+1 -> 46208 | H31: 42
A32: chifeihung02 | B32: Chi Fei Hung | C32: 2 | D32: Asbestos On Site Technical Air Testing | E32: 7 | F32: 46125 | G32: =TODAY()+1 -> 46208 | H32: 42
A33: cornelalbu01 | B33: Cornel Albu | C33: 1 | D33: Asbestos Project Monitor | E33: 7 | F33: 46125 | G33: =TODAY()+1 -> 46208 | H33: 42
A34: cornelalbu05 | B34: Cornel Albu | C34: 5 | D34: Asbestos Project Manager | E34: 7 | F34: 45658 | G34: =TODAY()+1 -> 46208 | H34: 45
A35: cornelalbu03 | B35: Cornel Albu | C35: 3 | D35: Asbestos Investigator | E35: 7 | F35: 46125 | G35: =TODAY()+1 -> 46208 | H35: 50
A36: ishahasan03 | B36: Isha Hasan | C36: 3 | D36: Asbestos Investigator | E36: 3 | F36: 43466 | G36: =TODAY()+1 -> 46208 | H36: 35
A37: igorgroysman01 | B37: Igor Groysman | C37: 1 | D37: Asbestos Project Monitor | E37: 7 | F37: 46125 | G37: =TODAY()+1 -> 46208 | H37: 42
A38: igorgroysman03 | B38: Igor Groysman | C38: 3 | D38: Asbestos Investigator | E38: 7 | F38: 46125 | G38: =TODAY()+1 -> 46208 | H38: 55
A39: igorgroysman02 | B39: Igor Groysman | C39: 2 | D39: Asbestos On Site Technical Air Testing | E39: 7 | F39: 46125 | G39: =TODAY()+1 -> 46208 | H39: 55
A40: joifeihung01 | B40: Joi Fei Hung | C40: 1 | D40: Asbestos Project Monitor | E40: 7 | F40: 46125 | G40: =TODAY()+1 -> 46208 | H40: 42
A41: leongroysman03 | B41: Leon Groysman | C41: 3 | D41: Asbestos Investigator | E41: 3 | F41: 46125 | G41: =TODAY()+1 -> 46208 | H41: 38
A42: leongroysman01 | B42: Leon Groysman | C42: 1 | D42: Asbestos Project Monitor | E42: 3 | F42: 46125 | G42: =TODAY()+1 -> 46208 | H42: 38
... A46: zviadinebieridze01 | B46: Zviadi Nebieridze | C46: 1 | D46: Asbestos Project Monitor | E46: 3 | F46: 46125 | G46: =TODAY()+1 -> 46208 | H46: 35
A47: vasilisbellos01 | B47: Vasilis Bellos | C47: 3 | D47: Asbestos Investigator | E47: 7 | F47: 43466 | G47: 46124 | H47: 89
A48: vasilisbellos03 | B48: Vasilis Bellos | C48: 3 | D48: Asbestos Investigator | E48: 7 | F48: 46125 | G48: =TODAY()+1 -> 46208 | H48: 89
A49: vasilisbellos03 | B49: Vasilis Bellos | C49: 3 | D49: Asbestos Investigator | E49: 7 | F49: 43466 | G49: 46124 | H49: 89
A50: vasilisbellos03 | B50: Vasilis Bellos | C50: 3 | D50: Asbestos Investigator | E50: 7 | F50: 46125 | G50: =TODAY()+1 -> 46208 | H50: 89
A51: vasilisbellos07 | B51: Vasilis Bellos | C51: 7 | D51: Lead Inspector/Risk Assessor | E51: 7 | F51: 43466 | G51: 46124 | H51: 89
A52: vasilisbellos07 | B52: Vasilis Bellos | C52: 7 | D52: Lead Inspector/Risk Assessor | E52: 7 | F52: 46125 | G52: =TODAY()+1 -> 46208 | H52: 89
A53: dimitribellos01 | B53: Dimitri Bellos | C53: 1 | D53: Asbestos Project Monitor | E53: 7 | F53: 43466 | G53: 46124 | H53: 89
A54: dimitribellos01 | B54: Dimitri Bellos | C54: 1 | D54: Asbestos Project Monitor | E54: 7 | F54: 46125 | G54: =TODAY()+1 -> 46208 | H54: 89
A55: dimitribellos03 | B55: Dimitri Bellos | C55: 3 | D55: Asbestos Investigator | E55: 7 | F55: 43466 | G55: 46124 | H55: 89
A56: patriciadros00 | B56: Patricia Dros | C56: 0 | D56: Admin | E56: 3 | F56: 44896 | G56: =TODAY()+1 -> 46208 | H56: 28

Sheet stg_lab_reports
A1: CLIENT_TYPE | B1: BID | C1: JOB_NO | D1: DATE OF REPORT | E1: BATCH NO | F1: SAMPLE TYPE | G1: QUANTITY | H1: TECHNICIAN | I1: FACILITY
A2: SCA | B2: X107 | C2: 25S-010 | D2: 45696 | E2: 25-02-233 | F2: Durings | G2: 4 | H2: Leon Groysman | I2: LTS
A3: SCA | B3: X107 | C3: 25S-010 | D3: 45696 | E3: 25-02-234 | F3: Finals | G3: 8 | H3: Leon Groysman | I3: LTS
A4: SCA | B4: X107 | C4: 25S-010 | D4: 45743 | E4: 25-03-812 | F4: Backgrounds | G4: 12 | H4: Cornel Albu | I4: LTS
A5: SCA | B5: X107 | C5: 25S-010 | D5: 45744 | E5: 25-03-908 | F5: Backgrounds | G5: 12 | H5: Soslan Lazarov | I5: LTS
A6: SCA | B6: X107 | C6: 25S-010 | D6: 45744 | E6: 25-03-871 | F6: Pre | G6: 12 | H6: Cornel Albu | I6: LTS
A7: SCA | B7: X107 | C7: 25S-010 | D7: 45744 | E7: 25-03-872 | F7: Durings | G7: 18 | H7: Cornel Albu | I7: LTS
A8: SCA | B8: X107 | C8: 25S-010 | D8: 45745 | E8: 25-03-909 | F8: Pre | G8: 12 | H8: Soslan Lazarov | I8: LTS
A9: SCA | B9: X107 | C9: 25S-010 | D9: 45745 | E9: 25-03-910 | F9: Durings | G9: 9 | H9: Soslan Lazarov | I9: LTS
A10: SCA | B10: X107 | C10: 25S-010 | D10: 45745 | E10: 25-03-873 | F10: Finals | G10: 12 | H10: Cornel Albu | I10: LTS
A11: SCA | B11: X107 | C11: 25S-010 | D11: 45745 | E11: 25-03-911 | F11: Finals | G11: 12 | H11: Soslan Lazarov | I11: LTS
A12: SCA | B12: X107 | C12: 25S-010 | D12: 45750 | E12: 25-04-082 | F12: Backgrounds | G12: 12 | H12: Cornel Albu | I12: LTS
A13: SCA | B13: X107 | C13: 25S-010 | D13: 45750 | E13: 25-04-081 | F13: Backgrounds | G13: 12 | H13: Cornel Albu | I13: LTS
... A38: SCA | B38: K014 | C38: 22S-029 | D38: 44757 | E38: 220715-32 | F38: DAF | G38: 7 | H38: Igor Groysman | I38: ALLAB

Sheet dim_date
A1: FullDate | B1: DateKey | C1: DayName | D1: MonthName | E1: Quarter | F1: Year | G1: WeekEndingDate | H1: WeekdayFlag
A2: =DATE(2019,1,1) -> 43466 | B2: =TEXT(A2,"yyyymmdd") -> 20190101 | C2: =TEXT(A2,"dddd") -> Tuesday | D2: =TEXT(A2,"mmmm") -> January | E2: ="Q"&ROUNDUP(MONTH(A2)/3,0) -> Q1 | F2: =YEAR(A2) -> 2019 | G2: =A2+(7-WEEKDAY(A2,1)) -> 43470 | H2: =IF(OR(TEXT(A2,"dddd")="Saturday",TEXT(A2,"dddd")="Sunday"),"No","Yes") -> Yes
A3: =A2+1 -> 43467 | B3: =TEXT(A3,"yyyymmdd") -> 20190102 | C3: =TEXT(A3,"dddd") -> Wednesday | D3: =TEXT(A3,"mmmm") -> January | E3: ="Q"&ROUNDUP(MONTH(A3)/3,0) -> Q1 | F3: =YEAR(A3) -> 2019 | G3: =A3+(7-WEEKDAY(A3,1)) -> 43470 | H3: =IF(OR(TEXT(A3,"dddd")="Saturday",TEXT(A3,"dddd")="Sunday"),"No","Yes") -> Yes
A4: =A3+1 -> 43468 | B4: =TEXT(A4,"yyyymmdd") -> 20190103 | C4: =TEXT(A4,"dddd") -> Thursday | D4: =TEXT(A4,"mmmm") -> January | E4: ="Q"&ROUNDUP(MONTH(A4)/3,0) -> Q1 | F4: =YEAR(A4) -> 2019 | G4: =A4+(7-WEEKDAY(A4,1)) -> 43470 | H4: =IF(OR(TEXT(A4,"dddd")="Saturday",TEXT(A4,"dddd")="Sunday"),"No","Yes") -> Yes
A5: =A4+1 -> 43469 | B5: =TEXT(A5,"yyyymmdd") -> 20190104 | C5: =TEXT(A5,"dddd") -> Friday | D5: =TEXT(A5,"mmmm") -> January | E5: ="Q"&ROUNDUP(MONTH(A5)/3,0) -> Q1 | F5: =YEAR(A5) -> 2019 | G5: =A5+(7-WEEKDAY(A5,1)) -> 43470 | H5: =IF(OR(TEXT(A5,"dddd")="Saturday",TEXT(A5,"dddd")="Sunday"),"No","Yes") -> Yes
A6: =A5+1 -> 43470 | B6: =TEXT(A6,"yyyymmdd") -> 20190105 | C6: =TEXT(A6,"dddd") -> Saturday | D6: =TEXT(A6,"mmmm") -> January | E6: ="Q"&ROUNDUP(MONTH(A6)/3,0) -> Q1 | F6: =YEAR(A6) -> 2019 | G6: =A6+(7-WEEKDAY(A6,1)) -> 43470 | H6: =IF(OR(TEXT(A6,"dddd")="Saturday",TEXT(A6,"dddd")="Sunday"),"No","Yes") -> No
A7: =A6+1 -> 43471 | B7: =TEXT(A7,"yyyymmdd") -> 20190106 | C7: =TEXT(A7,"dddd") -> Sunday | D7: =TEXT(A7,"mmmm") -> January | E7: ="Q"&ROUNDUP(MONTH(A7)/3,0) -> Q1 | F7: =YEAR(A7) -> 2019 | G7: =A7+(7-WEEKDAY(A7,1)) -> 43477 | H7: =IF(OR(TEXT(A7,"dddd")="Saturday",TEXT(A7,"dddd")="Sunday"),"No","Yes") -> No
A8: =A7+1 -> 43472 | B8: =TEXT(A8,"yyyymmdd") -> 20190107 | C8: =TEXT(A8,"dddd") -> Monday | D8: =TEXT(A8,"mmmm") -> January | E8: ="Q"&ROUNDUP(MONTH(A8)/3,0) -> Q1 | F8: =YEAR(A8) -> 2019 | G8: =A8+(7-WEEKDAY(A8,1)) -> 43477 | H8: =IF(OR(TEXT(A8,"dddd")="Saturday",TEXT(A8,"dddd")="Sunday"),"No","Yes") -> Yes
A9: =A8+1 -> 43473 | B9: =TEXT(A9,"yyyymmdd") -> 20190108 | C9: =TEXT(A9,"dddd") -> Tuesday | D9: =TEXT(A9,"mmmm") -> January | E9: ="Q"&ROUNDUP(MONTH(A9)/3,0) -> Q1 | F9: =YEAR(A9) -> 2019 | G9: =A9+(7-WEEKDAY(A9,1)) -> 43477 | H9: =IF(OR(TEXT(A9,"dddd")="Saturday",TEXT(A9,"dddd")="Sunday"),"No","Yes") -> Yes
A10: =A9+1 -> 43474 | B10: =TEXT(A10,"yyyymmdd") -> 20190109 | C10: =TEXT(A10,"dddd") -> Wednesday | D10: =TEXT(A10,"mmmm") -> January | E10: ="Q"&ROUNDUP(MONTH(A10)/3,0) -> Q1 | F10: =YEAR(A10) -> 2019 | G10: =A10+(7-WEEKDAY(A10,1)) -> 43477 | H10: =IF(OR(TEXT(A10,"dddd")="Saturday",TEXT(A10,"dddd")="Sunday"),"No","Yes") -> Yes
A11: =A10+1 -> 43475 | B11: =TEXT(A11,"yyyymmdd") -> 20190110 | C11: =TEXT(A11,"dddd") -> Thursday | D11: =TEXT(A11,"mmmm") -> January | E11: ="Q"&ROUNDUP(MONTH(A11)/3,0) -> Q1 | F11: =YEAR(A11) -> 2019 | G11: =A11+(7-WEEKDAY(A11,1)) -> 43477 | H11: =IF(OR(TEXT(A11,"dddd")="Saturday",TEXT(A11,"dddd")="Sunday"),"No","Yes") -> Yes
A12: =A11+1 -> 43476 | B12: =TEXT(A12,"yyyymmdd") -> 20190111 | C12: =TEXT(A12,"dddd") -> Friday | D12: =TEXT(A12,"mmmm") -> January | E12: ="Q"&ROUNDUP(MONTH(A12)/3,0) -> Q1 | F12: =YEAR(A12) -> 2019 | G12: =A12+(7-WEEKDAY(A12,1)) -> 43477 | H12: =IF(OR(TEXT(A12,"dddd")="Saturday",TEXT(A12,"dddd")="Sunday"),"No","Yes") -> Yes
A13: =A12+1 -> 43477 | B13: =TEXT(A13,"yyyymmdd") -> 20190112 | C13: =TEXT(A13,"dddd") -> Saturday | D13: =TEXT(A13,"mmmm") -> January | E13: ="Q"&ROUNDUP(MONTH(A13)/3,0) -> Q1 | F13: =YEAR(A13) -> 2019 | G13: =A13+(7-WEEKDAY(A13,1)) -> 43477 | H13: =IF(OR(TEXT(A13,"dddd")="Saturday",TEXT(A13,"dddd")="Sunday"),"No","Yes") -> No
A14: =A13+1 -> 43478 | B14: =TEXT(A14,"yyyymmdd") -> 20190113 | C14: =TEXT(A14,"dddd") -> Sunday | D14: =TEXT(A14,"mmmm") -> January | E14: ="Q"&ROUNDUP(MONTH(A14)/3,0) -> Q1 | F14: =YEAR(A14) -> 2019 | G14: =A14+(7-WEEKDAY(A14,1)) -> 43484 | H14: =IF(OR(TEXT(A14,"dddd")="Saturday",TEXT(A14,"dddd")="Sunday"),"No","Yes") -> No
... A2924: =A2923+1 -> 46388 | B2924: =TEXT(A2924,"yyyymmdd") -> 20270101 | C2924: =TEXT(A2924,"dddd") -> Friday | D2924: =TEXT(A2924,"mmmm") -> January | E2924: ="Q"&ROUNDUP(MONTH(A2924)/3,0) -> Q1 | F2924: =YEAR(A2924) -> 2027 | G2924: =A2924+(7-WEEKDAY(A2924,1)) -> 46389 | H2924: =IF(OR(TEXT(A2924,"dddd")="Saturday",TEXT(A2924,"dddd")="Sunday"),"No","Yes") -> Yes

Sheet dim_sai_rfp
A1: JobKey | B1: JobID | C1: ServiceID | D1: Contract_No | E1: SAI_RFP_No | F1: RFP_amount | G1: DateJobComplete | H1: RFP_Date
A2: 1 | B2: =stg_job_list!A2 -> 22S-029 | C2: =TRIM(stg_job_list!$D2) -> 85451 | D2: C000015869 | E2: 305 | F2: 3108.44 | G2: 44758 | H2: 46000
A3: 2 | B3: =stg_job_list!A3 -> 22S-079 | C3: =TRIM(stg_job_list!$D3) -> 86933 | D3: C000015869 | E3: 312 | F3: 1867.45 | G3: 44911 | H3: 46038
A4: 3 | B4: =stg_job_list!A4 -> 23S-056 | C4: =TRIM(stg_job_list!$D4) -> 88731 | D4: C000015869 | E4: 224 | F4: 2628.23 | G4: 45121 | H4: 45845
A5: 4 | B5: =stg_job_list!A5 -> 24S-114 | C5: =TRIM(stg_job_list!$D5) -> 93632 | D5: C000015869 | E5: 202 | F5: 4759.59 | G5: 45584 | H5: 45825
A6: 5 | B6: =stg_job_list!A6 -> 25S-010 | C6: =TRIM(stg_job_list!$D6) -> 94758 | D6: C000015869 | E6: 319 | F6: 39440.45 | G6: 45760 | H6: 46100

Sheet dim_job
A1: JobKey | B1: JobID | C1: BID | D1: Project_Description | E1: ServiceID | F1: Work_Auth_No | G1: PID | H1: Contract_No | I1: Initiation_Date | J1: Job_Status | K1: WA_Status
A2: 1 | B2: =stg_job_list!A2 -> 22S-029 | C2: =stg_job_list!$B2 -> K014 | D2: =stg_job_list!C2 -> LAP Construction Phase Services | E2: =stg_job_list!D2 -> 85451 | F2: 1229904 | G2: =stg_job_list!E2 -> P026159 | H2: =stg_job_list!F2 -> C000015869 | I2: 44749 | J2: =stg_job_list!G2 -> Complete | K2: Closed
A3: =A2+1 -> 2 | B3: =stg_job_list!A3 -> 22S-079 | C3: =stg_job_list!$B3 -> Q189 | D3: =stg_job_list!$C3 -> PO 18 Asbestos Service | E3: =stg_job_list!D3 -> 86933 | F3: 1157908 | G3: =stg_job_list!E3 -> 133460 | H3: =stg_job_list!F3 -> C000015869 | I3: 44910 | J3: =stg_job_list!G3 -> Complete | K3: Closed
A4: =A3+1 -> 3 | B4: =stg_job_list!A4 -> 23S-056 | C4: =stg_job_list!$B4 -> R445 | D4: =stg_job_list!$C4 -> PO 18 Asbestos Service | E4: =stg_job_list!D4 -> 88731 | F4: 1187909 | G4: =stg_job_list!E4 -> 135678 | H4: =stg_job_list!F4 -> C000015869 | I4: 45120 | J4: =stg_job_list!G4 -> Complete | K4: Closed
A5: =A4+1 -> 4 | B5: =stg_job_list!A5 -> 24S-114 | C5: =stg_job_list!$B5 -> M180 | D5: =stg_job_list!$C5 -> PO 18 Asbestos Service | E5: =stg_job_list!D5 -> 93632 | F5: 1315970 | G5: =stg_job_list!E5 -> 141149 | H5: =stg_job_list!F5 -> C000015869 | I5: 45575 | J5: =stg_job_list!G5 -> Complete | K5: Closed
A6: =A5+1 -> 5 | B6: =stg_job_list!A6 -> 25S-010 | C6: =stg_job_list!$B6 -> X107 | D6: =stg_job_list!$C6 -> PO 18 Asbestos Service | E6: =stg_job_list!D6 -> 94758 | F6: 1334935 | G6: =stg_job_list!E6 -> 141770 | H6: =stg_job_list!F6 -> C000015869 | I6: 45695 | J6: =stg_job_list!G6 -> Complete | K6: Closed

Sheet dim_labor_title
A1: LaborTitleKey | B1: Job_Code | C1: Job_Category | D1: Job_Title | E1: Title | F1: YearsExp | G1: Emp_YrsExp_Key
A2: 1 | B2: 1 | C2: Asbestos | D2: Project Monitor | E2: =dim_labor_title!$C2&" "&dim_labor_title!$D2 -> Asbestos Project Monitor | F2: 3 | G2: =dim_labor_title!$C2&" "&dim_labor_title!$D2&"|"&dim_labor_title!$F2 -> Asbestos Project Monitor|3
A3: 2 | B3: 2 | C3: Asbestos | D3: Air Testing | E3: =dim_labor_title!$C3&" "&dim_labor_title!$D3 -> Asbestos Air Testing | F3: 3 | G3: =dim_labor_title!$C3&" "&dim_labor_title!$D3&"|"&dim_labor_title!$F3 -> Asbestos Air Testing|3
A4: 3 | B4: 3 | C4: Asbestos | D4: Investigator | E4: =dim_labor_title!$C4&" "&dim_labor_title!$D4 -> Asbestos Investigator | F4: 3 | G4: =dim_labor_title!$C4&" "&dim_labor_title!$D4&"|"&dim_labor_title!$F4 -> Asbestos Investigator|3
A5: 4 | B5: 4 | C5: Asbestos | D5: Project Designer | E5: =dim_labor_title!$C5&" "&dim_labor_title!$D5 -> Asbestos Project Designer | F5: 3 | G5: =dim_labor_title!$C5&" "&dim_labor_title!$D5&"|"&dim_labor_title!$F5 -> Asbestos Project Designer|3
A6: 5 | B6: 5 | C6: Asbestos | D6: Project Manager | E6: =dim_labor_title!$C6&" "&dim_labor_title!$D6 -> Asbestos Project Manager | F6: 3 | G6: =dim_labor_title!$C6&" "&dim_labor_title!$D6&"|"&dim_labor_title!$F6 -> Asbestos Project Manager|3
A7: 6 | B7: 6 | C7: Lead | D7: Inspector | E7: =dim_labor_title!$C7&" "&dim_labor_title!$D7 -> Lead Inspector | F7: 3 | G7: =dim_labor_title!$C7&" "&dim_labor_title!$D7&"|"&dim_labor_title!$F7 -> Lead Inspector|3
A8: 7 | B8: 7 | C8: Lead | D8: Inspector / Risk Assessor | E8: =dim_labor_title!$C8&" "&dim_labor_title!$D8 -> Lead Inspector / Risk Assessor | F8: 3 | G8: =dim_labor_title!$C8&" "&dim_labor_title!$D8&"|"&dim_labor_title!$F8 -> Lead Inspector / Risk Assessor|3
A9: 8 | B9: 1 | C9: Asbestos | D9: Project Monitor | E9: =dim_labor_title!$C9&" "&dim_labor_title!$D9 -> Asbestos Project Monitor | F9: 7 | G9: =dim_labor_title!$C9&" "&dim_labor_title!$D9&"|"&dim_labor_title!$F9 -> Asbestos Project Monitor|7
A10: 9 | B10: 2 | C10: Asbestos | D10: Air Testing | E10: =dim_labor_title!$C10&" "&dim_labor_title!$D10 -> Asbestos Air Testing | F10: 7 | G10: =dim_labor_title!$C10&" "&dim_labor_title!$D10&"|"&dim_labor_title!$F10 -> Asbestos Air Testing|7
A11: 10 | B11: 3 | C11: Asbestos | D11: Investigator | E11: =dim_labor_title!$C11&" "&dim_labor_title!$D11 -> Asbestos Investigator | F11: 7 | G11: =dim_labor_title!$C11&" "&dim_labor_title!$D11&"|"&dim_labor_title!$F11 -> Asbestos Investigator|7
A12: 11 | B12: 4 | C12: Asbestos | D12: Project Designer | E12: =dim_labor_title!$C12&" "&dim_labor_title!$D12 -> Asbestos Project Designer | F12: 7 | G12: =dim_labor_title!$C12&" "&dim_labor_title!$D12&"|"&dim_labor_title!$F12 -> Asbestos Project Designer|7
A13: 12 | B13: 5 | C13: Asbestos | D13: Project Manager | E13: =dim_labor_title!$C13&" "&dim_labor_title!$D13 -> Asbestos Project Manager | F13: 7 | G13: =dim_labor_title!$C13&" "&dim_labor_title!$D13&"|"&dim_labor_title!$F13 -> Asbestos Project Manager|7
... A16: 15 | B16: 0 | C16: Office | D16: Admin | E16: =dim_labor_title!$C16&" "&dim_labor_title!$D16 -> Office Admin | F16: 3 | G16: =dim_labor_title!$C16&" "&dim_labor_title!$D16&"|"&dim_labor_title!$F16 -> Office Admin|3

Sheet dim_technician
A1: EmpIDKey | B1: Employee_Name | C1: First_Name | D1: Last_Name | E1: Job_Code | F1: SCA_Job_Title | G1: Yrs_Exp | H1: LegacyEmpKey
A2: 1 | B2: Cornel Albu | C2: Cornel | D2: Albu | E2: 1 | F2: {=XLOOKUP(dim_technician!$E2, dim_labor_title!$B$2:$B$16, dim_labor_title!$E$2:$E$16, "", 0)} -> Asbestos Project Monitor | G2: 7 | H2: =LOWER(dim_technician!$C2 & dim_technician!$D2 & TEXT(dim_technician!$E2, "00")) -> cornelalbu01
A3: 2 | B3: Cornel Albu | C3: Cornel | D3: Albu | E3: 2 | F3: {=XLOOKUP(dim_technician!$E3, dim_labor_title!$B$2:$B$16, dim_labor_title!$E$2:$E$16, "", 0)} -> Asbestos Air Testing | G3: 7 | H3: =LOWER(dim_technician!$C3 & dim_technician!$D3 & TEXT(dim_technician!$E3, "00")) -> cornelalbu02
A4: 3 | B4: Cornel Albu | C4: Cornel | D4: Albu | E4: 3 | F4: {=XLOOKUP(dim_technician!$E4, dim_labor_title!$B$2:$B$16, dim_labor_title!$E$2:$E$16, "", 0)} -> Asbestos Investigator | G4: 7 | H4: =LOWER(dim_technician!$C4 & dim_technician!$D4 & TEXT(dim_technician!$E4, "00")) -> cornelalbu03
A5: 4 | B5: Cornel Albu | C5: Cornel | D5: Albu | E5: 5 | F5: {=XLOOKUP(dim_technician!$E5, dim_labor_title!$B$2:$B$16, dim_labor_title!$E$2:$E$16, "", 0)} -> Asbestos Project Manager | G5: 7 | H5: =LOWER(dim_technician!$C5 & dim_technician!$D5 & TEXT(dim_technician!$E5, "00")) -> cornelalbu05
A6: 5 | B6: Marina Ablitsova | C6: Marina | D6: Ablitsova | E6: 1 | F6: {=XLOOKUP(dim_technician!$E6, dim_labor_title!$B$2:$B$16, dim_labor_title!$E$2:$E$16, "", 0)} -> Asbestos Project Monitor | G6: 3 | H6: =LOWER(dim_technician!$C6 & dim_technician!$D6 & TEXT(dim_technician!$E6, "00")) -> marinaablitsova01
A7: 6 | B7: Marina Ablitsova | C7: Marina | D7: Ablitsova | E7: 2 | F7: {=XLOOKUP(dim_technician!$E7, dim_labor_title!$B$2:$B$16, dim_labor_title!$E$2:$E$16, "", 0)} -> Asbestos Air Testing | G7: 3 | H7: =LOWER(dim_technician!$C7 & dim_technician!$D7 & TEXT(dim_technician!$E7, "00")) -> marinaablitsova02
A8: 7 | B8: Tatiana Ciobanu | C8: Tatiana | D8: Ciobanu | E8: 1 | F8: {=XLOOKUP(dim_technician!$E8, dim_labor_title!$B$2:$B$16, dim_labor_title!$E$2:$E$16, "", 0)} -> Asbestos Project Monitor | G8: 3 | H8: =LOWER(dim_technician!$C8 & dim_technician!$D8 & TEXT(dim_technician!$E8, "00")) -> tatianaciobanu01
A9: 8 | B9: Tatiana Ciobanu | C9: Tatiana | D9: Ciobanu | E9: 2 | F9: {=XLOOKUP(dim_technician!$E9, dim_labor_title!$B$2:$B$16, dim_labor_title!$E$2:$E$16, "", 0)} -> Asbestos Air Testing | G9: 3 | H9: =LOWER(dim_technician!$C9 & dim_technician!$D9 & TEXT(dim_technician!$E9, "00")) -> tatianaciobanu02
A10: 9 | B10: Chi Fei Hung | C10: ChiFei | D10: Hung | E10: 1 | F10: {=XLOOKUP(dim_technician!$E10, dim_labor_title!$B$2:$B$16, dim_labor_title!$E$2:$E$16, "", 0)} -> Asbestos Project Monitor | G10: 7 | H10: =LOWER(dim_technician!$C10 & dim_technician!$D10 & TEXT(dim_technician!$E10, "00")) -> chifeihung01
A11: 10 | B11: Chi Fei Hung | C11: ChiFei | D11: Hung | E11: 2 | F11: {=XLOOKUP(dim_technician!$E11, dim_labor_title!$B$2:$B$16, dim_labor_title!$E$2:$E$16, "", 0)} -> Asbestos Air Testing | G11: 7 | H11: =LOWER(dim_technician!$C11 & dim_technician!$D11 & TEXT(dim_technician!$E11, "00")) -> chifeihung02
A12: 11 | B12: Joi Fei Hung | C12: JoiFei | D12: Hung | E12: 1 | F12: {=XLOOKUP(dim_technician!$E12, dim_labor_title!$B$2:$B$16, dim_labor_title!$E$2:$E$16, "", 0)} -> Asbestos Project Monitor | G12: 7 | H12: =LOWER(dim_technician!$C12 & dim_technician!$D12 & TEXT(dim_technician!$E12, "00")) -> joifeihung01
A13: 12 | B13: Joi Fei Hung | C13: JoiFei | D13: Hung | E13: 2 | F13: {=XLOOKUP(dim_technician!$E13, dim_labor_title!$B$2:$B$16, dim_labor_title!$E$2:$E$16, "", 0)} -> Asbestos Air Testing | G13: 7 | H13: =LOWER(dim_technician!$C13 & dim_technician!$D13 & TEXT(dim_technician!$E13, "00")) -> joifeihung02
... A39: 38 | B39: Patricia Dros | C39: Patricia | D39: Dros | E39: 0 | F39: {=XLOOKUP(dim_technician!$E39, dim_labor_title!$B$2:$B$16, dim_labor_title!$E$2:$E$16, "", 0)} -> Office Admin | G39: 3 | H39: =LOWER(dim_technician!$C39 & dim_technician!$D39 & TEXT(dim_technician!$E39, "00")) -> patriciadros00

Sheet dim_emp_rate_history 
A1: EmpRateKey | B1: EmpKey | C1: Start_Date | D1: StartDateKey | E1: End_Date | F1: EndDateKey | G1: Hourly_Rate
B2: =TRIM(stg_emp_rate_history!$A2) -> adeniyiadeniran01 | C2: =stg_emp_rate_history!$F2 -> 45183 | D2: =TEXT(C2,"yyyymmdd") -> 20230914 | E2: =stg_emp_rate_history!$G2 -> 45207 | F2: =TEXT(E2,"yyyymmdd") -> 20231008 | G2: =stg_emp_rate_history!$H2 -> 33
B3: =TRIM(stg_emp_rate_history!$A3) -> aleksandrgasis01 | C3: =stg_emp_rate_history!$F3 -> 45536 | D3: =TEXT(C3,"yyyymmdd") -> 20240901 | E3: =stg_emp_rate_history!$G3 -> 46208 | F3: =TEXT(E3,"yyyymmdd") -> 20260705 | G3: =stg_emp_rate_history!$H3 -> 38
B4: =TRIM(stg_emp_rate_history!$A4) -> aleksandrtsvayg01 | C4: =stg_emp_rate_history!$F4 -> 43466 | D4: =TEXT(C4,"yyyymmdd") -> 20190101 | E4: =stg_emp_rate_history!$G4 -> 46124 | F4: =TEXT(E4,"yyyymmdd") -> 20260412 | G4: =stg_emp_rate_history!$H4 -> 33
B5: =TRIM(stg_emp_rate_history!$A5) -> aleksandrtsvayg01 | C5: =stg_emp_rate_history!$F5 -> 46125 | D5: =TEXT(C5,"yyyymmdd") -> 20260413 | E5: =stg_emp_rate_history!$G5 -> 46208 | F5: =TEXT(E5,"yyyymmdd") -> 20260705 | G5: =stg_emp_rate_history!$H5 -> 38
B6: =TRIM(stg_emp_rate_history!$A6) -> chifeihung01 | C6: =stg_emp_rate_history!$F6 -> 43466 | D6: =TEXT(C6,"yyyymmdd") -> 20190101 | E6: =stg_emp_rate_history!$G6 -> 46124 | F6: =TEXT(E6,"yyyymmdd") -> 20260412 | G6: =stg_emp_rate_history!$H6 -> 38
B7: =TRIM(stg_emp_rate_history!$A7) -> chifeihung02 | C7: =stg_emp_rate_history!$F7 -> 43466 | D7: =TEXT(C7,"yyyymmdd") -> 20190101 | E7: =stg_emp_rate_history!$G7 -> 46124 | F7: =TEXT(E7,"yyyymmdd") -> 20260412 | G7: =stg_emp_rate_history!$H7 -> 38
B8: =TRIM(stg_emp_rate_history!$A8) -> cornelalbu01 | C8: =stg_emp_rate_history!$F8 -> 43466 | D8: =TEXT(C8,"yyyymmdd") -> 20190101 | E8: =stg_emp_rate_history!$G8 -> 46124 | F8: =TEXT(E8,"yyyymmdd") -> 20260412 | G8: =stg_emp_rate_history!$H8 -> 38
B9: =TRIM(stg_emp_rate_history!$A9) -> cornelalbu03 | C9: =stg_emp_rate_history!$F9 -> 43466 | D9: =TEXT(C9,"yyyymmdd") -> 20190101 | E9: =stg_emp_rate_history!$G9 -> 46124 | F9: =TEXT(E9,"yyyymmdd") -> 20260412 | G9: =stg_emp_rate_history!$H9 -> 45
B10: =TRIM(stg_emp_rate_history!$A10) -> cornelalbu05 | C10: =stg_emp_rate_history!$F10 -> 43466 | D10: =TEXT(C10,"yyyymmdd") -> 20190101 | E10: =stg_emp_rate_history!$G10 -> 46208 | F10: =TEXT(E10,"yyyymmdd") -> 20260705 | G10: =stg_emp_rate_history!$H10 -> 45
B11: =TRIM(stg_emp_rate_history!$A11) -> igorgroysman01 | C11: =stg_emp_rate_history!$F11 -> 43466 | D11: =TEXT(C11,"yyyymmdd") -> 20190101 | E11: =stg_emp_rate_history!$G11 -> 46124 | F11: =TEXT(E11,"yyyymmdd") -> 20260412 | G11: =stg_emp_rate_history!$H11 -> 38
B12: =TRIM(stg_emp_rate_history!$A12) -> igorgroysman03 | C12: =stg_emp_rate_history!$F12 -> 43466 | D12: =TEXT(C12,"yyyymmdd") -> 20190101 | E12: =stg_emp_rate_history!$G12 -> 46124 | F12: =TEXT(E12,"yyyymmdd") -> 20260412 | G12: =stg_emp_rate_history!$H12 -> 45
B13: =TRIM(stg_emp_rate_history!$A13) -> igorgroysman02 | C13: =stg_emp_rate_history!$F13 -> 43466 | D13: =TEXT(C13,"yyyymmdd") -> 20190101 | E13: =stg_emp_rate_history!$G13 -> 46124 | F13: =TEXT(E13,"yyyymmdd") -> 20260412 | G13: =stg_emp_rate_history!$H13 -> 45
... B46: =TRIM(stg_emp_rate_history!$A46) -> zviadinebieridze01 | C46: =stg_emp_rate_history!$F46 -> 46125 | D46: =TEXT(C46,"yyyymmdd") -> 20260413 | E46: =stg_emp_rate_history!$G46 -> 46208 | F46: =TEXT(E46,"yyyymmdd") -> 20260705 | G46: =stg_emp_rate_history!$H46 -> 35
B47: =TRIM(stg_emp_rate_history!$A49) -> vasilisbellos03 | C47: =stg_emp_rate_history!$F49 -> 43466 | D47: =TEXT(C47,"yyyymmdd") -> 20190101 | E47: =stg_emp_rate_history!$G49 -> 46124 | F47: =TEXT(E47,"yyyymmdd") -> 20260412 | G47: =stg_emp_rate_history!$H49 -> 89
B48: =TRIM(stg_emp_rate_history!$A50) -> vasilisbellos03 | C48: =stg_emp_rate_history!$F50 -> 46125 | D48: =TEXT(C48,"yyyymmdd") -> 20260413 | E48: =stg_emp_rate_history!$G50 -> 46208 | F48: =TEXT(E48,"yyyymmdd") -> 20260705 | G48: =stg_emp_rate_history!$H50 -> 89
B49: =TRIM(stg_emp_rate_history!$A53) -> dimitribellos01 | C49: =stg_emp_rate_history!$F53 -> 43466 | D49: =TEXT(C49,"yyyymmdd") -> 20190101 | E49: =stg_emp_rate_history!$G53 -> 46124 | F49: =TEXT(E49,"yyyymmdd") -> 20260412 | G49: =stg_emp_rate_history!$H53 -> 89
B50: =TRIM(stg_emp_rate_history!$A54) -> dimitribellos01 | C50: =stg_emp_rate_history!$F54 -> 46125 | D50: =TEXT(C50,"yyyymmdd") -> 20260413 | E50: =stg_emp_rate_history!$G54 -> 46208 | F50: =TEXT(E50,"yyyymmdd") -> 20260705 | G50: =stg_emp_rate_history!$H54 -> 89
B51: =TRIM(stg_emp_rate_history!$A55) -> dimitribellos03 | C51: =stg_emp_rate_history!$F55 -> 43466 | D51: =TEXT(C51,"yyyymmdd") -> 20190101 | E51: =stg_emp_rate_history!$G55 -> 46124 | F51: =TEXT(E51,"yyyymmdd") -> 20260412 | G51: =stg_emp_rate_history!$H55 -> 89
B52: =TRIM(stg_emp_rate_history!$A56) -> patriciadros00 | C52: =stg_emp_rate_history!$F56 -> 44896 | D52: =TEXT(C52,"yyyymmdd") -> 20221201 | E52: =stg_emp_rate_history!$G56 -> 46208 | F52: =TEXT(E52,"yyyymmdd") -> 20260705 | G52: 28

Sheet dim_sca_labor_rate
A1: Contract_No | B1: Title Code | C1: SCA_Title_Description | D1: Category | E1: Job_Title | F1: SCA_JobTitle_Key | G1: Level | H1: Years of Experience | I1: Max Billable Hourly Rate | J1: Max Loaded Home Hourly Rate ($) | K1: Max Loaded Field Hourly Rate ($)
A2: C000015128 | B2: LMPABT1 | C2: Asbestos Certified Industrial Hygienist | D2: Asbestos | E2: Certified Industrial Hygienist | F2: =dim_sca_labor_rate!$A2&" "&dim_sca_labor_rate!$D2&" "&dim_sca_labor_rate!$E2&"|"&dim_sca_labor_rate!$H2 -> C000015128 Asbestos Certified Industrial Hygienist| | I2: 66.4 | J2: 166.664 | K2: 160.024
A3: C000015128 | B3: LMPABT9 | C3: Asbestos Inspector | D3: Asbestos | E3: Inspector | F3: =dim_sca_labor_rate!$A3&" "&dim_sca_labor_rate!$D3&" "&dim_sca_labor_rate!$E3&"|"&dim_sca_labor_rate!$H3 -> C000015128 Asbestos Inspector|7 | G3: A | H3: 7 | I3: 39.42 | J3: 98.9442 | K3: 95.0022
A4: C000015128 | B4: LMPABT10 | C4: Asbestos Inspector | D4: Asbestos | E4: Inspector | F4: =dim_sca_labor_rate!$A4&" "&dim_sca_labor_rate!$D4&" "&dim_sca_labor_rate!$E4&"|"&dim_sca_labor_rate!$H4 -> C000015128 Asbestos Inspector|3 | G4: B | H4: 3 | I4: 35.27 | J4: 88.5277 | K4: 85.0007
A5: C000015128 | B5: LMPABT4 | C5: Asbestos Investigator | D5: Asbestos | E5: Investigator | F5: =dim_sca_labor_rate!$A5&" "&dim_sca_labor_rate!$D5&" "&dim_sca_labor_rate!$E5&"|"&dim_sca_labor_rate!$H5 -> C000015128 Asbestos Investigator|7 | G5: A | H5: 7 | I5: 45.65 | J5: 114.5815 | K5: 110.0165
A6: C000015128 | B6: LMPABT5 | C6: Asbestos Investigator | D6: Asbestos | E6: Investigator | F6: =dim_sca_labor_rate!$A6&" "&dim_sca_labor_rate!$D6&" "&dim_sca_labor_rate!$E6&"|"&dim_sca_labor_rate!$H6 -> C000015128 Asbestos Investigator|3 | G6: B | H6: 3 | I6: 39.42 | J6: 98.9442 | K6: 95.0022
A7: C000015128 | B7: LMPABT11 | C7: Asbestos On Site Technical Air Testing | D7: Asbestos | E7: Air Testing | F7: =dim_sca_labor_rate!$A7&" "&dim_sca_labor_rate!$D7&" "&dim_sca_labor_rate!$E7&"|"&dim_sca_labor_rate!$H7 -> C000015128 Asbestos Air Testing|3 | G7: B | H7: 3 | I7: 33.2 | J7: 83.332 | K7: 80.012
A8: C000015128 | B8: LMPABT11 | C8: Asbestos On Site Technical Air Testing | D8: Asbestos | E8: Air Testing | F8: =dim_sca_labor_rate!$A8&" "&dim_sca_labor_rate!$D8&" "&dim_sca_labor_rate!$E8&"|"&dim_sca_labor_rate!$H8 -> C000015128 Asbestos Air Testing|7 | G8: A | H8: 7 | I8: 33.2 | J8: 83.332 | K8: 80.012
A9: C000015128 | B9: LMPABT6 | C9: Asbestos Project Designer | D9: Asbestos | E9: Project Designer | F9: =dim_sca_labor_rate!$A9&" "&dim_sca_labor_rate!$D9&" "&dim_sca_labor_rate!$E9&"|"&dim_sca_labor_rate!$H9 -> C000015128 Asbestos Project Designer|7 | G9: A | H9: 7 | I9: 45.65 | J9: 114.5815 | K9: 110.0165
A10: C000015128 | B10: LMPABT7 | C10: Asbestos Project Designer | D10: Asbestos | E10: Project Designer | F10: =dim_sca_labor_rate!$A10&" "&dim_sca_labor_rate!$D10&" "&dim_sca_labor_rate!$E10&"|"&dim_sca_labor_rate!$H10 -> C000015128 Asbestos Project Designer|3 | G10: B | H10: 3 | I10: 37.35 | J10: 93.7485 | K10: 90.0135
A11: C000015128 | B11: LMPABT2 | C11: Asbestos Project Manager | D11: Asbestos | E11: Project Manager | F11: =dim_sca_labor_rate!$A11&" "&dim_sca_labor_rate!$D11&" "&dim_sca_labor_rate!$E11&"|"&dim_sca_labor_rate!$H11 -> C000015128 Asbestos Project Manager|7 | G11: A | H11: 7 | I11: 58.1 | J11: 145.831 | K11: 140.021
A12: C000015128 | B12: LMPABT3 | C12: Asbestos Project Manager | D12: Asbestos | E12: Project Manager | F12: =dim_sca_labor_rate!$A12&" "&dim_sca_labor_rate!$D12&" "&dim_sca_labor_rate!$E12&"|"&dim_sca_labor_rate!$H12 -> C000015128 Asbestos Project Manager|3 | G12: B | H12: 3 | I12: 45.64 | J12: 114.5564 | K12: 109.9924
A13: C000015128 | B13: LMPABT8 | C13: Asbestos Project Monitor | D13: Asbestos | E13: Project Monitor | F13: =dim_sca_labor_rate!$A13&" "&dim_sca_labor_rate!$D13&" "&dim_sca_labor_rate!$E13&"|"&dim_sca_labor_rate!$H13 -> C000015128 Asbestos Project Monitor|7 | G13: A | H13: 7 | I13: 35.27 | J13: 88.5277 | K13: 85.0007
A14: C000015128 | B14: LMPABT8 | C14: Asbestos Project Monitor | D14: Asbestos | E14: Project Monitor | F14: =dim_sca_labor_rate!$A14&" "&dim_sca_labor_rate!$D14&" "&dim_sca_labor_rate!$E14&"|"&dim_sca_labor_rate!$H14 -> C000015128 Asbestos Project Monitor|3 | G14: B | H14: 3 | I14: 35.27 | J14: 88.5277 | K14: 85.0007
A15: C000015128 | B15: LMPGNT12 | C15: Computer Assisted Design Draftsperson | D15: Computer | E15: Assisted Design Draftsperson | F15: =dim_sca_labor_rate!$A15&" "&dim_sca_labor_rate!$D15&" "&dim_sca_labor_rate!$E15&"|"&dim_sca_labor_rate!$H15 -> C000015128 Computer Assisted Design Draftsperson|3 | G15: B | H15: 3 | I15: 29.05 | J15: 72.9155 | K15: 70.0105
A16: C000015128 | B16: LMPGNT13 | C16: Field Engineer P.E. | D16: Field | E16: Engineer P.E. | F16: =dim_sca_labor_rate!$A16&" "&dim_sca_labor_rate!$D16&" "&dim_sca_labor_rate!$E16&"|"&dim_sca_labor_rate!$H16 -> C000015128 Field Engineer P.E.| | I16: 68.46 | J16: 171.8346 | K16: 164.9886
A17: C000015128 | B17: LMPLDT21 | C17: Certified Lead Inspector | D17: Lead | E17: Inspector | F17: =dim_sca_labor_rate!$A17&" "&dim_sca_labor_rate!$D17&" "&dim_sca_labor_rate!$E17&"|"&dim_sca_labor_rate!$H17 -> C000015128 Lead Inspector|7 | G17: A | H17: 7 | I17: 37.34 | J17: 93.7234 | K17: 89.9894
A18: C000015128 | B18: LMPLDT22 | C18: Certified Lead Inspector | D18: Lead | E18: Inspector | F18: =dim_sca_labor_rate!$A18&" "&dim_sca_labor_rate!$D18&" "&dim_sca_labor_rate!$E18&"|"&dim_sca_labor_rate!$H18 -> C000015128 Lead Inspector|3 | G18: B | H18: 3 | I18: 31.12 | J18: 78.1112 | K18: 74.9992
A19: C000015128 | B19: LMPLDT19 | C19: Certified Lead Inspector / Risk Assessor | D19: Lead | E19: Inspector / Risk Assessor | F19: =dim_sca_labor_rate!$A19&" "&dim_sca_labor_rate!$D19&" "&dim_sca_labor_rate!$E19&"|"&dim_sca_labor_rate!$H19 -> C000015128 Lead Inspector / Risk Assessor|7 | G19: A | H19: 7 | I19: 45.64 | J19: 114.5564 | K19: 109.9924
A20: C000015128 | B20: LMPLDT20 | C20: Certified Lead Inspector / Risk Assessor | D20: Lead | E20: Inspector / Risk Assessor | F20: =dim_sca_labor_rate!$A20&" "&dim_sca_labor_rate!$D20&" "&dim_sca_labor_rate!$E20&"|"&dim_sca_labor_rate!$H20 -> C000015128 Lead Inspector / Risk Assessor|3 | G20: B | H20: 3 | I20: 39.42 | J20: 98.9442 | K20: 95.0022
A21: C000015128 | B21: LMPLDT23 | C21: Certified Lead Project Designer | D21: Lead | E21: Project Designer | F21: =dim_sca_labor_rate!$A21&" "&dim_sca_labor_rate!$D21&" "&dim_sca_labor_rate!$E21&"|"&dim_sca_labor_rate!$H21 -> C000015128 Lead Project Designer|7 | G21: A | H21: 7 | I21: 41.49 | J21: 104.1399 | K21: 99.9909
A22: C000015128 | B22: LMPLDT24 | C22: Certified Lead Project Designer | D22: Lead | E22: Project Designer | F22: =dim_sca_labor_rate!$A22&" "&dim_sca_labor_rate!$D22&" "&dim_sca_labor_rate!$E22&"|"&dim_sca_labor_rate!$H22 -> C000015128 Lead Project Designer|3 | G22: B | H22: 3 | I22: 31.12 | J22: 78.1112 | K22: 74.9992
A23: C000015128 | B23: LMPLDT25 | C23: SSPC C3 Certified Lead Supervisor | D23: SSPC | E23: C3 Certified Lead Supervisor | F23: =dim_sca_labor_rate!$A23&" "&dim_sca_labor_rate!$D23&" "&dim_sca_labor_rate!$E23&"|"&dim_sca_labor_rate!$H23 -> C000015128 SSPC C3 Certified Lead Supervisor|7 | G23: A | H23: 7 | I23: 41.49 | J23: 104.1399 | K23: 99.9909
A24: C000015128 | B24: LMPLDT26 | C24: SSPC C3 Certified Lead Supervisor | D24: SSPC | E24: C3 Certified Lead Supervisor | F24: =dim_sca_labor_rate!$A24&" "&dim_sca_labor_rate!$D24&" "&dim_sca_labor_rate!$E24&"|"&dim_sca_labor_rate!$H24 -> C000015128 SSPC C3 Certified Lead Supervisor|3 | G24: B | H24: 3 | I24: 35.27 | J24: 88.5277 | K24: 85.0007
A25: C000015128 | B25: LMPMDT18 | C25: Mold Certified Industrial Hygienist | D25: Mold | E25: Certified Industrial Hygienist | F25: =dim_sca_labor_rate!$A25&" "&dim_sca_labor_rate!$D25&" "&dim_sca_labor_rate!$E25&"|"&dim_sca_labor_rate!$H25 -> C000015128 Mold Certified Industrial Hygienist| | I25: 66.39 | J25: 166.6389 | K25: 159.9999
A26: C000015128 | B26: LMPMDT17 | C26: Mold Field Technician | D26: Mold | E26: Field Technician | F26: =dim_sca_labor_rate!$A26&" "&dim_sca_labor_rate!$D26&" "&dim_sca_labor_rate!$E26&"|"&dim_sca_labor_rate!$H26 -> C000015128 Mold Field Technician|3 | H26: 3 | I26: 33.2 | J26: 83.332 | K26: 80.012
A27: C000015128 | B27: LMPMDT14 | C27: Mold Program Director | D27: Mold | E27: Program Director | F27: =dim_sca_labor_rate!$A27&" "&dim_sca_labor_rate!$D27&" "&dim_sca_labor_rate!$E27&"|"&dim_sca_labor_rate!$H27 -> C000015128 Mold Program Director|15 | H27: 15 | I27: 66.39 | J27: 166.6389 | K27: 159.9999
A28: C000015128 | B28: LMPMDT15 | C28: Mold Project Manager | D28: Mold | E28: Project Manager | F28: =dim_sca_labor_rate!$A28&" "&dim_sca_labor_rate!$D28&" "&dim_sca_labor_rate!$E28&"|"&dim_sca_labor_rate!$H28 -> C000015128 Mold Project Manager|7 | G28: A | H28: 7 | I28: 60.17 | J28: 151.0267 | K28: 145.0097
A29: C000015128 | B29: LMPMDT16 | C29: Mold Project Manager | D29: Mold | E29: Project Manager | F29: =dim_sca_labor_rate!$A29&" "&dim_sca_labor_rate!$D29&" "&dim_sca_labor_rate!$E29&"|"&dim_sca_labor_rate!$H29 -> C000015128 Mold Project Manager|3 | G29: B | H29: 3 | I29: 45.64 | J29: 114.5564 | K29: 109.9924
A30: C000015128 | B30: LMPPBT31 | C30: PCB Certified Industrial Hygienist | D30: PCB | E30: Certified Industrial Hygienist | F30: =dim_sca_labor_rate!$A30&" "&dim_sca_labor_rate!$D30&" "&dim_sca_labor_rate!$E30&"|"&dim_sca_labor_rate!$H30 -> C000015128 PCB Certified Industrial Hygienist| | I30: 66.39 | J30: 166.6389 | K30: 159.9999
A31: C000015128 | B31: LMPPBT29 | C31: PCB Field Technician | D31: PCB | E31: Field Technician | F31: =dim_sca_labor_rate!$A31&" "&dim_sca_labor_rate!$D31&" "&dim_sca_labor_rate!$E31&"|"&dim_sca_labor_rate!$H31 -> C000015128 PCB Field Technician|7 | G31: A | H31: 7 | I31: 33.2 | J31: 83.332 | K31: 80.012
A32: C000015128 | B32: LMPPBT30 | C32: PCB Field Technician | D32: PCB | E32: Field Technician | F32: =dim_sca_labor_rate!$A32&" "&dim_sca_labor_rate!$D32&" "&dim_sca_labor_rate!$E32&"|"&dim_sca_labor_rate!$H32 -> C000015128 PCB Field Technician|3 | G32: B | H32: 3 | I32: 31.12 | J32: 78.1112 | K32: 74.9992
A33: C000015128 | B33: LMPPBT27 | C33: PCB Program Director | D33: PCB | E33: Program Director | F33: =dim_sca_labor_rate!$A33&" "&dim_sca_labor_rate!$D33&" "&dim_sca_labor_rate!$E33&"|"&dim_sca_labor_rate!$H33 -> C000015128 PCB Program Director|15 | H33: 15 | I33: 68.46 | J33: 171.8346 | K33: 164.9886
A34: C000015128 | B34: LMPPBT28 | C34: PCB Project Manager | D34: PCB | E34: Project Manager | F34: =dim_sca_labor_rate!$A34&" "&dim_sca_labor_rate!$D34&" "&dim_sca_labor_rate!$E34&"|"&dim_sca_labor_rate!$H34 -> C000015128 PCB Project Manager|5 | H34: 5 | I34: 58.09 | J34: 145.8059 | K34: 139.9969
A35: C000015869 | B35: LMPABT1 | C35: Asbestos Certified Industrial Hygienist | D35: Asbestos | E35: Certified Industrial Hygienist | F35: =dim_sca_labor_rate!$A35&" "&dim_sca_labor_rate!$D35&" "&dim_sca_labor_rate!$E35&"|"&dim_sca_labor_rate!$H35 -> C000015869 Asbestos Certified Industrial Hygienist| | I35: 75 | J35: 206.25 | K35: 190.5
A36: C000015869 | B36: LMPABT9 | C36: Asbestos Inspector | D36: Asbestos | E36: Inspector | F36: =dim_sca_labor_rate!$A36&" "&dim_sca_labor_rate!$D36&" "&dim_sca_labor_rate!$E36&"|"&dim_sca_labor_rate!$H36 -> C000015869 Asbestos Inspector|7 | G36: A | H36: 7 | I36: 43 | J36: 118.25 | K36: 109.22
A37: C000015869 | B37: LMPABT10 | C37: Asbestos Inspector | D37: Asbestos | E37: Inspector | F37: =dim_sca_labor_rate!$A37&" "&dim_sca_labor_rate!$D37&" "&dim_sca_labor_rate!$E37&"|"&dim_sca_labor_rate!$H37 -> C000015869 Asbestos Inspector|3 | G37: B | H37: 3 | I37: 36 | J37: 99 | K37: 91.44
A38: C000015869 | B38: LMPABT4 | C38: Asbestos Investigator | D38: Asbestos | E38: Investigator | F38: =dim_sca_labor_rate!$A38&" "&dim_sca_labor_rate!$D38&" "&dim_sca_labor_rate!$E38&"|"&dim_sca_labor_rate!$H38 -> C000015869 Asbestos Investigator|7 | G38: A | H38: 7 | I38: 49 | J38: 134.75 | K38: 124.46
A39: C000015869 | B39: LMPABT5 | C39: Asbestos Investigator | D39: Asbestos | E39: Investigator | F39: =dim_sca_labor_rate!$A39&" "&dim_sca_labor_rate!$D39&" "&dim_sca_labor_rate!$E39&"|"&dim_sca_labor_rate!$H39 -> C000015869 Asbestos Investigator|3 | G39: B | H39: 3 | I39: 42 | J39: 115.5 | K39: 106.68
A40: C000015869 | B40: LMPABT11 | C40: Asbestos On Site Technical Air Testing | D40: Asbestos | E40: Air Testing | F40: =dim_sca_labor_rate!$A40&" "&dim_sca_labor_rate!$D40&" "&dim_sca_labor_rate!$E40&"|"&dim_sca_labor_rate!$H40 -> C000015869 Asbestos Air Testing|3 | G40: B | H40: 3 | I40: 36 | J40: 99 | K40: 91.44
A41: C000015869 | B41: LMPABT11 | C41: Asbestos On Site Technical Air Testing | D41: Asbestos | E41: Air Testing | F41: =dim_sca_labor_rate!$A41&" "&dim_sca_labor_rate!$D41&" "&dim_sca_labor_rate!$E41&"|"&dim_sca_labor_rate!$H41 -> C000015869 Asbestos Air Testing|7 | G41: A | H41: 7 | I41: 36 | J41: 99 | K41: 91.44
A42: C000015869 | B42: LMPABT6 | C42: Asbestos Project Designer | D42: Asbestos | E42: Project Designer | F42: =dim_sca_labor_rate!$A42&" "&dim_sca_labor_rate!$D42&" "&dim_sca_labor_rate!$E42&"|"&dim_sca_labor_rate!$H42 -> C000015869 Asbestos Project Designer|7 | G42: A | H42: 7 | I42: 55 | J42: 151.25 | K42: 139.7
A43: C000015869 | B43: LMPABT7 | C43: Asbestos Project Designer | D43: Asbestos | E43: Project Designer | F43: =dim_sca_labor_rate!$A43&" "&dim_sca_labor_rate!$D43&" "&dim_sca_labor_rate!$E43&"|"&dim_sca_labor_rate!$H43 -> C000015869 Asbestos Project Designer|3 | G43: B | H43: 3 | I43: 45 | J43: 123.75 | K43: 114.3
A44: C000015869 | B44: LMPABT2 | C44: Asbestos Project Manager | D44: Asbestos | E44: Project Manager | F44: =dim_sca_labor_rate!$A44&" "&dim_sca_labor_rate!$D44&" "&dim_sca_labor_rate!$E44&"|"&dim_sca_labor_rate!$H44 -> C000015869 Asbestos Project Manager|7 | G44: A | H44: 7 | I44: 61 | J44: 167.75 | K44: 154.94
A45: C000015869 | B45: LMPABT3 | C45: Asbestos Project Manager | D45: Asbestos | E45: Project Manager | F45: =dim_sca_labor_rate!$A45&" "&dim_sca_labor_rate!$D45&" "&dim_sca_labor_rate!$E45&"|"&dim_sca_labor_rate!$H45 -> C000015869 Asbestos Project Manager|3 | G45: B | H45: 3 | I45: 46 | J45: 126.5 | K45: 116.84
A46: C000015869 | B46: LMPABT8 | C46: Asbestos Project Monitor | D46: Asbestos | E46: Project Monitor | F46: =dim_sca_labor_rate!$A46&" "&dim_sca_labor_rate!$D46&" "&dim_sca_labor_rate!$E46&"|"&dim_sca_labor_rate!$H46 -> C000015869 Asbestos Project Monitor|7 | G46: A | H46: 7 | I46: 38 | J46: 104.5 | K46: 96.52
A47: C000015869 | B47: LMPABT8 | C47: Asbestos Project Monitor | D47: Asbestos | E47: Project Monitor | F47: =dim_sca_labor_rate!$A47&" "&dim_sca_labor_rate!$D47&" "&dim_sca_labor_rate!$E47&"|"&dim_sca_labor_rate!$H47 -> C000015869 Asbestos Project Monitor|3 | G47: B | H47: 3 | I47: 38 | J47: 104.5 | K47: 96.52
A48: C000015869 | B48: LMPGNT12 | C48: Computer Assisted Design Draftsperson | D48: Computer | E48: Assisted Design Draftsperson | F48: =dim_sca_labor_rate!$A48&" "&dim_sca_labor_rate!$D48&" "&dim_sca_labor_rate!$E48&"|"&dim_sca_labor_rate!$H48 -> C000015869 Computer Assisted Design Draftsperson|3 | H48: 3 | I48: 30 | J48: 82.5 | K48: 76.2
A49: C000015869 | B49: LMPGNT13 | C49: Field Engineer P.E. | D49: Field | E49: Engineer P.E. | F49: =dim_sca_labor_rate!$A49&" "&dim_sca_labor_rate!$D49&" "&dim_sca_labor_rate!$E49&"|"&dim_sca_labor_rate!$H49 -> C000015869 Field Engineer P.E.| | I49: 75 | J49: 206.25 | K49: 190.5
A50: C000015869 | B50: LMPLDT21 | C50: Certified Lead Inspector | D50: Lead | E50: Inspector | F50: =dim_sca_labor_rate!$A50&" "&dim_sca_labor_rate!$D50&" "&dim_sca_labor_rate!$E50&"|"&dim_sca_labor_rate!$H50 -> C000015869 Lead Inspector|7 | G50: A | H50: 7 | I50: 43 | J50: 118.25 | K50: 109.22
A51: C000015869 | B51: LMPLDT22 | C51: Certified Lead Inspector | D51: Lead | E51: Inspector | F51: =dim_sca_labor_rate!$A51&" "&dim_sca_labor_rate!$D51&" "&dim_sca_labor_rate!$E51&"|"&dim_sca_labor_rate!$H51 -> C000015869 Lead Inspector|3 | G51: B | H51: 3 | I51: 35 | J51: 96.25 | K51: 88.9
A52: C000015869 | B52: LMPLDT19 | C52: Certified Lead Inspector / Risk Assessor | D52: Lead | E52: Inspector / Risk Assessor | F52: =dim_sca_labor_rate!$A52&" "&dim_sca_labor_rate!$D52&" "&dim_sca_labor_rate!$E52&"|"&dim_sca_labor_rate!$H52 -> C000015869 Lead Inspector / Risk Assessor|7 | G52: A | H52: 7 | I52: 51 | J52: 140.25 | K52: 129.54
A53: C000015869 | B53: LMPLDT20 | C53: Certified Lead Inspector / Risk Assessor | D53: Lead | E53: Inspector / Risk Assessor | F53: =dim_sca_labor_rate!$A53&" "&dim_sca_labor_rate!$D53&" "&dim_sca_labor_rate!$E53&"|"&dim_sca_labor_rate!$H53 -> C000015869 Lead Inspector / Risk Assessor|3 | G53: B | H53: 3 | I53: 39 | J53: 107.25 | K53: 99.06
A54: C000015869 | B54: LMPLDT23 | C54: Certified Lead Project Designer | D54: Lead | E54: Project Designer | F54: =dim_sca_labor_rate!$A54&" "&dim_sca_labor_rate!$D54&" "&dim_sca_labor_rate!$E54&"|"&dim_sca_labor_rate!$H54 -> C000015869 Lead Project Designer|7 | G54: A | H54: 7 | I54: 50 | J54: 137.5 | K54: 127
A55: C000015869 | B55: LMPLDT24 | C55: Certified Lead Project Designer | D55: Lead | E55: Project Designer | F55: =dim_sca_labor_rate!$A55&" "&dim_sca_labor_rate!$D55&" "&dim_sca_labor_rate!$E55&"|"&dim_sca_labor_rate!$H55 -> C000015869 Lead Project Designer|3 | G55: B | H55: 3 | I55: 40 | J55: 110 | K55: 101.6
A56: C000015869 | B56: LMPLDT25 | C56: SSPC C3 Certified Lead Supervisor | D56: SSPC | E56: C3 Certified Lead Supervisor | F56: =dim_sca_labor_rate!$A56&" "&dim_sca_labor_rate!$D56&" "&dim_sca_labor_rate!$E56&"|"&dim_sca_labor_rate!$H56 -> C000015869 SSPC C3 Certified Lead Supervisor|7 | G56: A | H56: 7 | I56: 45 | J56: 123.75 | K56: 114.3
A57: C000015869 | B57: LMPLDT26 | C57: SSPC C3 Certified Lead Supervisor | D57: SSPC | E57: C3 Certified Lead Supervisor | F57: =dim_sca_labor_rate!$A57&" "&dim_sca_labor_rate!$D57&" "&dim_sca_labor_rate!$E57&"|"&dim_sca_labor_rate!$H57 -> C000015869 SSPC C3 Certified Lead Supervisor|3 | G57: B | H57: 3 | I57: 40 | J57: 110 | K57: 101.6
A58: C000015869 | B58: LMPMDT18 | C58: Mold Certified Industrial Hygienist | D58: Mold | E58: Certified Industrial Hygienist | F58: =dim_sca_labor_rate!$A58&" "&dim_sca_labor_rate!$D58&" "&dim_sca_labor_rate!$E58&"|"&dim_sca_labor_rate!$H58 -> C000015869 Mold Certified Industrial Hygienist| | I58: 50 | J58: 137.5 | K58: 127
A59: C000015869 | B59: LMPMDT17 | C59: Mold Field Technician | D59: Mold | E59: Field Technician | F59: =dim_sca_labor_rate!$A59&" "&dim_sca_labor_rate!$D59&" "&dim_sca_labor_rate!$E59&"|"&dim_sca_labor_rate!$H59 -> C000015869 Mold Field Technician|3 | H59: 3 | I59: 34 | J59: 93.5 | K59: 86.36
A60: C000015869 | B60: LMPMDT14 | C60: Mold Program Director | D60: Mold | E60: Program Director | F60: =dim_sca_labor_rate!$A60&" "&dim_sca_labor_rate!$D60&" "&dim_sca_labor_rate!$E60&"|"&dim_sca_labor_rate!$H60 -> C000015869 Mold Program Director|15 | H60: 15 | I60: 68 | J60: 187 | K60: 172.72
A61: C000015869 | B61: LMPMDT15 | C61: Mold Project Manager | D61: Mold | E61: Project Manager | F61: =dim_sca_labor_rate!$A61&" "&dim_sca_labor_rate!$D61&" "&dim_sca_labor_rate!$E61&"|"&dim_sca_labor_rate!$H61 -> C000015869 Mold Project Manager|7 | G61: A | H61: 7 | I61: 50 | J61: 137.5 | K61: 127
A62: C000015869 | B62: LMPMDT16 | C62: Mold Project Manager | D62: Mold | E62: Project Manager | F62: =dim_sca_labor_rate!$A62&" "&dim_sca_labor_rate!$D62&" "&dim_sca_labor_rate!$E62&"|"&dim_sca_labor_rate!$H62 -> C000015869 Mold Project Manager|3 | G62: B | H62: 3 | I62: 46 | J62: 126.5 | K62: 116.84
A63: C000015869 | B63: LMPPBT31 | C63: PCB Certified Industrial Hygienist | D63: PCB | E63: Certified Industrial Hygienist | F63: =dim_sca_labor_rate!$A63&" "&dim_sca_labor_rate!$D63&" "&dim_sca_labor_rate!$E63&"|"&dim_sca_labor_rate!$H63 -> C000015869 PCB Certified Industrial Hygienist| | I63: 75 | J63: 206.25 | K63: 190.5
A64: C000015869 | B64: LMPPBT29 | C64: PCB Field Technician | D64: PCB | E64: Field Technician | F64: =dim_sca_labor_rate!$A64&" "&dim_sca_labor_rate!$D64&" "&dim_sca_labor_rate!$E64&"|"&dim_sca_labor_rate!$H64 -> C000015869 PCB Field Technician|7 | G64: A | H64: 7 | I64: 36 | J64: 99 | K64: 91.44
A65: C000015869 | B65: LMPPBT30 | C65: PCB Field Technician | D65: PCB | E65: Field Technician | F65: =dim_sca_labor_rate!$A65&" "&dim_sca_labor_rate!$D65&" "&dim_sca_labor_rate!$E65&"|"&dim_sca_labor_rate!$H65 -> C000015869 PCB Field Technician|3 | G65: B | H65: 3 | I65: 31 | J65: 85.25 | K65: 78.74
A66: C000015869 | B66: LMPPBT27 | C66: PCB Program Director | D66: PCB | E66: Program Director | F66: =dim_sca_labor_rate!$A66&" "&dim_sca_labor_rate!$D66&" "&dim_sca_labor_rate!$E66&"|"&dim_sca_labor_rate!$H66 -> C000015869 PCB Program Director|15 | H66: 15 | I66: 65 | J66: 178.75 | K66: 165.1
A67: C000015869 | B67: LMPPBT28 | C67: PCB Project Manager | D67: PCB | E67: Project Manager | F67: =dim_sca_labor_rate!$A67&" "&dim_sca_labor_rate!$D67&" "&dim_sca_labor_rate!$E67&"|"&dim_sca_labor_rate!$H67 -> C000015869 PCB Project Manager|5 | H67: 5 | I67: 55 | J67: 151.25 | K67: 139.7
A68: C000016435 | B68: LMPABT1 | C68: Asbestos Certified Industrial Hygienist | D68: Asbestos | E68: Certified Industrial Hygienist | F68: =dim_sca_labor_rate!$A68&" "&dim_sca_labor_rate!$D68&" "&dim_sca_labor_rate!$E68&"|"&dim_sca_labor_rate!$H68 -> C000016435 Asbestos Certified Industrial Hygienist| | I68: 77 | J68: 321 | K68: 225.61
A69: C000016435 | B69: LMPABT9 | C69: Asbestos Inspector | D69: Asbestos | E69: Inspector | F69: =dim_sca_labor_rate!$A69&" "&dim_sca_labor_rate!$D69&" "&dim_sca_labor_rate!$E69&"|"&dim_sca_labor_rate!$H69 -> C000016435 Asbestos Inspector|7 | G69: A | H69: 7 | I69: 55 | J69: =dim_sca_labor_rate!$I69*3 -> 165 | K69: =dim_sca_labor_rate!$I69*2.93 -> 161.15
A70: C000016435 | B70: LMPABT10 | C70: Asbestos Inspector | D70: Asbestos | E70: Inspector | F70: =dim_sca_labor_rate!$A70&" "&dim_sca_labor_rate!$D70&" "&dim_sca_labor_rate!$E70&"|"&dim_sca_labor_rate!$H70 -> C000016435 Asbestos Inspector|3 | G70: B | H70: 3 | I70: 44 | J70: =dim_sca_labor_rate!$I70*3 -> 132 | K70: =dim_sca_labor_rate!$I70*2.93 -> 128.92
A71: C000016435 | B71: LMPABT4 | C71: Asbestos Investigator | D71: Asbestos | E71: Investigator | F71: =dim_sca_labor_rate!$A71&" "&dim_sca_labor_rate!$D71&" "&dim_sca_labor_rate!$E71&"|"&dim_sca_labor_rate!$H71 -> C000016435 Asbestos Investigator|7 | G71: A | H71: 7 | I71: 67 | J71: =dim_sca_labor_rate!$I71*3 -> 201 | K71: =dim_sca_labor_rate!$I71*2.93 -> 196.31
A72: C000016435 | B72: LMPABT5 | C72: Asbestos Investigator | D72: Asbestos | E72: Investigator | F72: =dim_sca_labor_rate!$A72&" "&dim_sca_labor_rate!$D72&" "&dim_sca_labor_rate!$E72&"|"&dim_sca_labor_rate!$H72 -> C000016435 Asbestos Investigator|3 | G72: B | H72: 3 | I72: 60 | J72: =dim_sca_labor_rate!$I72*3 -> 180 | K72: =dim_sca_labor_rate!$I72*2.93 -> 175.8
A73: C000016435 | B73: LMPABT11 | C73: Asbestos On Site Technical Air Testing | D73: Asbestos | E73: Air Testing | F73: =dim_sca_labor_rate!$A73&" "&dim_sca_labor_rate!$D73&" "&dim_sca_labor_rate!$E73&"|"&dim_sca_labor_rate!$H73 -> C000016435 Asbestos Air Testing|3 | G73: B | H73: 3 | I73: 44 | J73: =dim_sca_labor_rate!$I73*3 -> 132 | K73: =dim_sca_labor_rate!$I73*2.93 -> 128.92
A74: C000016435 | B74: LMPABT11 | C74: Asbestos On Site Technical Air Testing | D74: Asbestos | E74: Air Testing | F74: =dim_sca_labor_rate!$A74&" "&dim_sca_labor_rate!$D74&" "&dim_sca_labor_rate!$E74&"|"&dim_sca_labor_rate!$H74 -> C000016435 Asbestos Air Testing|7 | G74: A | H74: 7 | I74: 44 | J74: =dim_sca_labor_rate!$I74*3 -> 132 | K74: =dim_sca_labor_rate!$I74*2.93 -> 128.92
A75: C000016435 | B75: LMPABT6 | C75: Asbestos Project Designer | D75: Asbestos | E75: Project Designer | F75: =dim_sca_labor_rate!$A75&" "&dim_sca_labor_rate!$D75&" "&dim_sca_labor_rate!$E75&"|"&dim_sca_labor_rate!$H75 -> C000016435 Asbestos Project Designer|7 | G75: A | H75: 7 | I75: 72 | J75: =dim_sca_labor_rate!$I75*3 -> 216 | K75: =dim_sca_labor_rate!$I75*2.93 -> 210.96
A76: C000016435 | B76: LMPABT7 | C76: Asbestos Project Designer | D76: Asbestos | E76: Project Designer | F76: =dim_sca_labor_rate!$A76&" "&dim_sca_labor_rate!$D76&" "&dim_sca_labor_rate!$E76&"|"&dim_sca_labor_rate!$H76 -> C000016435 Asbestos Project Designer|3 | G76: B | H76: 3 | I76: 63 | J76: =dim_sca_labor_rate!$I76*3 -> 189 | K76: =dim_sca_labor_rate!$I76*2.93 -> 184.59
A77: C000016435 | B77: LMPABT2 | C77: Asbestos Project Manager | D77: Asbestos | E77: Project Manager | F77: =dim_sca_labor_rate!$A77&" "&dim_sca_labor_rate!$D77&" "&dim_sca_labor_rate!$E77&"|"&dim_sca_labor_rate!$H77 -> C000016435 Asbestos Project Manager|7 | G77: A | H77: 7 | I77: 77 | J77: =dim_sca_labor_rate!$I77*3 -> 231 | K77: =dim_sca_labor_rate!$I77*2.93 -> 225.61
A78: C000016435 | B78: LMPABT3 | C78: Asbestos Project Manager | D78: Asbestos | E78: Project Manager | F78: =dim_sca_labor_rate!$A78&" "&dim_sca_labor_rate!$D78&" "&dim_sca_labor_rate!$E78&"|"&dim_sca_labor_rate!$H78 -> C000016435 Asbestos Project Manager|3 | G78: B | H78: 3 | I78: 67 | J78: =dim_sca_labor_rate!$I78*3 -> 201 | K78: =dim_sca_labor_rate!$I78*2.93 -> 196.31
A79: C000016435 | B79: LMPABT8 | C79: Asbestos Project Monitor | D79: Asbestos | E79: Project Monitor | F79: =dim_sca_labor_rate!$A79&" "&dim_sca_labor_rate!$D79&" "&dim_sca_labor_rate!$E79&"|"&dim_sca_labor_rate!$H79 -> C000016435 Asbestos Project Monitor|7 | G79: A | H79: 7 | I79: 48 | J79: =dim_sca_labor_rate!$I79*3 -> 144 | K79: =dim_sca_labor_rate!$I79*2.93 -> 140.64
A80: C000016435 | B80: LMPABT8 | C80: Asbestos Project Monitor | D80: Asbestos | E80: Project Monitor | F80: =dim_sca_labor_rate!$A80&" "&dim_sca_labor_rate!$D80&" "&dim_sca_labor_rate!$E80&"|"&dim_sca_labor_rate!$H80 -> C000016435 Asbestos Project Monitor|3 | G80: B | H80: 3 | I80: 48 | J80: 144 | K80: 140.64
A81: C000016435 | B81: LMPGNT12 | C81: Computer Assisted Design Draftsperson | D81: Computer | E81: Assisted Design Draftsperson | F81: =dim_sca_labor_rate!$A81&" "&dim_sca_labor_rate!$D81&" "&dim_sca_labor_rate!$E81&"|"&dim_sca_labor_rate!$H81 -> C000016435 Computer Assisted Design Draftsperson|3 | H81: 3 | I81: 39 | J81: =dim_sca_labor_rate!$I81*3 -> 117 | K81: =dim_sca_labor_rate!$I81*2.93 -> 114.27
A82: C000016435 | B82: LMPGNT13 | C82: Field Engineer P.E. | D82: Field | E82: Engineer P.E. | F82: =dim_sca_labor_rate!$A82&" "&dim_sca_labor_rate!$D82&" "&dim_sca_labor_rate!$E82&"|"&dim_sca_labor_rate!$H82 -> C000016435 Field Engineer P.E.| | I82: 85 | J82: =dim_sca_labor_rate!$I82*3 -> 255 | K82: =dim_sca_labor_rate!$I82*2.93 -> 249.05
A83: C000016435 | B83: LMPLDT21 | C83: Certified Lead Inspector | D83: Lead | E83: Inspector | F83: =dim_sca_labor_rate!$A83&" "&dim_sca_labor_rate!$D83&" "&dim_sca_labor_rate!$E83&"|"&dim_sca_labor_rate!$H83 -> C000016435 Lead Inspector|7 | G83: A | H83: 7 | I83: 55 | J83: =dim_sca_labor_rate!$I83*3 -> 165 | K83: =dim_sca_labor_rate!$I83*2.93 -> 161.15
A84: C000016435 | B84: LMPLDT22 | C84: Certified Lead Inspector | D84: Lead | E84: Inspector | F84: =dim_sca_labor_rate!$A84&" "&dim_sca_labor_rate!$D84&" "&dim_sca_labor_rate!$E84&"|"&dim_sca_labor_rate!$H84 -> C000016435 Lead Inspector|3 | G84: B | H84: 3 | I84: 45 | J84: =dim_sca_labor_rate!$I84*3 -> 135 | K84: =dim_sca_labor_rate!$I84*2.93 -> 131.85
A85: C000016435 | B85: LMPLDT19 | C85: Certified Lead Inspector / Risk Assessor | D85: Lead | E85: Inspector / Risk Assessor | F85: =dim_sca_labor_rate!$A85&" "&dim_sca_labor_rate!$D85&" "&dim_sca_labor_rate!$E85&"|"&dim_sca_labor_rate!$H85 -> C000016435 Lead Inspector / Risk Assessor|7 | G85: A | H85: 7 | I85: 61 | J85: =dim_sca_labor_rate!$I85*3 -> 183 | K85: =dim_sca_labor_rate!$I85*2.93 -> 178.73
A86: C000016435 | B86: LMPLDT20 | C86: Certified Lead Inspector / Risk Assessor | D86: Lead | E86: Inspector / Risk Assessor | F86: =dim_sca_labor_rate!$A86&" "&dim_sca_labor_rate!$D86&" "&dim_sca_labor_rate!$E86&"|"&dim_sca_labor_rate!$H86 -> C000016435 Lead Inspector / Risk Assessor|3 | G86: B | H86: 3 | I86: 61 | J86: =dim_sca_labor_rate!$I86*3 -> 183 | K86: =dim_sca_labor_rate!$I86*2.93 -> 178.73
A87: C000016435 | B87: LMPLDT23 | C87: Certified Lead Project Designer | D87: Lead | E87: Project Designer | F87: =dim_sca_labor_rate!$A87&" "&dim_sca_labor_rate!$D87&" "&dim_sca_labor_rate!$E87&"|"&dim_sca_labor_rate!$H87 -> C000016435 Lead Project Designer|7 | G87: A | H87: 7 | I87: 69 | J87: =dim_sca_labor_rate!$I87*3 -> 207 | K87: =dim_sca_labor_rate!$I87*2.93 -> 202.17
A88: C000016435 | B88: LMPLDT24 | C88: Certified Lead Project Designer | D88: Lead | E88: Project Designer | F88: =dim_sca_labor_rate!$A88&" "&dim_sca_labor_rate!$D88&" "&dim_sca_labor_rate!$E88&"|"&dim_sca_labor_rate!$H88 -> C000016435 Lead Project Designer|3 | G88: B | H88: 3 | I88: 47 | J88: =dim_sca_labor_rate!$I88*3 -> 141 | K88: =dim_sca_labor_rate!$I88*2.93 -> 137.71
A89: C000016435 | B89: LMPLDT25 | C89: SSPC C3 Certified Lead Supervisor | D89: SSPC | E89: C3 Certified Lead Supervisor | F89: =dim_sca_labor_rate!$A89&" "&dim_sca_labor_rate!$D89&" "&dim_sca_labor_rate!$E89&"|"&dim_sca_labor_rate!$H89 -> C000016435 SSPC C3 Certified Lead Supervisor|7 | G89: A | H89: 7 | I89: 65 | J89: =dim_sca_labor_rate!$I89*3 -> 195 | K89: =dim_sca_labor_rate!$I89*2.93 -> 190.45
A90: C000016435 | B90: LMPLDT26 | C90: SSPC C3 Certified Lead Supervisor | D90: SSPC | E90: C3 Certified Lead Supervisor | F90: =dim_sca_labor_rate!$A90&" "&dim_sca_labor_rate!$D90&" "&dim_sca_labor_rate!$E90&"|"&dim_sca_labor_rate!$H90 -> C000016435 SSPC C3 Certified Lead Supervisor|3 | G90: B | H90: 3 | I90: 50 | J90: =dim_sca_labor_rate!$I90*3 -> 150 | K90: =dim_sca_labor_rate!$I90*2.93 -> 146.5
A91: C000016435 | B91: LMPMDT18 | C91: Mold Certified Industrial Hygienist | D91: Mold | E91: Certified Industrial Hygienist | F91: =dim_sca_labor_rate!$A91&" "&dim_sca_labor_rate!$D91&" "&dim_sca_labor_rate!$E91&"|"&dim_sca_labor_rate!$H91 -> C000016435 Mold Certified Industrial Hygienist| | I91: 48 | J91: =dim_sca_labor_rate!$I91*3 -> 144 | K91: =dim_sca_labor_rate!$I91*2.93 -> 140.64
A92: C000016435 | B92: LMPMDT17 | C92: Mold Field Technician | D92: Mold | E92: Field Technician | F92: =dim_sca_labor_rate!$A92&" "&dim_sca_labor_rate!$D92&" "&dim_sca_labor_rate!$E92&"|"&dim_sca_labor_rate!$H92 -> C000016435 Mold Field Technician|3 | H92: 3 | I92: 42 | J92: =dim_sca_labor_rate!$I92*3 -> 126 | K92: =dim_sca_labor_rate!$I92*2.93 -> 123.06
A93: C000016435 | B93: LMPMDT14 | C93: Mold Program Director | D93: Mold | E93: Program Director | F93: =dim_sca_labor_rate!$A93&" "&dim_sca_labor_rate!$D93&" "&dim_sca_labor_rate!$E93&"|"&dim_sca_labor_rate!$H93 -> C000016435 Mold Program Director|15 | H93: 15 | I93: 85 | J93: =dim_sca_labor_rate!$I93*3 -> 255 | K93: =dim_sca_labor_rate!$I93*2.93 -> 249.05
A94: C000016435 | B94: LMPMDT15 | C94: Mold Project Manager | D94: Mold | E94: Project Manager | F94: =dim_sca_labor_rate!$A94&" "&dim_sca_labor_rate!$D94&" "&dim_sca_labor_rate!$E94&"|"&dim_sca_labor_rate!$H94 -> C000016435 Mold Project Manager|7 | G94: A | H94: 7 | I94: 59 | J94: =dim_sca_labor_rate!$I94*3 -> 177 | K94: =dim_sca_labor_rate!$I94*2.93 -> 172.87
A95: C000016435 | B95: LMPMDT16 | C95: Mold Project Manager | D95: Mold | E95: Project Manager | F95: =dim_sca_labor_rate!$A95&" "&dim_sca_labor_rate!$D95&" "&dim_sca_labor_rate!$E95&"|"&dim_sca_labor_rate!$H95 -> C000016435 Mold Project Manager|3 | G95: B | H95: 3 | I95: 75 | J95: =dim_sca_labor_rate!$I95*3 -> 225 | K95: =dim_sca_labor_rate!$I95*2.93 -> 219.75
A96: C000016435 | B96: LMPPBT31 | C96: PCB Certified Industrial Hygienist | D96: PCB | E96: Certified Industrial Hygienist | F96: =dim_sca_labor_rate!$A96&" "&dim_sca_labor_rate!$D96&" "&dim_sca_labor_rate!$E96&"|"&dim_sca_labor_rate!$H96 -> C000016435 PCB Certified Industrial Hygienist| | I96: 85 | J96: =dim_sca_labor_rate!$I96*3 -> 255 | K96: =dim_sca_labor_rate!$I96*2.93 -> 249.05
A97: C000016435 | B97: LMPPBT29 | C97: PCB Field Technician | D97: PCB | E97: Field Technician | F97: =dim_sca_labor_rate!$A97&" "&dim_sca_labor_rate!$D97&" "&dim_sca_labor_rate!$E97&"|"&dim_sca_labor_rate!$H97 -> C000016435 PCB Field Technician|7 | G97: A | H97: 7 | I97: 50 | J97: =dim_sca_labor_rate!$I97*3 -> 150 | K97: =dim_sca_labor_rate!$I97*2.93 -> 146.5
A98: C000016435 | B98: LMPPBT30 | C98: PCB Field Technician | D98: PCB | E98: Field Technician | F98: =dim_sca_labor_rate!$A98&" "&dim_sca_labor_rate!$D98&" "&dim_sca_labor_rate!$E98&"|"&dim_sca_labor_rate!$H98 -> C000016435 PCB Field Technician|3 | G98: B | H98: 3 | I98: 43 | J98: =dim_sca_labor_rate!$I98*3 -> 129 | K98: =dim_sca_labor_rate!$I98*2.93 -> 125.99
A99: C000016435 | B99: LMPPBT27 | C99: PCB Program Director | D99: PCB | E99: Program Director | F99: =dim_sca_labor_rate!$A99&" "&dim_sca_labor_rate!$D99&" "&dim_sca_labor_rate!$E99&"|"&dim_sca_labor_rate!$H99 -> C000016435 PCB Program Director|15 | H99: 15 | I99: 65 | J99: =dim_sca_labor_rate!$I99*3 -> 195 | K99: =dim_sca_labor_rate!$I99*2.93 -> 190.45
A100: C000016435 | B100: LMPPBT28 | C100: PCB Project Manager | D100: PCB | E100: Project Manager | F100: =dim_sca_labor_rate!$A100&" "&dim_sca_labor_rate!$D100&" "&dim_sca_labor_rate!$E100&"|"&dim_sca_labor_rate!$H100 -> C000016435 PCB Project Manager|5 | H100: 5 | I100: 80 | J100: =dim_sca_labor_rate!$I100*3 -> 240 | K100: =dim_sca_labor_rate!$I100*2.93 -> 234.4

Sheet dim_labor_sca_map
A1: Category | B1: Title | C1: Years_Experience | D1: Map_SCA_Labor_Key | E1: SCA_Labor_Rate_Lookup | F1: MaxLoadFieldHourly | G1: Actual_Bill_Rate | H1: Contract_No
A2: Asbestos | B2: Project Monitor | C2: 7 | D2: =dim_labor_sca_map!$H2&" "&dim_labor_sca_map!$A2&" "&dim_labor_sca_map!$B2&"|"&dim_labor_sca_map!$C2 -> C000015128 Asbestos Project Monitor|7 | E2: {=XLOOKUP(dim_labor_sca_map!$D2, dim_sca_labor_rate!$F$2:$F$100, dim_sca_labor_rate!$J$2:$J$100, 0, 0)} -> 88.5277 | F2: =E2*2.41 -> 213.35176 | G2: =F2-E2 -> 124.82406 | H2: C000015128
A3: Asbestos | B3: Project Monitor | C3: 3 | D3: =dim_labor_sca_map!$H3&" "&dim_labor_sca_map!$A3&" "&dim_labor_sca_map!$B3&"|"&dim_labor_sca_map!$C3 -> C000015128 Asbestos Project Monitor|3 | E3: {=XLOOKUP(dim_labor_sca_map!$D3, dim_sca_labor_rate!$F$2:$F$100, dim_sca_labor_rate!$J$2:$J$100, 0, 0)} -> 88.5277 | F3: =E3*2.41 -> 213.35176 | G3: =F3-E3 -> 124.82406 | H3: C000015128
A4: Asbestos | B4: Air Testing | C4: 7 | D4: =dim_labor_sca_map!$H4&" "&dim_labor_sca_map!$A4&" "&dim_labor_sca_map!$B4&"|"&dim_labor_sca_map!$C4 -> C000015128 Asbestos Air Testing|7 | E4: {=XLOOKUP(dim_labor_sca_map!$D4, dim_sca_labor_rate!$F$2:$F$100, dim_sca_labor_rate!$J$2:$J$100, 0, 0)} -> 83.332 | F4: =E4*2.41 -> 200.83012 | G4: =F4-E4 -> 117.49812 | H4: C000015128
A5: Asbestos | B5: Air Testing | C5: 3 | D5: =dim_labor_sca_map!$H5&" "&dim_labor_sca_map!$A5&" "&dim_labor_sca_map!$B5&"|"&dim_labor_sca_map!$C5 -> C000015128 Asbestos Air Testing|3 | E5: {=XLOOKUP(dim_labor_sca_map!$D5, dim_sca_labor_rate!$F$2:$F$100, dim_sca_labor_rate!$J$2:$J$100, 0, 0)} -> 83.332 | F5: =E5*2.41 -> 200.83012 | G5: =F5-E5 -> 117.49812 | H5: C000015128
A6: Asbestos | B6: Investigator | C6: 3 | D6: =dim_labor_sca_map!$H6&" "&dim_labor_sca_map!$A6&" "&dim_labor_sca_map!$B6&"|"&dim_labor_sca_map!$C6 -> C000015128 Asbestos Investigator|3 | E6: {=XLOOKUP(dim_labor_sca_map!$D6, dim_sca_labor_rate!$F$2:$F$100, dim_sca_labor_rate!$J$2:$J$100, 0, 0)} -> 98.9442 | F6: =E6*2.41 -> 238.45552 | G6: =F6-E6 -> 139.51132 | H6: C000015128
A7: Asbestos | B7: Project Designer | C7: 3 | D7: =dim_labor_sca_map!$H7&" "&dim_labor_sca_map!$A7&" "&dim_labor_sca_map!$B7&"|"&dim_labor_sca_map!$C7 -> C000015128 Asbestos Project Designer|3 | E7: {=XLOOKUP(dim_labor_sca_map!$D7, dim_sca_labor_rate!$F$2:$F$100, dim_sca_labor_rate!$J$2:$J$100, 0, 0)} -> 93.7485 | F7: =E7*2.41 -> 225.93389 | G7: =F7-E7 -> 132.18538 | H7: C000015128
A8: Asbestos | B8: Project Manager | C8: 3 | D8: =dim_labor_sca_map!$H8&" "&dim_labor_sca_map!$A8&" "&dim_labor_sca_map!$B8&"|"&dim_labor_sca_map!$C8 -> C000015128 Asbestos Project Manager|3 | E8: {=XLOOKUP(dim_labor_sca_map!$D8, dim_sca_labor_rate!$F$2:$F$100, dim_sca_labor_rate!$J$2:$J$100, 0, 0)} -> 114.5564 | F8: =E8*2.41 -> 276.08092 | G8: =F8-E8 -> 161.52452 | H8: C000015128
A9: Lead | B9: Inspector | C9: 3 | D9: =dim_labor_sca_map!$H9&" "&dim_labor_sca_map!$A9&" "&dim_labor_sca_map!$B9&"|"&dim_labor_sca_map!$C9 -> C000015128 Lead Inspector|3 | E9: {=XLOOKUP(dim_labor_sca_map!$D9, dim_sca_labor_rate!$F$2:$F$100, dim_sca_labor_rate!$J$2:$J$100, 0, 0)} -> 78.1112 | F9: =E9*2.41 -> 188.24799 | G9: =F9-E9 -> 110.13679 | H9: C000015128
A10: Lead | B10: Inspector / Risk Assessor | C10: 3 | D10: =dim_labor_sca_map!$H10&" "&dim_labor_sca_map!$A10&" "&dim_labor_sca_map!$B10&"|"&dim_labor_sca_map!$C10 -> C000015128 Lead Inspector / Risk Assessor|3 | E10: {=XLOOKUP(dim_labor_sca_map!$D10, dim_sca_labor_rate!$F$2:$F$100, dim_sca_labor_rate!$J$2:$J$100, 0, 0)} -> 98.9442 | F10: =E10*2.41 -> 238.45552 | G10: =F10-E10 -> 139.51132 | H10: C000015128
A11: PCB | B11: Field Technician | C11: 3 | D11: =dim_labor_sca_map!$H11&" "&dim_labor_sca_map!$A11&" "&dim_labor_sca_map!$B11&"|"&dim_labor_sca_map!$C11 -> C000015128 PCB Field Technician|3 | E11: {=XLOOKUP(dim_labor_sca_map!$D11, dim_sca_labor_rate!$F$2:$F$100, dim_sca_labor_rate!$J$2:$J$100, 0, 0)} -> 78.1112 | F11: =E11*2.41 -> 188.24799 | G11: =F11-E11 -> 110.13679 | H11: C000015128
A12: Asbestos | B12: Investigator | C12: 7 | D12: =dim_labor_sca_map!$H12&" "&dim_labor_sca_map!$A12&" "&dim_labor_sca_map!$B12&"|"&dim_labor_sca_map!$C12 -> C000015128 Asbestos Investigator|7 | E12: {=XLOOKUP(dim_labor_sca_map!$D12, dim_sca_labor_rate!$F$2:$F$100, dim_sca_labor_rate!$J$2:$J$100, 0, 0)} -> 114.5815 | F12: =E12*2.41 -> 276.14141 | G12: =F12-E12 -> 161.55991 | H12: C000015128
A13: Asbestos | B13: Project Designer | C13: 7 | D13: =dim_labor_sca_map!$H13&" "&dim_labor_sca_map!$A13&" "&dim_labor_sca_map!$B13&"|"&dim_labor_sca_map!$C13 -> C000015128 Asbestos Project Designer|7 | E13: {=XLOOKUP(dim_labor_sca_map!$D13, dim_sca_labor_rate!$F$2:$F$100, dim_sca_labor_rate!$J$2:$J$100, 0, 0)} -> 114.5815 | F13: =E13*2.41 -> 276.14141 | G13: =F13-E13 -> 161.55991 | H13: C000015128
... A21: Asbestos | B21: Project Monitor | C21: 7 | D21: =dim_labor_sca_map!$H21&" "&dim_labor_sca_map!$A21&" "&dim_labor_sca_map!$B21&"|"&dim_labor_sca_map!$C21 -> C000015869 Asbestos Project Monitor|7 | E21: {=XLOOKUP(dim_labor_sca_map!$D21, dim_sca_labor_rate!$F$2:$F$100, dim_sca_labor_rate!$J$2:$J$100, 0, 0)} -> 104.5 | F21: =E21*2.41 -> 251.845 | G21: =F21-E21 -> 147.345 | H21: C000015869
A22: Asbestos | B22: Project Monitor | C22: 3 | D22: =dim_labor_sca_map!$H22&" "&dim_labor_sca_map!$A22&" "&dim_labor_sca_map!$B22&"|"&dim_labor_sca_map!$C22 -> C000015869 Asbestos Project Monitor|3 | E22: {=XLOOKUP(dim_labor_sca_map!$D22, dim_sca_labor_rate!$F$2:$F$100, dim_sca_labor_rate!$J$2:$J$100, 0, 0)} -> 104.5 | F22: =E22*2.54 -> 265.43 | G22: =F22-E22 -> 160.93 | H22: C000015869
A23: Asbestos | B23: Air Testing | C23: 3 | D23: =dim_labor_sca_map!$H23&" "&dim_labor_sca_map!$A23&" "&dim_labor_sca_map!$B23&"|"&dim_labor_sca_map!$C23 -> C000015869 Asbestos Air Testing|3 | E23: {=XLOOKUP(dim_labor_sca_map!$D23, dim_sca_labor_rate!$F$2:$F$100, dim_sca_labor_rate!$J$2:$J$100, 0, 0)} -> 99 | F23: =E23*2.54 -> 251.46 | G23: =F23-E23 -> 152.46 | H23: C000015869
A24: Asbestos | B24: Air Testing | C24: 7 | D24: =dim_labor_sca_map!$H24&" "&dim_labor_sca_map!$A24&" "&dim_labor_sca_map!$B24&"|"&dim_labor_sca_map!$C24 -> C000015869 Asbestos Air Testing|7 | E24: {=XLOOKUP(dim_labor_sca_map!$D24, dim_sca_labor_rate!$F$2:$F$100, dim_sca_labor_rate!$J$2:$J$100, 0, 0)} -> 99 | F24: =E24*2.54 -> 251.46 | G24: =F24-E24 -> 152.46 | H24: C000015869
A25: Asbestos | B25: Investigator | C25: 3 | D25: =dim_labor_sca_map!$H25&" "&dim_labor_sca_map!$A25&" "&dim_labor_sca_map!$B25&"|"&dim_labor_sca_map!$C25 -> C000015869 Asbestos Investigator|3 | E25: {=XLOOKUP(dim_labor_sca_map!$D25, dim_sca_labor_rate!$F$2:$F$100, dim_sca_labor_rate!$J$2:$J$100, 0, 0)} -> 115.5 | F25: =E25*2.54 -> 293.37 | G25: =F25-E25 -> 177.87 | H25: C000015869
A26: Asbestos | B26: Project Designer | C26: 3 | D26: =dim_labor_sca_map!$H26&" "&dim_labor_sca_map!$A26&" "&dim_labor_sca_map!$B26&"|"&dim_labor_sca_map!$C26 -> C000015869 Asbestos Project Designer|3 | E26: {=XLOOKUP(dim_labor_sca_map!$D26, dim_sca_labor_rate!$F$2:$F$100, dim_sca_labor_rate!$J$2:$J$100, 0, 0)} -> 123.75 | F26: =E26*2.54 -> 314.325 | G26: =F26-E26 -> 190.575 | H26: C000015869
A27: Asbestos | B27: Project Manager | C27: 3 | D27: =dim_labor_sca_map!$H27&" "&dim_labor_sca_map!$A27&" "&dim_labor_sca_map!$B27&"|"&dim_labor_sca_map!$C27 -> C000015869 Asbestos Project Manager|3 | E27: {=XLOOKUP(dim_labor_sca_map!$D27, dim_sca_labor_rate!$F$2:$F$100, dim_sca_labor_rate!$J$2:$J$100, 0, 0)} -> 126.5 | F27: =E27*2.54 -> 321.31 | G27: =F27-E27 -> 194.81 | H27: C000015869
A28: Lead | B28: Inspector | C28: 3 | D28: =dim_labor_sca_map!$H28&" "&dim_labor_sca_map!$A28&" "&dim_labor_sca_map!$B28&"|"&dim_labor_sca_map!$C28 -> C000015869 Lead Inspector|3 | E28: {=XLOOKUP(dim_labor_sca_map!$D28, dim_sca_labor_rate!$F$2:$F$100, dim_sca_labor_rate!$J$2:$J$100, 0, 0)} -> 96.25 | F28: =E28*2.54 -> 244.475 | G28: =F28-E28 -> 148.225 | H28: C000015869
A29: Lead | B29: Inspector / Risk Assessor | C29: 3 | D29: =dim_labor_sca_map!$H29&" "&dim_labor_sca_map!$A29&" "&dim_labor_sca_map!$B29&"|"&dim_labor_sca_map!$C29 -> C000015869 Lead Inspector / Risk Assessor|3 | E29: {=XLOOKUP(dim_labor_sca_map!$D29, dim_sca_labor_rate!$F$2:$F$100, dim_sca_labor_rate!$J$2:$J$100, 0, 0)} -> 107.25 | F29: =E29*2.54 -> 272.415 | G29: =F29-E29 -> 165.165 | H29: C000015869
A30: PCB | B30: Field Technician | C30: 3 | D30: =dim_labor_sca_map!$H30&" "&dim_labor_sca_map!$A30&" "&dim_labor_sca_map!$B30&"|"&dim_labor_sca_map!$C30 -> C000015869 PCB Field Technician|3 | E30: {=XLOOKUP(dim_labor_sca_map!$D30, dim_sca_labor_rate!$F$2:$F$100, dim_sca_labor_rate!$J$2:$J$100, 0, 0)} -> 85.25 | F30: =E30*2.54 -> 216.535 | G30: =F30-E30 -> 131.285 | H30: C000015869
A31: Asbestos | B31: Investigator | C31: 7 | D31: =dim_labor_sca_map!$H31&" "&dim_labor_sca_map!$A31&" "&dim_labor_sca_map!$B31&"|"&dim_labor_sca_map!$C31 -> C000015869 Asbestos Investigator|7 | E31: {=XLOOKUP(dim_labor_sca_map!$D31, dim_sca_labor_rate!$F$2:$F$100, dim_sca_labor_rate!$J$2:$J$100, 0, 0)} -> 134.75 | F31: =E31*2.54 -> 342.265 | G31: =F31-E31 -> 207.515 | H31: C000015869
A32: Asbestos | B32: Project Designer | C32: 7 | D32: =dim_labor_sca_map!$H32&" "&dim_labor_sca_map!$A32&" "&dim_labor_sca_map!$B32&"|"&dim_labor_sca_map!$C32 -> C000015869 Asbestos Project Designer|7 | E32: {=XLOOKUP(dim_labor_sca_map!$D32, dim_sca_labor_rate!$F$2:$F$100, dim_sca_labor_rate!$J$2:$J$100, 0, 0)} -> 151.25 | F32: =E32*2.54 -> 384.175 | G32: =F32-E32 -> 232.925 | H32: C000015869
A33: Asbestos | B33: Project Manager | C33: 7 | D33: =dim_labor_sca_map!$H33&" "&dim_labor_sca_map!$A33&" "&dim_labor_sca_map!$B33&"|"&dim_labor_sca_map!$C33 -> C000015869 Asbestos Project Manager|7 | E33: {=XLOOKUP(dim_labor_sca_map!$D33, dim_sca_labor_rate!$F$2:$F$100, dim_sca_labor_rate!$J$2:$J$100, 0, 0)} -> 167.75 | F33: =E33*2.54 -> 426.085 | G33: =F33-E33 -> 258.335 | H33: C000015869
... A35: Lead | B35: Inspector / Risk Assessor | C35: 7 | D35: =dim_labor_sca_map!$H35&" "&dim_labor_sca_map!$A35&" "&dim_labor_sca_map!$B35&"|"&dim_labor_sca_map!$C35 -> C000015869 Lead Inspector / Risk Assessor|7 | E35: {=XLOOKUP(dim_labor_sca_map!$D35, dim_sca_labor_rate!$F$2:$F$100, dim_sca_labor_rate!$J$2:$J$100, 0, 0)} -> 140.25 | F35: =E35*2.54 -> 356.235 | G35: =F35-E35 -> 215.985 | H35: C000015869
A36: PCB | B36: Field Technician | C36: 7 | D36: =dim_labor_sca_map!$H36&" "&dim_labor_sca_map!$A36&" "&dim_labor_sca_map!$B36&"|"&dim_labor_sca_map!$C36 -> C000015869 PCB Field Technician|7 | E36: {=XLOOKUP(dim_labor_sca_map!$D36, dim_sca_labor_rate!$F$2:$F$100, dim_sca_labor_rate!$J$2:$J$100, 0, 0)} -> 99 | F36: =E36*2.41 -> 238.59 | G36: =F36-E36 -> 139.59 | H36: C000015869
A37: PCB | B37: Field Technician | C37: 3 | D37: =dim_labor_sca_map!$H37&" "&dim_labor_sca_map!$A37&" "&dim_labor_sca_map!$B37&"|"&dim_labor_sca_map!$C37 -> C000015869 PCB Field Technician|3 | E37: {=XLOOKUP(dim_labor_sca_map!$D37, dim_sca_labor_rate!$F$2:$F$100, dim_sca_labor_rate!$J$2:$J$100, 0, 0)} -> 85.25 | F37: =E37*2.41 -> 205.4525 | G37: =F37-E37 -> 120.2025 | H37: C000015869
A38: Asbestos | B38: Inspector | C38: 3 | D38: =dim_labor_sca_map!$H38&" "&dim_labor_sca_map!$A38&" "&dim_labor_sca_map!$B38&"|"&dim_labor_sca_map!$C38 -> C000015869 Asbestos Inspector|3 | E38: {=XLOOKUP(dim_labor_sca_map!$D38, dim_sca_labor_rate!$F$2:$F$100, dim_sca_labor_rate!$J$2:$J$100, 0, 0)} -> 99 | F38: =E38*2.41 -> 238.59 | G38: =F38-E38 -> 139.59 | H38: C000015869
A39: Asbestos | B39: Inspector | C39: 7 | D39: =dim_labor_sca_map!$H39&" "&dim_labor_sca_map!$A39&" "&dim_labor_sca_map!$B39&"|"&dim_labor_sca_map!$C39 -> C000015869 Asbestos Inspector|7 | E39: {=XLOOKUP(dim_labor_sca_map!$D39, dim_sca_labor_rate!$F$2:$F$100, dim_sca_labor_rate!$J$2:$J$100, 0, 0)} -> 118.25 | F39: =E39*2.41 -> 284.9825 | G39: =F39-E39 -> 166.7325 | H39: C000015869
A40: Asbestos | B40: Project Monitor | C40: 3 | D40: =dim_labor_sca_map!$H40&" "&dim_labor_sca_map!$A40&" "&dim_labor_sca_map!$B40&"|"&dim_labor_sca_map!$C40 -> C000016435 Asbestos Project Monitor|3 | E40: {=XLOOKUP(dim_labor_sca_map!$D40, dim_sca_labor_rate!$F$2:$F$100, dim_sca_labor_rate!$J$2:$J$100, 0, 0)} -> 144 | F40: =E40*2.93 -> 421.92 | G40: =F40-E40 -> 277.92 | H40: C000016435
A41: Asbestos | B41: Project Monitor | C41: 7 | D41: =dim_labor_sca_map!$H41&" "&dim_labor_sca_map!$A41&" "&dim_labor_sca_map!$B41&"|"&dim_labor_sca_map!$C41 -> C000016435 Asbestos Project Monitor|7 | E41: {=XLOOKUP(dim_labor_sca_map!$D41, dim_sca_labor_rate!$F$2:$F$100, dim_sca_labor_rate!$J$2:$J$100, 0, 0)} -> 144 | F41: =E41*2.93 -> 421.92 | G41: =F41-E41 -> 277.92 | H41: C000016435
A42: Asbestos | B42: Air Testing | C42: 3 | D42: =dim_labor_sca_map!$H42&" "&dim_labor_sca_map!$A42&" "&dim_labor_sca_map!$B42&"|"&dim_labor_sca_map!$C42 -> C000016435 Asbestos Air Testing|3 | E42: {=XLOOKUP(dim_labor_sca_map!$D42, dim_sca_labor_rate!$F$2:$F$100, dim_sca_labor_rate!$J$2:$J$100, 0, 0)} -> 132 | F42: =E42*2.93 -> 386.76 | G42: =F42-E42 -> 254.76 | H42: C000016435
A43: Asbestos | B43: Air Testing | C43: 7 | D43: =dim_labor_sca_map!$H43&" "&dim_labor_sca_map!$A43&" "&dim_labor_sca_map!$B43&"|"&dim_labor_sca_map!$C43 -> C000016435 Asbestos Air Testing|7 | E43: {=XLOOKUP(dim_labor_sca_map!$D43, dim_sca_labor_rate!$F$2:$F$100, dim_sca_labor_rate!$J$2:$J$100, 0, 0)} -> 132 | F43: =E43*2.93 -> 386.76 | G43: =F43-E43 -> 254.76 | H43: C000016435
A44: Asbestos | B44: Investigator | C44: 3 | D44: =dim_labor_sca_map!$H44&" "&dim_labor_sca_map!$A44&" "&dim_labor_sca_map!$B44&"|"&dim_labor_sca_map!$C44 -> C000016435 Asbestos Investigator|3 | E44: {=XLOOKUP(dim_labor_sca_map!$D44, dim_sca_labor_rate!$F$2:$F$100, dim_sca_labor_rate!$J$2:$J$100, 0, 0)} -> 180 | F44: =E44*2.93 -> 527.4 | G44: =F44-E44 -> 347.4 | H44: C000016435
A45: Asbestos | B45: Project Designer | C45: 3 | D45: =dim_labor_sca_map!$H45&" "&dim_labor_sca_map!$A45&" "&dim_labor_sca_map!$B45&"|"&dim_labor_sca_map!$C45 -> C000016435 Asbestos Project Designer|3 | E45: {=XLOOKUP(dim_labor_sca_map!$D45, dim_sca_labor_rate!$F$2:$F$100, dim_sca_labor_rate!$J$2:$J$100, 0, 0)} -> 189 | F45: =E45*2.93 -> 553.77 | G45: =F45-E45 -> 364.77 | H45: C000016435
A46: Asbestos | B46: Project Manager | C46: 3 | D46: =dim_labor_sca_map!$H46&" "&dim_labor_sca_map!$A46&" "&dim_labor_sca_map!$B46&"|"&dim_labor_sca_map!$C46 -> C000016435 Asbestos Project Manager|3 | E46: {=XLOOKUP(dim_labor_sca_map!$D46, dim_sca_labor_rate!$F$2:$F$100, dim_sca_labor_rate!$J$2:$J$100, 0, 0)} -> 201 | F46: =E46*2.93 -> 588.93 | G46: =F46-E46 -> 387.93 | H46: C000016435
A47: Lead | B47: Inspector | C47: 3 | D47: =dim_labor_sca_map!$H47&" "&dim_labor_sca_map!$A47&" "&dim_labor_sca_map!$B47&"|"&dim_labor_sca_map!$C47 -> C000016435 Lead Inspector|3 | E47: {=XLOOKUP(dim_labor_sca_map!$D47, dim_sca_labor_rate!$F$2:$F$100, dim_sca_labor_rate!$J$2:$J$100, 0, 0)} -> 135 | F47: =E47*2.93 -> 395.55 | G47: =F47-E47 -> 260.55 | H47: C000016435
A48: Lead | B48: Inspector / Risk Assessor | C48: 3 | D48: =dim_labor_sca_map!$H48&" "&dim_labor_sca_map!$A48&" "&dim_labor_sca_map!$B48&"|"&dim_labor_sca_map!$C48 -> C000016435 Lead Inspector / Risk Assessor|3 | E48: {=XLOOKUP(dim_labor_sca_map!$D48, dim_sca_labor_rate!$F$2:$F$100, dim_sca_labor_rate!$J$2:$J$100, 0, 0)} -> 183 | F48: =E48*2.93 -> 536.19 | G48: =F48-E48 -> 353.19 | H48: C000016435
A49: PCB | B49: Field Technician | C49: 3 | D49: =dim_labor_sca_map!$H49&" "&dim_labor_sca_map!$A49&" "&dim_labor_sca_map!$B49&"|"&dim_labor_sca_map!$C49 -> C000016435 PCB Field Technician|3 | E49: {=XLOOKUP(dim_labor_sca_map!$D49, dim_sca_labor_rate!$F$2:$F$100, dim_sca_labor_rate!$J$2:$J$100, 0, 0)} -> 129 | F49: =E49*2.93 -> 377.97 | G49: =F49-E49 -> 248.97 | H49: C000016435
A50: Asbestos | B50: Investigator | C50: 7 | D50: =dim_labor_sca_map!$H50&" "&dim_labor_sca_map!$A50&" "&dim_labor_sca_map!$B50&"|"&dim_labor_sca_map!$C50 -> C000016435 Asbestos Investigator|7 | E50: {=XLOOKUP(dim_labor_sca_map!$D50, dim_sca_labor_rate!$F$2:$F$100, dim_sca_labor_rate!$J$2:$J$100, 0, 0)} -> 201 | F50: =E50*2.93 -> 588.93 | G50: =F50-E50 -> 387.93 | H50: C000016435
A51: Asbestos | B51: Project Designer | C51: 7 | D51: =dim_labor_sca_map!$H51&" "&dim_labor_sca_map!$A51&" "&dim_labor_sca_map!$B51&"|"&dim_labor_sca_map!$C51 -> C000016435 Asbestos Project Designer|7 | E51: {=XLOOKUP(dim_labor_sca_map!$D51, dim_sca_labor_rate!$F$2:$F$100, dim_sca_labor_rate!$J$2:$J$100, 0, 0)} -> 216 | F51: =E51*2.93 -> 632.88 | G51: =F51-E51 -> 416.88 | H51: C000016435
... A58: Asbestos | B58: Inspector | C58: 7 | D58: =dim_labor_sca_map!$H58&" "&dim_labor_sca_map!$A58&" "&dim_labor_sca_map!$B58&"|"&dim_labor_sca_map!$C58 -> C000016435 Asbestos Inspector|7 | E58: {=XLOOKUP(dim_labor_sca_map!$D58, dim_sca_labor_rate!$F$2:$F$100, dim_sca_labor_rate!$J$2:$J$100, 0, 0)} -> 165 | F58: =E58*2.93 -> 483.45 | G58: =F58-E58 -> 318.45 | H58: C000016435

Sheet dim_lab_sca_rates
A1: Contract_No | B1: Test_Code | C1: SCA_Lab_Key | D1: Sample_Type | E1: Test_Description | F1: TATime | G1: Test_Rate | H1: Check_Duplicates
A2: C000015128 | B2: LMPACM56 | C2: =TRIM(dim_lab_sca_rates!$A2&"|"&dim_lab_sca_rates!$D2&"|"&dim_lab_sca_rates!$F2) -> C000015128|Amph|10 Day | D2: Amph | E2: NYS 198.8 Segment II:Amphibole Prep and Analysis | F2: 10 Day | G2: 275 | H2: =dim_lab_sca_rates!$A2&"|"&dim_lab_sca_rates!$B2&"|"&dim_lab_sca_rates!$F2 -> C000015128|LMPACM56|10 Day
A3: C000015128 | B3: LMPACM56 | C3: =TRIM(dim_lab_sca_rates!$A3&"|"&dim_lab_sca_rates!$D3&"|"&dim_lab_sca_rates!$F3) -> C000015128|Amph|2 Day | D3: Amph | E3: NYS 198.8 Segment II:Amphibole Prep and Analysis | F3: 2 Day | G3: 550 | H3: =dim_lab_sca_rates!$A3&"|"&dim_lab_sca_rates!$B3&"|"&dim_lab_sca_rates!$F3 -> C000015128|LMPACM56|2 Day
A4: C000015128 | B4: LMPACM56 | C4: =TRIM(dim_lab_sca_rates!$A4&"|"&dim_lab_sca_rates!$D4&"|"&dim_lab_sca_rates!$F4) -> C000015128|Amph|5 Day | D4: Amph | E4: NYS 198.8 Segment II:Amphibole Prep and Analysis | F4: 5 Day | G4: 375 | H4: =dim_lab_sca_rates!$A4&"|"&dim_lab_sca_rates!$B4&"|"&dim_lab_sca_rates!$F4 -> C000015128|LMPACM56|5 Day
A5: C000015128 | B5: LMPACM58 | C5: =TRIM(dim_lab_sca_rates!$A5&"|"&dim_lab_sca_rates!$D5&"|"&dim_lab_sca_rates!$F5) -> C000015128|Chrys|2 Day | D5: Chrys | E5: NYS 198.8 Segment I:Chrysotile Prep and Analysis | F5: 2 Day | G5: 400 | H5: =dim_lab_sca_rates!$A5&"|"&dim_lab_sca_rates!$B5&"|"&dim_lab_sca_rates!$F5 -> C000015128|LMPACM58|2 Day
A6: C000015128 | B6: LMPACM58 | C6: =TRIM(dim_lab_sca_rates!$A6&"|"&dim_lab_sca_rates!$D6&"|"&dim_lab_sca_rates!$F6) -> C000015128|Chrys|5 Day | D6: Chrys | E6: NYS 198.8 Segment I:Chrysotile Prep and Analysis | F6: 5 Day | G6: 310 | H6: =dim_lab_sca_rates!$A6&"|"&dim_lab_sca_rates!$B6&"|"&dim_lab_sca_rates!$F6 -> C000015128|LMPACM58|5 Day
A7: C000015128 | B7: LMPACM58 | C7: =TRIM(dim_lab_sca_rates!$A7&"|"&dim_lab_sca_rates!$D7&"|"&dim_lab_sca_rates!$F7) -> C000015128|Chrys|10 Day | D7: Chrys | E7: NYS 198.8 Segment I:Chrysotile Prep and Analysis | F7: 10 Day | G7: 225 | H7: =dim_lab_sca_rates!$A7&"|"&dim_lab_sca_rates!$B7&"|"&dim_lab_sca_rates!$F7 -> C000015128|LMPACM58|10 Day
A8: C000015128 | B8: LMPACMC1 | C8: =TRIM(dim_lab_sca_rates!$A8&"|"&dim_lab_sca_rates!$D8&"|"&dim_lab_sca_rates!$F8) -> C000015128|PLM|1 Hr | D8: PLM | E8: Unit Price-Bulk SamplAnalysis by PLM/DS | F8: 1 Hr | G8: 30 | H8: =dim_lab_sca_rates!$A8&"|"&dim_lab_sca_rates!$B8&"|"&dim_lab_sca_rates!$F8 -> C000015128|LMPACMC1|1 Hr
A9: C000015128 | B9: LMPACMC1 | C9: =TRIM(dim_lab_sca_rates!$A9&"|"&dim_lab_sca_rates!$D9&"|"&dim_lab_sca_rates!$F9) -> C000015128|PLM|24 Hr | D9: PLM | E9: Unit Price-Bulk SamplAnalysis by PLM/DS | F9: 24 Hr | G9: 22 | H9: =dim_lab_sca_rates!$A9&"|"&dim_lab_sca_rates!$B9&"|"&dim_lab_sca_rates!$F9 -> C000015128|LMPACMC1|24 Hr
A10: C000015128 | B10: LMPACMC1 | C10: =TRIM(dim_lab_sca_rates!$A10&"|"&dim_lab_sca_rates!$D10&"|"&dim_lab_sca_rates!$F10) -> C000015128|PLM|6 Hr | D10: PLM | E10: Unit Price-Bulk SamplAnalysis by PLM/DS | F10: 6 Hr | G10: 25 | H10: =dim_lab_sca_rates!$A10&"|"&dim_lab_sca_rates!$B10&"|"&dim_lab_sca_rates!$F10 -> C000015128|LMPACMC1|6 Hr
A11: C000015128 | B11: LMPACMC2 | C11: =TRIM(dim_lab_sca_rates!$A11&"|"&dim_lab_sca_rates!$D11&"|"&dim_lab_sca_rates!$F11) -> C000015128|PCM|6 Hr | D11: PCM | E11: Unit Price-Airborne FFiber Analysis by PCM | F11: 6 Hr | G11: 22 | H11: =dim_lab_sca_rates!$A11&"|"&dim_lab_sca_rates!$B11&"|"&dim_lab_sca_rates!$F11 -> C000015128|LMPACMC2|6 Hr
A12: C000015128 | B12: LMPACMC2 | C12: =TRIM(dim_lab_sca_rates!$A12&"|"&dim_lab_sca_rates!$D12&"|"&dim_lab_sca_rates!$F12) -> C000015128|PCM|1 Hr | D12: PCM | E12: Unit Price-Airborne FFiber Analysis by PCM | F12: 1 Hr | G12: 25 | H12: =dim_lab_sca_rates!$A12&"|"&dim_lab_sca_rates!$B12&"|"&dim_lab_sca_rates!$F12 -> C000015128|LMPACMC2|1 Hr
A13: C000015128 | B13: LMPACMC2 | C13: =TRIM(dim_lab_sca_rates!$A13&"|"&dim_lab_sca_rates!$D13&"|"&dim_lab_sca_rates!$F13) -> C000015128|PCM|24 Hr | D13: PCM | E13: Unit Price-Airborne FFiber Analysis by PCM | F13: 24 Hr | G13: 20 | H13: =dim_lab_sca_rates!$A13&"|"&dim_lab_sca_rates!$B13&"|"&dim_lab_sca_rates!$F13 -> C000015128|LMPACMC2|24 Hr
... A316: C000016435 | B316: LMPPCBC32 | C316: =TRIM(dim_lab_sca_rates!$A316&"|"&dim_lab_sca_rates!$D316&"|"&dim_lab_sca_rates!$F316) -> C000016435|PCB Waste / Wash Water|5 Day | D316: PCB Waste / Wash Water | E316: Waste / Wash Water | F316: 5 Day | G316: 140 | H316: =dim_lab_sca_rates!$A316&"|"&dim_lab_sca_rates!$B316&"|"&dim_lab_sca_rates!$F316 -> C000016435|LMPPCBC32|5 Day

Sheet dim_lab_vendor_rates
A1: Facility_Sample | B1: Facility | C1: Sample | D1: TAT | E1: Rate
A2: =dim_lab_vendor_rates!$B2 & "|" & dim_lab_vendor_rates!$C2 -> ALLAB|PLM | B2: ALLAB | C2: PLM | D2: 24 Hr | E2: 5
A3: =dim_lab_vendor_rates!$B3 & "|" & dim_lab_vendor_rates!$C3 -> ALLAB|NOB-PLM | B3: ALLAB | C3: NOB-PLM | D3: 24 Hr | E3: 9.5
A4: =dim_lab_vendor_rates!$B4 & "|" & dim_lab_vendor_rates!$C4 -> ALLAB|NOB-TEM | B4: ALLAB | C4: NOB-TEM | D4: 24 Hr | E4: 20
A5: =dim_lab_vendor_rates!$B5 & "|" & dim_lab_vendor_rates!$C5 -> ALLAB|DAF | B5: ALLAB | C5: DAF | D5: 1 Hr | E5: 5
A6: =dim_lab_vendor_rates!$B6 & "|" & dim_lab_vendor_rates!$C6 -> ALLAB|FINALS | B6: ALLAB | C6: FINALS | D6: 1 Hr | E6: 5
A7: =dim_lab_vendor_rates!$B7 & "|" & dim_lab_vendor_rates!$C7 -> ALLAB|DURINGS | B7: ALLAB | C7: DURINGS | D7: 24 Hr | E7: 5
A8: =dim_lab_vendor_rates!$B8 & "|" & dim_lab_vendor_rates!$C8 -> ALLAB|TEM | B8: ALLAB | C8: TEM | D8: 3 Hr | E8: 20
A9: =dim_lab_vendor_rates!$B9 & "|" & dim_lab_vendor_rates!$C9 -> ALLAB|BACKGROUNDS | B9: ALLAB | C9: BACKGROUNDS | D9: 24 Hr | E9: 5
A10: =dim_lab_vendor_rates!$B10 & "|" & dim_lab_vendor_rates!$C10 -> ALLAB|PRE | B10: ALLAB | C10: PRE | D10: 24 Hr | E10: 5
A11: =dim_lab_vendor_rates!$B11 & "|" & dim_lab_vendor_rates!$C11 -> ALLAB|SLIDE PREP | B11: ALLAB | C11: SLIDE PREP | D11: 0 Hr | E11: 5
A12: =dim_lab_vendor_rates!$B12 & "|" & dim_lab_vendor_rates!$C12 -> ALLAB|VERMICULITE | B12: ALLAB | C12: VERMICULITE | D12: 10 Day | E12: 200
A13: =dim_lab_vendor_rates!$B13 & "|" & dim_lab_vendor_rates!$C13 -> ATC|PLM | B13: ATC | C13: PLM | D13: 24 Hr | E13: 0
... A49: =dim_lab_vendor_rates!$B49 & "|" & dim_lab_vendor_rates!$C49 -> LTS|CHRYS-2 DAY | B49: LTS | C49: CHRYS-2 DAY | D49: 2 Day | E49: 230

Sheet dim_lab_sca_map
A1: Map_Key | B1: SCA_Sample_Name | C1: Vendor_Sample_Name | D1: TAT | E1: SCA_Rate_Lookup | F1: Contract_No | G1: Final_Key
A2: =dim_lab_sca_map!$B2&"|"&dim_lab_sca_map!$D2 -> PLM|24 Hr | B2: PLM | C2: PLM | D2: 24 Hr | E2: {=XLOOKUP(TRIM(dim_lab_sca_map!$G2), TRIM(dim_lab_sca_rates!$C$2:$C$316), dim_lab_sca_rates!$G$2:$G$316, 0, 0)} -> 22 | F2: C000015128 | G2: =dim_lab_sca_map!$F2&"|"&dim_lab_sca_map!$A2 -> C000015128|PLM|24 Hr
A3: =dim_lab_sca_map!$B3&"|"&dim_lab_sca_map!$D3 -> NOB-PLM|24 Hr | B3: NOB-PLM | C3: NOB-PLM | D3: 24 Hr | E3: {=XLOOKUP(TRIM(dim_lab_sca_map!$G3), TRIM(dim_lab_sca_rates!$C$2:$C$316), dim_lab_sca_rates!$G$2:$G$316, 0, 0)} -> 35 | F3: C000015128 | G3: =dim_lab_sca_map!$F3&"|"&dim_lab_sca_map!$A3 -> C000015128|NOB-PLM|24 Hr
A4: =dim_lab_sca_map!$B4&"|"&dim_lab_sca_map!$D4 -> NOB-TEM|24 Hr | B4: NOB-TEM | C4: NOB-TEM | D4: 24 Hr | E4: {=XLOOKUP(TRIM(dim_lab_sca_map!$G4), TRIM(dim_lab_sca_rates!$C$2:$C$316), dim_lab_sca_rates!$G$2:$G$316, 0, 0)} -> 70 | F4: C000015128 | G4: =dim_lab_sca_map!$F4&"|"&dim_lab_sca_map!$A4 -> C000015128|NOB-TEM|24 Hr
A5: =dim_lab_sca_map!$B5&"|"&dim_lab_sca_map!$D5 -> PCM|1 Hr | B5: PCM | C5: DAF | D5: 1 Hr | E5: {=XLOOKUP(TRIM(dim_lab_sca_map!$G5), TRIM(dim_lab_sca_rates!$C$2:$C$316), dim_lab_sca_rates!$G$2:$G$316, 0, 0)} -> 25 | F5: C000015128 | G5: =dim_lab_sca_map!$F5&"|"&dim_lab_sca_map!$A5 -> C000015128|PCM|1 Hr
A6: =dim_lab_sca_map!$B6&"|"&dim_lab_sca_map!$D6 -> PCM|1 Hr | B6: PCM | C6: FINALS | D6: 1 Hr | E6: {=XLOOKUP(TRIM(dim_lab_sca_map!$G6), TRIM(dim_lab_sca_rates!$C$2:$C$316), dim_lab_sca_rates!$G$2:$G$316, 0, 0)} -> 25 | F6: C000015128 | G6: =dim_lab_sca_map!$F6&"|"&dim_lab_sca_map!$A6 -> C000015128|PCM|1 Hr
A7: =dim_lab_sca_map!$B7&"|"&dim_lab_sca_map!$D7 -> PCM|24 Hr | B7: PCM | C7: DURINGS | D7: 24 Hr | E7: {=XLOOKUP(TRIM(dim_lab_sca_map!$G7), TRIM(dim_lab_sca_rates!$C$2:$C$316), dim_lab_sca_rates!$G$2:$G$316, 0, 0)} -> 20 | F7: C000015128 | G7: =dim_lab_sca_map!$F7&"|"&dim_lab_sca_map!$A7 -> C000015128|PCM|24 Hr
A8: =dim_lab_sca_map!$B8&"|"&dim_lab_sca_map!$D8 -> TEM|3 Hr | B8: TEM | C8: TEM | D8: 3 Hr | E8: {=XLOOKUP(TRIM(dim_lab_sca_map!$G8), TRIM(dim_lab_sca_rates!$C$2:$C$316), dim_lab_sca_rates!$G$2:$G$316, 0, 0)} -> 145 | F8: C000015128 | G8: =dim_lab_sca_map!$F8&"|"&dim_lab_sca_map!$A8 -> C000015128|TEM|3 Hr
A9: =dim_lab_sca_map!$B9&"|"&dim_lab_sca_map!$D9 -> PCM|24 Hr | B9: PCM | C9: BACKGROUNDS | D9: 24 Hr | E9: {=XLOOKUP(TRIM(dim_lab_sca_map!$G9), TRIM(dim_lab_sca_rates!$C$2:$C$316), dim_lab_sca_rates!$G$2:$G$316, 0, 0)} -> 20 | F9: C000015128 | G9: =dim_lab_sca_map!$F9&"|"&dim_lab_sca_map!$A9 -> C000015128|PCM|24 Hr
A10: =dim_lab_sca_map!$B10&"|"&dim_lab_sca_map!$D10 -> PCM|24 Hr | B10: PCM | C10: PRE | D10: 24 Hr | E10: {=XLOOKUP(TRIM(dim_lab_sca_map!$G10), TRIM(dim_lab_sca_rates!$C$2:$C$316), dim_lab_sca_rates!$G$2:$G$316, 0, 0)} -> 20 | F10: C000015128 | G10: =dim_lab_sca_map!$F10&"|"&dim_lab_sca_map!$A10 -> C000015128|PCM|24 Hr
A11: =dim_lab_sca_map!$B11&"|"&dim_lab_sca_map!$D11 -> SLIDE PREP|0 Hr | B11: SLIDE PREP | C11: SLIDE PREP | D11: 0 Hr | E11: {=XLOOKUP(TRIM(dim_lab_sca_map!$G11), TRIM(dim_lab_sca_rates!$C$2:$C$316), dim_lab_sca_rates!$G$2:$G$316, 0, 0)} -> 20 | F11: C000015128 | G11: =dim_lab_sca_map!$F11&"|"&dim_lab_sca_map!$A11 -> C000015128|SLIDE PREP|0 Hr
A12: =dim_lab_sca_map!$B12&"|"&dim_lab_sca_map!$D12 -> AMPH|10 Day | B12: AMPH | C12: VERMICULITE | D12: 10 Day | E12: {=XLOOKUP(TRIM(dim_lab_sca_map!$G12), TRIM(dim_lab_sca_rates!$C$2:$C$316), dim_lab_sca_rates!$G$2:$G$316, 0, 0)} -> 275 | F12: C000015128 | G12: =dim_lab_sca_map!$F12&"|"&dim_lab_sca_map!$A12 -> C000015128|AMPH|10 Day
A13: =dim_lab_sca_map!$B13&"|"&dim_lab_sca_map!$D13 -> PCM|24 Hr | B13: PCM | C13: PCM-24HRS | D13: 24 Hr | E13: {=XLOOKUP(TRIM(dim_lab_sca_map!$G13), TRIM(dim_lab_sca_rates!$C$2:$C$316), dim_lab_sca_rates!$G$2:$G$316, 0, 0)} -> 20 | F13: C000015128 | G13: =dim_lab_sca_map!$F13&"|"&dim_lab_sca_map!$A13 -> C000015128|PCM|24 Hr
... A64: =dim_lab_sca_map!$B64&"|"&dim_lab_sca_map!$D64 -> CHRYS|2 Day | B64: CHRYS | C64: CHRYS-2 DAY | D64: 2 Day | E64: {=XLOOKUP(TRIM(dim_lab_sca_map!$G64), TRIM(dim_lab_sca_rates!$C$2:$C$316), dim_lab_sca_rates!$G$2:$G$316, 0, 0)} -> 510 | F64: C000016435 | G64: =dim_lab_sca_map!$F64&"|"&dim_lab_sca_map!$A64 -> C000016435|CHRYS|2 Day

Sheet dim_fixed_fees
A1: JobIDKey | B1: JobID | C1: JobReportCost
A2: {=XLOOKUP(dim_fixed_fees!$B2,dim_job!$B$2:$B$6,dim_job!$A$2:$A$6,"",0)} -> 3 | B2: 23S-056 | C2: 700
A3: {=XLOOKUP(dim_fixed_fees!$B3,dim_job!$B$2:$B$6,dim_job!$A$2:$A$6,"",0)} -> 5 | B3: 25S-010 | C3: 775
A4: {=XLOOKUP(dim_fixed_fees!$B4,dim_job!$B$2:$B$6,dim_job!$A$2:$A$6,"",0)} -> 4 | B4: 24S-114 | C4: 700
A5: {=XLOOKUP(dim_fixed_fees!$B5,dim_job!$B$2:$B$6,dim_job!$A$2:$A$6,"",0)} -> 2 | B5: 22S-079 | C5: 200
A6: {=XLOOKUP(dim_fixed_fees!$B6,dim_job!$B$2:$B$6,dim_job!$A$2:$A$6,"",0)} -> 1 | B6: 22S-029 | C6: 700

Sheet fact_labor
A1: EmpKey | B1: LegacyEmpKey | C1: Employee_Name | D1: JobCode | E1: Hourly_Rate | F1: Date_Worked | G1: WeekEndingDateKey | H1: Hours_Worked | I1: JobID | J1: Expenses | K1: Clean_JobID | L1: Contract_No | M1: JobTitle_YrsExp_Key | N1: SCA_Labor_Key | O1: HomeMultiplier | P1: SCA_Labor_Rate | Q1: Hourly_HomeMult | R1: COST | S1: REVENUE | T1: PROFIT | U1: MARGIN | V1: ActualRFPAMT
A2: {=XLOOKUP(fact_labor!$B2,dim_technician!$H$2:$H$39,dim_technician!$A$2:$A$39,"",0)} -> 15 | B2: =LOWER(SUBSTITUTE(fact_labor!$C2," ","")&TEXT(fact_labor!$D2,"00")) -> igorgroysman01 | C2: =stg_payroll!$A2 -> Igor Groysman | D2: =stg_payroll!$B2 -> 1 | E2: =stg_payroll!$C2 -> 38 | F2: =stg_payroll!$E2 -> 44910 | G2: {=XLOOKUP(fact_labor!$F2,dim_date!$A$2:$A$2924,dim_date!$G$2:$G$2924,"",0)} -> 44912 | H2: =stg_payroll!$G2 -> 6.5 | I2: =stg_payroll!$H2 -> 22S-079 | J2: =stg_payroll!$J2 | K2: =TRIM(fact_labor!$I2) -> 22S-079 | L2: {=XLOOKUP(fact_labor!$K2,TRIM(dim_job!$B$2:$B$6),#REF!,"no contract",0)} -> #N/A | M2: {=XLOOKUP(fact_labor!$A2,dim_technician!$A$2:$A$39,#REF!,"",0)} -> #N/A | N2: =fact_labor!$L2&" "&fact_labor!$M2 -> #N/A | O2: {=XLOOKUP(fact_labor!$L2, stg_contract_values!$A$2:$A$4,stg_contract_values!$E$2:$E$4,"",0)} -> #N/A | P2: {=XLOOKUP(fact_labor!$N2,dim_sca_labor_rate!$F$2:$F$100, dim_sca_labor_rate!$J$2:$J$100,0,0)} -> #N/A | Q2: =fact_labor!$E2*fact_labor!$O2 -> #N/A | R2: =IF(fact_labor!$L2="no contract",0,fact_labor!$E2*fact_labor!$H2) -> #N/A | S2: =IF(fact_labor!$L2="no contract",0,fact_labor!$P2*fact_labor!$H2) -> #N/A | T2: =fact_labor!$S2-fact_labor!$R2 -> #N/A | U2: =IF(fact_labor!$L2="no contract",0,((fact_labor!$S2-fact_labor!$R2)/fact_labor!$S2)) -> #N/A
A3: {=XLOOKUP(fact_labor!$B3,dim_technician!$H$2:$H$39,dim_technician!$A$2:$A$39,"",0)} -> 15 | B3: =LOWER(SUBSTITUTE(fact_labor!$C3," ","")&TEXT(fact_labor!$D3,"00")) -> igorgroysman01 | C3: =stg_payroll!$A3 -> Igor Groysman | D3: =stg_payroll!$B3 -> 1 | E3: =stg_payroll!$C3 -> 38 | F3: =stg_payroll!$E3 -> 44911 | G3: {=XLOOKUP(fact_labor!$F3,dim_date!$A$2:$A$2924,dim_date!$G$2:$G$2924,"",0)} -> 44912 | H3: =stg_payroll!$G3 -> 4.5 | I3: =stg_payroll!$H3 -> 22S-079 | J3: =stg_payroll!$J3 | K3: =TRIM(fact_labor!$I3) -> 22S-079 | L3: {=XLOOKUP(fact_labor!$K3,TRIM(dim_job!$B$2:$B$6),#REF!,"no contract",0)} -> #N/A | M3: {=XLOOKUP(fact_labor!$A3,dim_technician!$A$2:$A$39,#REF!,"",0)} -> #N/A | N3: =fact_labor!$L3&" "&fact_labor!$M3 -> #N/A | O3: {=XLOOKUP(fact_labor!$L3, stg_contract_values!$A$2:$A$4,stg_contract_values!$E$2:$E$4,"",0)} -> #N/A | P3: {=XLOOKUP(fact_labor!$N3,dim_sca_labor_rate!$F$2:$F$100, dim_sca_labor_rate!$J$2:$J$100,0,0)} -> #N/A | Q3: =fact_labor!$E3*fact_labor!$O3 -> #N/A | R3: =IF(fact_labor!$L3="no contract",0,fact_labor!$E3*fact_labor!$H3) -> #N/A | S3: =IF(fact_labor!$L3="no contract",0,fact_labor!$P3*fact_labor!$H3) -> #N/A | T3: =fact_labor!$S3-fact_labor!$R3 -> #N/A | U3: =IF(fact_labor!$L3="no contract",0,((fact_labor!$S3-fact_labor!$R3)/fact_labor!$S3)) -> #N/A
A4: {=XLOOKUP(fact_labor!$B4,dim_technician!$H$2:$H$39,dim_technician!$A$2:$A$39,"",0)} -> 18 | B4: =LOWER(SUBSTITUTE(fact_labor!$C4," ","")&TEXT(fact_labor!$D4,"00")) -> ricardovilchez01 | C4: =stg_payroll!$A4 -> Ricardo Vilchez | D4: =stg_payroll!$B4 -> 1 | E4: =stg_payroll!$C4 -> 38 | F4: =stg_payroll!$E4 -> 45120 | G4: {=XLOOKUP(fact_labor!$F4,dim_date!$A$2:$A$2924,dim_date!$G$2:$G$2924,"",0)} -> 45122 | H4: =stg_payroll!$G4 -> 11 | I4: =stg_payroll!$H4 -> 23S-056 | J4: =stg_payroll!$J4 -> 6.55 | K4: =TRIM(fact_labor!$I4) -> 23S-056 | L4: {=XLOOKUP(fact_labor!$K4,TRIM(dim_job!$B$2:$B$6),#REF!,"no contract",0)} -> #N/A | M4: {=XLOOKUP(fact_labor!$A4,dim_technician!$A$2:$A$39,#REF!,"",0)} -> #N/A | N4: =fact_labor!$L4&" "&fact_labor!$M4 -> #N/A | O4: {=XLOOKUP(fact_labor!$L4, stg_contract_values!$A$2:$A$4,stg_contract_values!$E$2:$E$4,"",0)} -> #N/A | P4: {=XLOOKUP(fact_labor!$N4,dim_sca_labor_rate!$F$2:$F$100, dim_sca_labor_rate!$J$2:$J$100,0,0)} -> #N/A | Q4: =fact_labor!$E4*fact_labor!$O4 -> #N/A | R4: =IF(fact_labor!$L4="no contract",0,fact_labor!$E4*fact_labor!$H4) -> #N/A | S4: =IF(fact_labor!$L4="no contract",0,fact_labor!$P4*fact_labor!$H4) -> #N/A | T4: =fact_labor!$S4-fact_labor!$R4 -> #N/A | U4: =IF(fact_labor!$L4="no contract",0,((fact_labor!$S4-fact_labor!$R4)/fact_labor!$S4)) -> #N/A
A5: {=XLOOKUP(fact_labor!$B5,dim_technician!$H$2:$H$39,dim_technician!$A$2:$A$39,"",0)} -> 1 | B5: =LOWER(SUBSTITUTE(fact_labor!$C5," ","")&TEXT(fact_labor!$D5,"00")) -> cornelalbu01 | C5: =stg_payroll!$A5 -> Cornel Albu | D5: =stg_payroll!$B5 -> 1 | E5: =stg_payroll!$C5 -> 38 | F5: =stg_payroll!$E5 -> 45583 | G5: {=XLOOKUP(fact_labor!$F5,dim_date!$A$2:$A$2924,dim_date!$G$2:$G$2924,"",0)} -> 45584 | H5: =stg_payroll!$G5 -> 7.5 | I5: =stg_payroll!$H5 -> 24S-114 | J5: =stg_payroll!$J5 | K5: =TRIM(fact_labor!$I5) -> 24S-114 | L5: {=XLOOKUP(fact_labor!$K5,TRIM(dim_job!$B$2:$B$6),#REF!,"no contract",0)} -> #N/A | M5: {=XLOOKUP(fact_labor!$A5,dim_technician!$A$2:$A$39,#REF!,"",0)} -> #N/A | N5: =fact_labor!$L5&" "&fact_labor!$M5 -> #N/A | O5: {=XLOOKUP(fact_labor!$L5, stg_contract_values!$A$2:$A$4,stg_contract_values!$E$2:$E$4,"",0)} -> #N/A | P5: {=XLOOKUP(fact_labor!$N5,dim_sca_labor_rate!$F$2:$F$100, dim_sca_labor_rate!$J$2:$J$100,0,0)} -> #N/A | Q5: =fact_labor!$E5*fact_labor!$O5 -> #N/A | R5: =IF(fact_labor!$L5="no contract",0,fact_labor!$E5*fact_labor!$H5) -> #N/A | S5: =IF(fact_labor!$L5="no contract",0,fact_labor!$P5*fact_labor!$H5) -> #N/A | T5: =fact_labor!$S5-fact_labor!$R5 -> #N/A | U5: =IF(fact_labor!$L5="no contract",0,((fact_labor!$S5-fact_labor!$R5)/fact_labor!$S5)) -> #N/A
A6: {=XLOOKUP(fact_labor!$B6,dim_technician!$H$2:$H$39,dim_technician!$A$2:$A$39,"",0)} -> 1 | B6: =LOWER(SUBSTITUTE(fact_labor!$C6," ","")&TEXT(fact_labor!$D6,"00")) -> cornelalbu01 | C6: =stg_payroll!$A6 -> Cornel Albu | D6: =stg_payroll!$B6 -> 1 | E6: =stg_payroll!$C6 -> 38 | F6: =stg_payroll!$E6 -> 45584 | G6: {=XLOOKUP(fact_labor!$F6,dim_date!$A$2:$A$2924,dim_date!$G$2:$G$2924,"",0)} -> 45584 | H6: =stg_payroll!$G6 -> 18.5 | I6: =stg_payroll!$H6 -> 24S-114 | J6: =stg_payroll!$J6 | K6: =TRIM(fact_labor!$I6) -> 24S-114 | L6: {=XLOOKUP(fact_labor!$K6,TRIM(dim_job!$B$2:$B$6),#REF!,"no contract",0)} -> #N/A | M6: {=XLOOKUP(fact_labor!$A6,dim_technician!$A$2:$A$39,#REF!,"",0)} -> #N/A | N6: =fact_labor!$L6&" "&fact_labor!$M6 -> #N/A | O6: {=XLOOKUP(fact_labor!$L6, stg_contract_values!$A$2:$A$4,stg_contract_values!$E$2:$E$4,"",0)} -> #N/A | P6: {=XLOOKUP(fact_labor!$N6,dim_sca_labor_rate!$F$2:$F$100, dim_sca_labor_rate!$J$2:$J$100,0,0)} -> #N/A | Q6: =fact_labor!$E6*fact_labor!$O6 -> #N/A | R6: =IF(fact_labor!$L6="no contract",0,fact_labor!$E6*fact_labor!$H6) -> #N/A | S6: =IF(fact_labor!$L6="no contract",0,fact_labor!$P6*fact_labor!$H6) -> #N/A | T6: =fact_labor!$S6-fact_labor!$R6 -> #N/A | U6: =IF(fact_labor!$L6="no contract",0,((fact_labor!$S6-fact_labor!$R6)/fact_labor!$S6)) -> #N/A
A7: {=XLOOKUP(fact_labor!$B7,dim_technician!$H$2:$H$39,dim_technician!$A$2:$A$39,"",0)} -> 3 | B7: =LOWER(SUBSTITUTE(fact_labor!$C7," ","")&TEXT(fact_labor!$D7,"00")) -> cornelalbu03 | C7: =stg_payroll!$A7 -> Cornel Albu | D7: =stg_payroll!$B7 -> 3 | E7: =stg_payroll!$C7 -> 45 | F7: =stg_payroll!$E7 -> 45698 | G7: {=XLOOKUP(fact_labor!$F7,dim_date!$A$2:$A$2924,dim_date!$G$2:$G$2924,"",0)} -> 45703 | H7: =stg_payroll!$G7 -> 9 | I7: =stg_payroll!$H7 -> 25S-010 | J7: =stg_payroll!$J7 | K7: =TRIM(fact_labor!$I7) -> 25S-010 | L7: {=XLOOKUP(fact_labor!$K7,TRIM(dim_job!$B$2:$B$6),#REF!,"no contract",0)} -> #N/A | M7: {=XLOOKUP(fact_labor!$A7,dim_technician!$A$2:$A$39,#REF!,"",0)} -> #N/A | N7: =fact_labor!$L7&" "&fact_labor!$M7 -> #N/A | O7: {=XLOOKUP(fact_labor!$L7, stg_contract_values!$A$2:$A$4,stg_contract_values!$E$2:$E$4,"",0)} -> #N/A | P7: {=XLOOKUP(fact_labor!$N7,dim_sca_labor_rate!$F$2:$F$100, dim_sca_labor_rate!$J$2:$J$100,0,0)} -> #N/A | Q7: =fact_labor!$E7*fact_labor!$O7 -> #N/A | R7: =IF(fact_labor!$L7="no contract",0,fact_labor!$E7*fact_labor!$H7) -> #N/A | S7: =IF(fact_labor!$L7="no contract",0,fact_labor!$P7*fact_labor!$H7) -> #N/A | T7: =fact_labor!$S7-fact_labor!$R7 -> #N/A | U7: =IF(fact_labor!$L7="no contract",0,((fact_labor!$S7-fact_labor!$R7)/fact_labor!$S7)) -> #N/A
A8: {=XLOOKUP(fact_labor!$B8,dim_technician!$H$2:$H$39,dim_technician!$A$2:$A$39,"",0)} -> 1 | B8: =LOWER(SUBSTITUTE(fact_labor!$C8," ","")&TEXT(fact_labor!$D8,"00")) -> cornelalbu01 | C8: =stg_payroll!$A8 -> Cornel Albu | D8: =stg_payroll!$B8 -> 1 | E8: =stg_payroll!$C8 -> 38 | F8: =stg_payroll!$E8 -> 45743 | G8: {=XLOOKUP(fact_labor!$F8,dim_date!$A$2:$A$2924,dim_date!$G$2:$G$2924,"",0)} -> 45745 | H8: =stg_payroll!$G8 -> 5 | I8: =stg_payroll!$H8 -> 25S-010 | J8: =stg_payroll!$J8 | K8: =TRIM(fact_labor!$I8) -> 25S-010 | L8: {=XLOOKUP(fact_labor!$K8,TRIM(dim_job!$B$2:$B$6),#REF!,"no contract",0)} -> #N/A | M8: {=XLOOKUP(fact_labor!$A8,dim_technician!$A$2:$A$39,#REF!,"",0)} -> #N/A | N8: =fact_labor!$L8&" "&fact_labor!$M8 -> #N/A | O8: {=XLOOKUP(fact_labor!$L8, stg_contract_values!$A$2:$A$4,stg_contract_values!$E$2:$E$4,"",0)} -> #N/A | P8: {=XLOOKUP(fact_labor!$N8,dim_sca_labor_rate!$F$2:$F$100, dim_sca_labor_rate!$J$2:$J$100,0,0)} -> #N/A | Q8: =fact_labor!$E8*fact_labor!$O8 -> #N/A | R8: =IF(fact_labor!$L8="no contract",0,fact_labor!$E8*fact_labor!$H8) -> #N/A | S8: =IF(fact_labor!$L8="no contract",0,fact_labor!$P8*fact_labor!$H8) -> #N/A | T8: =fact_labor!$S8-fact_labor!$R8 -> #N/A | U8: =IF(fact_labor!$L8="no contract",0,((fact_labor!$S8-fact_labor!$R8)/fact_labor!$S8)) -> #N/A
A9: {=XLOOKUP(fact_labor!$B9,dim_technician!$H$2:$H$39,dim_technician!$A$2:$A$39,"",0)} -> 1 | B9: =LOWER(SUBSTITUTE(fact_labor!$C9," ","")&TEXT(fact_labor!$D9,"00")) -> cornelalbu01 | C9: =stg_payroll!$A9 -> Cornel Albu | D9: =stg_payroll!$B9 -> 1 | E9: =stg_payroll!$C9 -> 38 | F9: =stg_payroll!$E9 -> 45744 | G9: {=XLOOKUP(fact_labor!$F9,dim_date!$A$2:$A$2924,dim_date!$G$2:$G$2924,"",0)} -> 45745 | H9: =stg_payroll!$G9 -> 6.5 | I9: =stg_payroll!$H9 -> 25S-010 | J9: =stg_payroll!$J9 | K9: =TRIM(fact_labor!$I9) -> 25S-010 | L9: {=XLOOKUP(fact_labor!$K9,TRIM(dim_job!$B$2:$B$6),#REF!,"no contract",0)} -> #N/A | M9: {=XLOOKUP(fact_labor!$A9,dim_technician!$A$2:$A$39,#REF!,"",0)} -> #N/A | N9: =fact_labor!$L9&" "&fact_labor!$M9 -> #N/A | O9: {=XLOOKUP(fact_labor!$L9, stg_contract_values!$A$2:$A$4,stg_contract_values!$E$2:$E$4,"",0)} -> #N/A | P9: {=XLOOKUP(fact_labor!$N9,dim_sca_labor_rate!$F$2:$F$100, dim_sca_labor_rate!$J$2:$J$100,0,0)} -> #N/A | Q9: =fact_labor!$E9*fact_labor!$O9 -> #N/A | R9: =IF(fact_labor!$L9="no contract",0,fact_labor!$E9*fact_labor!$H9) -> #N/A | S9: =IF(fact_labor!$L9="no contract",0,fact_labor!$P9*fact_labor!$H9) -> #N/A | T9: =fact_labor!$S9-fact_labor!$R9 -> #N/A | U9: =IF(fact_labor!$L9="no contract",0,((fact_labor!$S9-fact_labor!$R9)/fact_labor!$S9)) -> #N/A
A10: {=XLOOKUP(fact_labor!$B10,dim_technician!$H$2:$H$39,dim_technician!$A$2:$A$39,"",0)} -> 1 | B10: =LOWER(SUBSTITUTE(fact_labor!$C10," ","")&TEXT(fact_labor!$D10,"00")) -> cornelalbu01 | C10: =stg_payroll!$A10 -> Cornel Albu | D10: =stg_payroll!$B10 -> 1 | E10: =stg_payroll!$C10 -> 38 | F10: =stg_payroll!$E10 -> 45745 | G10: {=XLOOKUP(fact_labor!$F10,dim_date!$A$2:$A$2924,dim_date!$G$2:$G$2924,"",0)} -> 45745 | H10: =stg_payroll!$G10 -> 21 | I10: =stg_payroll!$H10 -> 25S-010 | J10: =stg_payroll!$J10 -> 27.76 | K10: =TRIM(fact_labor!$I10) -> 25S-010 | L10: {=XLOOKUP(fact_labor!$K10,TRIM(dim_job!$B$2:$B$6),#REF!,"no contract",0)} -> #N/A | M10: {=XLOOKUP(fact_labor!$A10,dim_technician!$A$2:$A$39,#REF!,"",0)} -> #N/A | N10: =fact_labor!$L10&" "&fact_labor!$M10 -> #N/A | O10: {=XLOOKUP(fact_labor!$L10, stg_contract_values!$A$2:$A$4,stg_contract_values!$E$2:$E$4,"",0)} -> #N/A | P10: {=XLOOKUP(fact_labor!$N10,dim_sca_labor_rate!$F$2:$F$100, dim_sca_labor_rate!$J$2:$J$100,0,0)} -> #N/A | Q10: =fact_labor!$E10*fact_labor!$O10 -> #N/A | R10: =IF(fact_labor!$L10="no contract",0,fact_labor!$E10*fact_labor!$H10) -> #N/A | S10: =IF(fact_labor!$L10="no contract",0,fact_labor!$P10*fact_labor!$H10) -> #N/A | T10: =fact_labor!$S10-fact_labor!$R10 -> #N/A | U10: =IF(fact_labor!$L10="no contract",0,((fact_labor!$S10-fact_labor!$R10)/fact_labor!$S10)) -> #N/A
A11: {=XLOOKUP(fact_labor!$B11,dim_technician!$H$2:$H$39,dim_technician!$A$2:$A$39,"",0)} -> 1 | B11: =LOWER(SUBSTITUTE(fact_labor!$C11," ","")&TEXT(fact_labor!$D11,"00")) -> cornelalbu01 | C11: =stg_payroll!$A11 -> Cornel Albu | D11: =stg_payroll!$B11 -> 1 | E11: =stg_payroll!$C11 -> 38 | F11: =stg_payroll!$E11 -> 45750 | G11: {=XLOOKUP(fact_labor!$F11,dim_date!$A$2:$A$2924,dim_date!$G$2:$G$2924,"",0)} -> 45752 | H11: =stg_payroll!$G11 -> 6 | I11: =stg_payroll!$H11 -> 25S-010 | J11: =stg_payroll!$J11 | K11: =TRIM(fact_labor!$I11) -> 25S-010 | L11: {=XLOOKUP(fact_labor!$K11,TRIM(dim_job!$B$2:$B$6),#REF!,"no contract",0)} -> #N/A | M11: {=XLOOKUP(fact_labor!$A11,dim_technician!$A$2:$A$39,#REF!,"",0)} -> #N/A | N11: =fact_labor!$L11&" "&fact_labor!$M11 -> #N/A | O11: {=XLOOKUP(fact_labor!$L11, stg_contract_values!$A$2:$A$4,stg_contract_values!$E$2:$E$4,"",0)} -> #N/A | P11: {=XLOOKUP(fact_labor!$N11,dim_sca_labor_rate!$F$2:$F$100, dim_sca_labor_rate!$J$2:$J$100,0,0)} -> #N/A | Q11: =fact_labor!$E11*fact_labor!$O11 -> #N/A | R11: =IF(fact_labor!$L11="no contract",0,fact_labor!$E11*fact_labor!$H11) -> #N/A | S11: =IF(fact_labor!$L11="no contract",0,fact_labor!$P11*fact_labor!$H11) -> #N/A | T11: =fact_labor!$S11-fact_labor!$R11 -> #N/A | U11: =IF(fact_labor!$L11="no contract",0,((fact_labor!$S11-fact_labor!$R11)/fact_labor!$S11)) -> #N/A
A12: {=XLOOKUP(fact_labor!$B12,dim_technician!$H$2:$H$39,dim_technician!$A$2:$A$39,"",0)} -> 1 | B12: =LOWER(SUBSTITUTE(fact_labor!$C12," ","")&TEXT(fact_labor!$D12,"00")) -> cornelalbu01 | C12: =stg_payroll!$A12 -> Cornel Albu | D12: =stg_payroll!$B12 -> 1 | E12: =stg_payroll!$C12 -> 38 | F12: =stg_payroll!$E12 -> 45751 | G12: {=XLOOKUP(fact_labor!$F12,dim_date!$A$2:$A$2924,dim_date!$G$2:$G$2924,"",0)} -> 45752 | H12: =stg_payroll!$G12 -> 6.5 | I12: =stg_payroll!$H12 -> 25S-010 | J12: =stg_payroll!$J12 | K12: =TRIM(fact_labor!$I12) -> 25S-010 | L12: {=XLOOKUP(fact_labor!$K12,TRIM(dim_job!$B$2:$B$6),#REF!,"no contract",0)} -> #N/A | M12: {=XLOOKUP(fact_labor!$A12,dim_technician!$A$2:$A$39,#REF!,"",0)} -> #N/A | N12: =fact_labor!$L12&" "&fact_labor!$M12 -> #N/A | O12: {=XLOOKUP(fact_labor!$L12, stg_contract_values!$A$2:$A$4,stg_contract_values!$E$2:$E$4,"",0)} -> #N/A | P12: {=XLOOKUP(fact_labor!$N12,dim_sca_labor_rate!$F$2:$F$100, dim_sca_labor_rate!$J$2:$J$100,0,0)} -> #N/A | Q12: =fact_labor!$E12*fact_labor!$O12 -> #N/A | R12: =IF(fact_labor!$L12="no contract",0,fact_labor!$E12*fact_labor!$H12) -> #N/A | S12: =IF(fact_labor!$L12="no contract",0,fact_labor!$P12*fact_labor!$H12) -> #N/A | T12: =fact_labor!$S12-fact_labor!$R12 -> #N/A | U12: =IF(fact_labor!$L12="no contract",0,((fact_labor!$S12-fact_labor!$R12)/fact_labor!$S12)) -> #N/A
A13: {=XLOOKUP(fact_labor!$B13,dim_technician!$H$2:$H$39,dim_technician!$A$2:$A$39,"",0)} -> 1 | B13: =LOWER(SUBSTITUTE(fact_labor!$C13," ","")&TEXT(fact_labor!$D13,"00")) -> cornelalbu01 | C13: =stg_payroll!$A13 -> Cornel Albu | D13: =stg_payroll!$B13 -> 1 | E13: =stg_payroll!$C13 -> 38 | F13: =stg_payroll!$E13 -> 45752 | G13: {=XLOOKUP(fact_labor!$F13,dim_date!$A$2:$A$2924,dim_date!$G$2:$G$2924,"",0)} -> 45752 | H13: =stg_payroll!$G13 -> 20.5 | I13: =stg_payroll!$H13 -> 25S-010 | J13: =stg_payroll!$J13 -> 34.7 | K13: =TRIM(fact_labor!$I13) -> 25S-010 | L13: {=XLOOKUP(fact_labor!$K13,TRIM(dim_job!$B$2:$B$6),#REF!,"no contract",0)} -> #N/A | M13: {=XLOOKUP(fact_labor!$A13,dim_technician!$A$2:$A$39,#REF!,"",0)} -> #N/A | N13: =fact_labor!$L13&" "&fact_labor!$M13 -> #N/A | O13: {=XLOOKUP(fact_labor!$L13, stg_contract_values!$A$2:$A$4,stg_contract_values!$E$2:$E$4,"",0)} -> #N/A | P13: {=XLOOKUP(fact_labor!$N13,dim_sca_labor_rate!$F$2:$F$100, dim_sca_labor_rate!$J$2:$J$100,0,0)} -> #N/A | Q13: =fact_labor!$E13*fact_labor!$O13 -> #N/A | R13: =IF(fact_labor!$L13="no contract",0,fact_labor!$E13*fact_labor!$H13) -> #N/A | S13: =IF(fact_labor!$L13="no contract",0,fact_labor!$P13*fact_labor!$H13) -> #N/A | T13: =fact_labor!$S13-fact_labor!$R13 -> #N/A | U13: =IF(fact_labor!$L13="no contract",0,((fact_labor!$S13-fact_labor!$R13)/fact_labor!$S13)) -> #N/A
... A29: {=XLOOKUP(fact_labor!$B29,dim_technician!$H$2:$H$39,dim_technician!$A$2:$A$39,"",0)} -> 32 | B29: =LOWER(SUBSTITUTE(fact_labor!$C29," ","")&TEXT(fact_labor!$D29,"00")) -> dimitribellos03 | C29: =stg_payroll!$A29 -> Dimitri Bellos | D29: =stg_payroll!$B29 -> 3 | E29: =stg_payroll!$C29 -> 89 | F29: =stg_payroll!$E29 -> 44749 | G29: {=XLOOKUP(fact_labor!$F29,dim_date!$A$2:$A$2924,dim_date!$G$2:$G$2924,"",0)} -> 44751 | H29: =stg_payroll!$G29 -> 6 | I29: =stg_payroll!$H29 -> 22S-029 | J29: =stg_payroll!$J29 | K29: =TRIM(fact_labor!$I29) -> 22S-029 | L29: {=XLOOKUP(fact_labor!$K29,TRIM(dim_job!$B$2:$B$6),#REF!,"no contract",0)} -> #N/A | M29: {=XLOOKUP(fact_labor!$A29,dim_technician!$A$2:$A$39,#REF!,"",0)} -> #N/A | N29: =fact_labor!$L29&" "&fact_labor!$M29 -> #N/A | O29: {=XLOOKUP(fact_labor!$L29, stg_contract_values!$A$2:$A$4,stg_contract_values!$E$2:$E$4,"",0)} -> #N/A | P29: {=XLOOKUP(fact_labor!$N29,dim_sca_labor_rate!$F$2:$F$100, dim_sca_labor_rate!$J$2:$J$100,0,0)} -> #N/A | Q29: =fact_labor!$E29*fact_labor!$O29 -> #N/A | R29: =IF(fact_labor!$L29="no contract",0,fact_labor!$E29*fact_labor!$H29) -> #N/A | S29: =IF(fact_labor!$L29="no contract",0,fact_labor!$P29*fact_labor!$H29) -> #N/A | T29: =fact_labor!$S29-fact_labor!$R29 -> #N/A | U29: =IF(fact_labor!$L29="no contract",0,((fact_labor!$S29-fact_labor!$R29)/fact_labor!$S29)) -> #N/A

Sheet fact_lab
A1: JobID | B1: Job_Type | C1: Sample | D1: Sample_Bridge | E1: Quantity | F1: TAT | G1: Facility | H1: Contract_No | I1: Vendor_Rate | J1: SCA_Rate | K1: Cost | L1: Revenue | M1: Profit | N1: Map_Key | O1: Final_Key | P1: Vendor_Key | Q1: JobID_Labs | R1: check
A2: {=XLOOKUP( TRIM(fact_lab!$Q2), dim_job!$B$2:$B$6, dim_job!$B$2:$B$6, "" )} -> 25S-010 | B2: =stg_lab_reports!$A2 -> SCA | C2: =stg_lab_reports!$F2 -> Durings | D2: {=XLOOKUP(fact_lab!$C2,dim_lab_sca_map!$C$2:$C$64, dim_lab_sca_map!$B$2:$B$64, 0)} -> PCM | E2: =stg_lab_reports!$G2 -> 4 | F2: {=XLOOKUP(fact_lab!$D2, dim_lab_sca_map!$B$2:$B$64, dim_lab_sca_map!$D$2:$D$64)} -> 1 Hr | G2: =stg_lab_reports!$I2 -> LTS | H2: {=XLOOKUP(fact_lab!$A2, dim_job!$B$2:$B$6, dim_job!$H$2:$H$6, "Missing Contract")} -> C000015869 | I2: {=XLOOKUP(fact_lab!$P2, dim_lab_vendor_rates!$A$2:$A$49, dim_lab_vendor_rates!$E$2:$E$49, "No Rate")} -> 6 | J2: {=XLOOKUP( fact_lab!$O2, dim_lab_sca_map!$G$2:$G$64, dim_lab_sca_map!$E$2:$E$64, 0 )} -> 27 | K2: =fact_lab!$E2*fact_lab!$I2 -> 24 | L2: =IF(fact_lab!$B2="SCA",fact_lab!$E2*fact_lab!$J2, fact_lab!$K2) -> 108 | M2: =IF(fact_lab!$H2="Missing Contract", 0, fact_lab!$L2-fact_lab!$K2) -> 84 | N2: =fact_lab!$D2&"|"&fact_lab!$F2 -> PCM|1 Hr | O2: =fact_lab!$H2&"|"&fact_lab!$N2 -> C000015869|PCM|1 Hr | P2: =fact_lab!$G2&"|"&fact_lab!$C2 -> LTS|Durings | Q2: =TRIM(stg_lab_reports!$C2) -> 25S-010 | R2: {=XLOOKUP( TRIM(fact_lab!$Q2), dim_job!$B$2:$B$6, dim_job!$B$2:$B$6, "" )} -> 25S-010
A3: {=XLOOKUP( TRIM(fact_lab!$Q3), dim_job!$B$2:$B$6, dim_job!$B$2:$B$6, "" )} -> 25S-010 | B3: =stg_lab_reports!$A3 -> SCA | C3: =stg_lab_reports!$F3 -> Finals | D3: {=XLOOKUP(fact_lab!$C3,dim_lab_sca_map!$C$2:$C$64, dim_lab_sca_map!$B$2:$B$64, 0)} -> PCM | E3: =stg_lab_reports!$G3 -> 8 | F3: {=XLOOKUP(fact_lab!$D3, dim_lab_sca_map!$B$2:$B$64, dim_lab_sca_map!$D$2:$D$64)} -> 1 Hr | G3: =stg_lab_reports!$I3 -> LTS | H3: {=XLOOKUP(fact_lab!$A3, dim_job!$B$2:$B$6, dim_job!$H$2:$H$6, "Missing Contract")} -> C000015869 | I3: {=XLOOKUP(fact_lab!$P3, dim_lab_vendor_rates!$A$2:$A$49, dim_lab_vendor_rates!$E$2:$E$49, "No Rate")} -> 6 | J3: {=XLOOKUP( fact_lab!$O3, dim_lab_sca_map!$G$2:$G$64, dim_lab_sca_map!$E$2:$E$64, 0 )} -> 27 | K3: =fact_lab!$E3*fact_lab!$I3 -> 48 | L3: =IF(fact_lab!$B3="SCA",fact_lab!$E3*fact_lab!$J3, fact_lab!$K3) -> 216 | M3: =IF(fact_lab!$H3="Missing Contract", 0, fact_lab!$L3-fact_lab!$K3) -> 168 | N3: =fact_lab!$D3&"|"&fact_lab!$F3 -> PCM|1 Hr | O3: =fact_lab!$H3&"|"&fact_lab!$N3 -> C000015869|PCM|1 Hr | P3: =fact_lab!$G3&"|"&fact_lab!$C3 -> LTS|Finals | Q3: =TRIM(stg_lab_reports!$C3) -> 25S-010 | R3: {=XLOOKUP( TRIM(fact_lab!$Q3), dim_job!$B$2:$B$6, dim_job!$B$2:$B$6, "" )} -> 25S-010
A4: {=XLOOKUP( TRIM(fact_lab!$Q4), dim_job!$B$2:$B$6, dim_job!$B$2:$B$6, "" )} -> 25S-010 | B4: =stg_lab_reports!$A4 -> SCA | C4: =stg_lab_reports!$F4 -> Backgrounds | D4: {=XLOOKUP(fact_lab!$C4,dim_lab_sca_map!$C$2:$C$64, dim_lab_sca_map!$B$2:$B$64, 0)} -> PCM | E4: =stg_lab_reports!$G4 -> 12 | F4: {=XLOOKUP(fact_lab!$D4, dim_lab_sca_map!$B$2:$B$64, dim_lab_sca_map!$D$2:$D$64)} -> 1 Hr | G4: =stg_lab_reports!$I4 -> LTS | H4: {=XLOOKUP(fact_lab!$A4, dim_job!$B$2:$B$6, dim_job!$H$2:$H$6, "Missing Contract")} -> C000015869 | I4: {=XLOOKUP(fact_lab!$P4, dim_lab_vendor_rates!$A$2:$A$49, dim_lab_vendor_rates!$E$2:$E$49, "No Rate")} -> 6 | J4: {=XLOOKUP( fact_lab!$O4, dim_lab_sca_map!$G$2:$G$64, dim_lab_sca_map!$E$2:$E$64, 0 )} -> 27 | K4: =fact_lab!$E4*fact_lab!$I4 -> 72 | L4: =IF(fact_lab!$B4="SCA",fact_lab!$E4*fact_lab!$J4, fact_lab!$K4) -> 324 | M4: =IF(fact_lab!$H4="Missing Contract", 0, fact_lab!$L4-fact_lab!$K4) -> 252 | N4: =fact_lab!$D4&"|"&fact_lab!$F4 -> PCM|1 Hr | O4: =fact_lab!$H4&"|"&fact_lab!$N4 -> C000015869|PCM|1 Hr | P4: =fact_lab!$G4&"|"&fact_lab!$C4 -> LTS|Backgrounds | Q4: =TRIM(stg_lab_reports!$C4) -> 25S-010 | R4: {=XLOOKUP( TRIM(fact_lab!$Q4), dim_job!$B$2:$B$6, dim_job!$B$2:$B$6, "" )} -> 25S-010
A5: {=XLOOKUP( TRIM(fact_lab!$Q5), dim_job!$B$2:$B$6, dim_job!$B$2:$B$6, "" )} -> 25S-010 | B5: =stg_lab_reports!$A5 -> SCA | C5: =stg_lab_reports!$F5 -> Backgrounds | D5: {=XLOOKUP(fact_lab!$C5,dim_lab_sca_map!$C$2:$C$64, dim_lab_sca_map!$B$2:$B$64, 0)} -> PCM | E5: =stg_lab_reports!$G5 -> 12 | F5: {=XLOOKUP(fact_lab!$D5, dim_lab_sca_map!$B$2:$B$64, dim_lab_sca_map!$D$2:$D$64)} -> 1 Hr | G5: =stg_lab_reports!$I5 -> LTS | H5: {=XLOOKUP(fact_lab!$A5, dim_job!$B$2:$B$6, dim_job!$H$2:$H$6, "Missing Contract")} -> C000015869 | I5: {=XLOOKUP(fact_lab!$P5, dim_lab_vendor_rates!$A$2:$A$49, dim_lab_vendor_rates!$E$2:$E$49, "No Rate")} -> 6 | J5: {=XLOOKUP( fact_lab!$O5, dim_lab_sca_map!$G$2:$G$64, dim_lab_sca_map!$E$2:$E$64, 0 )} -> 27 | K5: =fact_lab!$E5*fact_lab!$I5 -> 72 | L5: =IF(fact_lab!$B5="SCA",fact_lab!$E5*fact_lab!$J5, fact_lab!$K5) -> 324 | M5: =IF(fact_lab!$H5="Missing Contract", 0, fact_lab!$L5-fact_lab!$K5) -> 252 | N5: =fact_lab!$D5&"|"&fact_lab!$F5 -> PCM|1 Hr | O5: =fact_lab!$H5&"|"&fact_lab!$N5 -> C000015869|PCM|1 Hr | P5: =fact_lab!$G5&"|"&fact_lab!$C5 -> LTS|Backgrounds | Q5: =TRIM(stg_lab_reports!$C5) -> 25S-010 | R5: {=XLOOKUP( TRIM(fact_lab!$Q5), dim_job!$B$2:$B$6, dim_job!$B$2:$B$6, "" )} -> 25S-010
A6: {=XLOOKUP( TRIM(fact_lab!$Q6), dim_job!$B$2:$B$6, dim_job!$B$2:$B$6, "" )} -> 25S-010 | B6: =stg_lab_reports!$A6 -> SCA | C6: =stg_lab_reports!$F6 -> Pre | D6: {=XLOOKUP(fact_lab!$C6,dim_lab_sca_map!$C$2:$C$64, dim_lab_sca_map!$B$2:$B$64, 0)} -> PCM | E6: =stg_lab_reports!$G6 -> 12 | F6: {=XLOOKUP(fact_lab!$D6, dim_lab_sca_map!$B$2:$B$64, dim_lab_sca_map!$D$2:$D$64)} -> 1 Hr | G6: =stg_lab_reports!$I6 -> LTS | H6: {=XLOOKUP(fact_lab!$A6, dim_job!$B$2:$B$6, dim_job!$H$2:$H$6, "Missing Contract")} -> C000015869 | I6: {=XLOOKUP(fact_lab!$P6, dim_lab_vendor_rates!$A$2:$A$49, dim_lab_vendor_rates!$E$2:$E$49, "No Rate")} -> 6 | J6: {=XLOOKUP( fact_lab!$O6, dim_lab_sca_map!$G$2:$G$64, dim_lab_sca_map!$E$2:$E$64, 0 )} -> 27 | K6: =fact_lab!$E6*fact_lab!$I6 -> 72 | L6: =IF(fact_lab!$B6="SCA",fact_lab!$E6*fact_lab!$J6, fact_lab!$K6) -> 324 | M6: =IF(fact_lab!$H6="Missing Contract", 0, fact_lab!$L6-fact_lab!$K6) -> 252 | N6: =fact_lab!$D6&"|"&fact_lab!$F6 -> PCM|1 Hr | O6: =fact_lab!$H6&"|"&fact_lab!$N6 -> C000015869|PCM|1 Hr | P6: =fact_lab!$G6&"|"&fact_lab!$C6 -> LTS|Pre | Q6: =TRIM(stg_lab_reports!$C6) -> 25S-010 | R6: {=XLOOKUP( TRIM(fact_lab!$Q6), dim_job!$B$2:$B$6, dim_job!$B$2:$B$6, "" )} -> 25S-010
A7: {=XLOOKUP( TRIM(fact_lab!$Q7), dim_job!$B$2:$B$6, dim_job!$B$2:$B$6, "" )} -> 25S-010 | B7: =stg_lab_reports!$A7 -> SCA | C7: =stg_lab_reports!$F7 -> Durings | D7: {=XLOOKUP(fact_lab!$C7,dim_lab_sca_map!$C$2:$C$64, dim_lab_sca_map!$B$2:$B$64, 0)} -> PCM | E7: =stg_lab_reports!$G7 -> 18 | F7: {=XLOOKUP(fact_lab!$D7, dim_lab_sca_map!$B$2:$B$64, dim_lab_sca_map!$D$2:$D$64)} -> 1 Hr | G7: =stg_lab_reports!$I7 -> LTS | H7: {=XLOOKUP(fact_lab!$A7, dim_job!$B$2:$B$6, dim_job!$H$2:$H$6, "Missing Contract")} -> C000015869 | I7: {=XLOOKUP(fact_lab!$P7, dim_lab_vendor_rates!$A$2:$A$49, dim_lab_vendor_rates!$E$2:$E$49, "No Rate")} -> 6 | J7: {=XLOOKUP( fact_lab!$O7, dim_lab_sca_map!$G$2:$G$64, dim_lab_sca_map!$E$2:$E$64, 0 )} -> 27 | K7: =fact_lab!$E7*fact_lab!$I7 -> 108 | L7: =IF(fact_lab!$B7="SCA",fact_lab!$E7*fact_lab!$J7, fact_lab!$K7) -> 486 | M7: =IF(fact_lab!$H7="Missing Contract", 0, fact_lab!$L7-fact_lab!$K7) -> 378 | N7: =fact_lab!$D7&"|"&fact_lab!$F7 -> PCM|1 Hr | O7: =fact_lab!$H7&"|"&fact_lab!$N7 -> C000015869|PCM|1 Hr | P7: =fact_lab!$G7&"|"&fact_lab!$C7 -> LTS|Durings | Q7: =TRIM(stg_lab_reports!$C7) -> 25S-010 | R7: {=XLOOKUP( TRIM(fact_lab!$Q7), dim_job!$B$2:$B$6, dim_job!$B$2:$B$6, "" )} -> 25S-010
A8: {=XLOOKUP( TRIM(fact_lab!$Q8), dim_job!$B$2:$B$6, dim_job!$B$2:$B$6, "" )} -> 25S-010 | B8: =stg_lab_reports!$A8 -> SCA | C8: =stg_lab_reports!$F8 -> Pre | D8: {=XLOOKUP(fact_lab!$C8,dim_lab_sca_map!$C$2:$C$64, dim_lab_sca_map!$B$2:$B$64, 0)} -> PCM | E8: =stg_lab_reports!$G8 -> 12 | F8: {=XLOOKUP(fact_lab!$D8, dim_lab_sca_map!$B$2:$B$64, dim_lab_sca_map!$D$2:$D$64)} -> 1 Hr | G8: =stg_lab_reports!$I8 -> LTS | H8: {=XLOOKUP(fact_lab!$A8, dim_job!$B$2:$B$6, dim_job!$H$2:$H$6, "Missing Contract")} -> C000015869 | I8: {=XLOOKUP(fact_lab!$P8, dim_lab_vendor_rates!$A$2:$A$49, dim_lab_vendor_rates!$E$2:$E$49, "No Rate")} -> 6 | J8: {=XLOOKUP( fact_lab!$O8, dim_lab_sca_map!$G$2:$G$64, dim_lab_sca_map!$E$2:$E$64, 0 )} -> 27 | K8: =fact_lab!$E8*fact_lab!$I8 -> 72 | L8: =IF(fact_lab!$B8="SCA",fact_lab!$E8*fact_lab!$J8, fact_lab!$K8) -> 324 | M8: =IF(fact_lab!$H8="Missing Contract", 0, fact_lab!$L8-fact_lab!$K8) -> 252 | N8: =fact_lab!$D8&"|"&fact_lab!$F8 -> PCM|1 Hr | O8: =fact_lab!$H8&"|"&fact_lab!$N8 -> C000015869|PCM|1 Hr | P8: =fact_lab!$G8&"|"&fact_lab!$C8 -> LTS|Pre | Q8: =TRIM(stg_lab_reports!$C8) -> 25S-010 | R8: {=XLOOKUP( TRIM(fact_lab!$Q8), dim_job!$B$2:$B$6, dim_job!$B$2:$B$6, "" )} -> 25S-010
A9: {=XLOOKUP( TRIM(fact_lab!$Q9), dim_job!$B$2:$B$6, dim_job!$B$2:$B$6, "" )} -> 25S-010 | B9: =stg_lab_reports!$A9 -> SCA | C9: =stg_lab_reports!$F9 -> Durings | D9: {=XLOOKUP(fact_lab!$C9,dim_lab_sca_map!$C$2:$C$64, dim_lab_sca_map!$B$2:$B$64, 0)} -> PCM | E9: =stg_lab_reports!$G9 -> 9 | F9: {=XLOOKUP(fact_lab!$D9, dim_lab_sca_map!$B$2:$B$64, dim_lab_sca_map!$D$2:$D$64)} -> 1 Hr | G9: =stg_lab_reports!$I9 -> LTS | H9: {=XLOOKUP(fact_lab!$A9, dim_job!$B$2:$B$6, dim_job!$H$2:$H$6, "Missing Contract")} -> C000015869 | I9: {=XLOOKUP(fact_lab!$P9, dim_lab_vendor_rates!$A$2:$A$49, dim_lab_vendor_rates!$E$2:$E$49, "No Rate")} -> 6 | J9: {=XLOOKUP( fact_lab!$O9, dim_lab_sca_map!$G$2:$G$64, dim_lab_sca_map!$E$2:$E$64, 0 )} -> 27 | K9: =fact_lab!$E9*fact_lab!$I9 -> 54 | L9: =IF(fact_lab!$B9="SCA",fact_lab!$E9*fact_lab!$J9, fact_lab!$K9) -> 243 | M9: =IF(fact_lab!$H9="Missing Contract", 0, fact_lab!$L9-fact_lab!$K9) -> 189 | N9: =fact_lab!$D9&"|"&fact_lab!$F9 -> PCM|1 Hr | O9: =fact_lab!$H9&"|"&fact_lab!$N9 -> C000015869|PCM|1 Hr | P9: =fact_lab!$G9&"|"&fact_lab!$C9 -> LTS|Durings | Q9: =TRIM(stg_lab_reports!$C9) -> 25S-010 | R9: {=XLOOKUP( TRIM(fact_lab!$Q9), dim_job!$B$2:$B$6, dim_job!$B$2:$B$6, "" )} -> 25S-010
A10: {=XLOOKUP( TRIM(fact_lab!$Q10), dim_job!$B$2:$B$6, dim_job!$B$2:$B$6, "" )} -> 25S-010 | B10: =stg_lab_reports!$A10 -> SCA | C10: =stg_lab_reports!$F10 -> Finals | D10: {=XLOOKUP(fact_lab!$C10,dim_lab_sca_map!$C$2:$C$64, dim_lab_sca_map!$B$2:$B$64, 0)} -> PCM | E10: =stg_lab_reports!$G10 -> 12 | F10: {=XLOOKUP(fact_lab!$D10, dim_lab_sca_map!$B$2:$B$64, dim_lab_sca_map!$D$2:$D$64)} -> 1 Hr | G10: =stg_lab_reports!$I10 -> LTS | H10: {=XLOOKUP(fact_lab!$A10, dim_job!$B$2:$B$6, dim_job!$H$2:$H$6, "Missing Contract")} -> C000015869 | I10: {=XLOOKUP(fact_lab!$P10, dim_lab_vendor_rates!$A$2:$A$49, dim_lab_vendor_rates!$E$2:$E$49, "No Rate")} -> 6 | J10: {=XLOOKUP( fact_lab!$O10, dim_lab_sca_map!$G$2:$G$64, dim_lab_sca_map!$E$2:$E$64, 0 )} -> 27 | K10: =fact_lab!$E10*fact_lab!$I10 -> 72 | L10: =IF(fact_lab!$B10="SCA",fact_lab!$E10*fact_lab!$J10, fact_lab!$K10) -> 324 | M10: =IF(fact_lab!$H10="Missing Contract", 0, fact_lab!$L10-fact_lab!$K10) -> 252 | N10: =fact_lab!$D10&"|"&fact_lab!$F10 -> PCM|1 Hr | O10: =fact_lab!$H10&"|"&fact_lab!$N10 -> C000015869|PCM|1 Hr | P10: =fact_lab!$G10&"|"&fact_lab!$C10 -> LTS|Finals | Q10: =TRIM(stg_lab_reports!$C10) -> 25S-010 | R10: {=XLOOKUP( TRIM(fact_lab!$Q10), dim_job!$B$2:$B$6, dim_job!$B$2:$B$6, "" )} -> 25S-010
A11: {=XLOOKUP( TRIM(fact_lab!$Q11), dim_job!$B$2:$B$6, dim_job!$B$2:$B$6, "" )} -> 25S-010 | B11: =stg_lab_reports!$A11 -> SCA | C11: =stg_lab_reports!$F11 -> Finals | D11: {=XLOOKUP(fact_lab!$C11,dim_lab_sca_map!$C$2:$C$64, dim_lab_sca_map!$B$2:$B$64, 0)} -> PCM | E11: =stg_lab_reports!$G11 -> 12 | F11: {=XLOOKUP(fact_lab!$D11, dim_lab_sca_map!$B$2:$B$64, dim_lab_sca_map!$D$2:$D$64)} -> 1 Hr | G11: =stg_lab_reports!$I11 -> LTS | H11: {=XLOOKUP(fact_lab!$A11, dim_job!$B$2:$B$6, dim_job!$H$2:$H$6, "Missing Contract")} -> C000015869 | I11: {=XLOOKUP(fact_lab!$P11, dim_lab_vendor_rates!$A$2:$A$49, dim_lab_vendor_rates!$E$2:$E$49, "No Rate")} -> 6 | J11: {=XLOOKUP( fact_lab!$O11, dim_lab_sca_map!$G$2:$G$64, dim_lab_sca_map!$E$2:$E$64, 0 )} -> 27 | K11: =fact_lab!$E11*fact_lab!$I11 -> 72 | L11: =IF(fact_lab!$B11="SCA",fact_lab!$E11*fact_lab!$J11, fact_lab!$K11) -> 324 | M11: =IF(fact_lab!$H11="Missing Contract", 0, fact_lab!$L11-fact_lab!$K11) -> 252 | N11: =fact_lab!$D11&"|"&fact_lab!$F11 -> PCM|1 Hr | O11: =fact_lab!$H11&"|"&fact_lab!$N11 -> C000015869|PCM|1 Hr | P11: =fact_lab!$G11&"|"&fact_lab!$C11 -> LTS|Finals | Q11: =TRIM(stg_lab_reports!$C11) -> 25S-010 | R11: {=XLOOKUP( TRIM(fact_lab!$Q11), dim_job!$B$2:$B$6, dim_job!$B$2:$B$6, "" )} -> 25S-010
A12: {=XLOOKUP( TRIM(fact_lab!$Q12), dim_job!$B$2:$B$6, dim_job!$B$2:$B$6, "" )} -> 25S-010 | B12: =stg_lab_reports!$A12 -> SCA | C12: =stg_lab_reports!$F12 -> Backgrounds | D12: {=XLOOKUP(fact_lab!$C12,dim_lab_sca_map!$C$2:$C$64, dim_lab_sca_map!$B$2:$B$64, 0)} -> PCM | E12: =stg_lab_reports!$G12 -> 12 | F12: {=XLOOKUP(fact_lab!$D12, dim_lab_sca_map!$B$2:$B$64, dim_lab_sca_map!$D$2:$D$64)} -> 1 Hr | G12: =stg_lab_reports!$I12 -> LTS | H12: {=XLOOKUP(fact_lab!$A12, dim_job!$B$2:$B$6, dim_job!$H$2:$H$6, "Missing Contract")} -> C000015869 | I12: {=XLOOKUP(fact_lab!$P12, dim_lab_vendor_rates!$A$2:$A$49, dim_lab_vendor_rates!$E$2:$E$49, "No Rate")} -> 6 | J12: {=XLOOKUP( fact_lab!$O12, dim_lab_sca_map!$G$2:$G$64, dim_lab_sca_map!$E$2:$E$64, 0 )} -> 27 | K12: =fact_lab!$E12*fact_lab!$I12 -> 72 | L12: =IF(fact_lab!$B12="SCA",fact_lab!$E12*fact_lab!$J12, fact_lab!$K12) -> 324 | M12: =IF(fact_lab!$H12="Missing Contract", 0, fact_lab!$L12-fact_lab!$K12) -> 252 | N12: =fact_lab!$D12&"|"&fact_lab!$F12 -> PCM|1 Hr | O12: =fact_lab!$H12&"|"&fact_lab!$N12 -> C000015869|PCM|1 Hr | P12: =fact_lab!$G12&"|"&fact_lab!$C12 -> LTS|Backgrounds | Q12: =TRIM(stg_lab_reports!$C12) -> 25S-010 | R12: {=XLOOKUP( TRIM(fact_lab!$Q12), dim_job!$B$2:$B$6, dim_job!$B$2:$B$6, "" )} -> 25S-010
A13: {=XLOOKUP( TRIM(fact_lab!$Q13), dim_job!$B$2:$B$6, dim_job!$B$2:$B$6, "" )} -> 25S-010 | B13: =stg_lab_reports!$A13 -> SCA | C13: =stg_lab_reports!$F13 -> Backgrounds | D13: {=XLOOKUP(fact_lab!$C13,dim_lab_sca_map!$C$2:$C$64, dim_lab_sca_map!$B$2:$B$64, 0)} -> PCM | E13: =stg_lab_reports!$G13 -> 12 | F13: {=XLOOKUP(fact_lab!$D13, dim_lab_sca_map!$B$2:$B$64, dim_lab_sca_map!$D$2:$D$64)} -> 1 Hr | G13: =stg_lab_reports!$I13 -> LTS | H13: {=XLOOKUP(fact_lab!$A13, dim_job!$B$2:$B$6, dim_job!$H$2:$H$6, "Missing Contract")} -> C000015869 | I13: {=XLOOKUP(fact_lab!$P13, dim_lab_vendor_rates!$A$2:$A$49, dim_lab_vendor_rates!$E$2:$E$49, "No Rate")} -> 6 | J13: {=XLOOKUP( fact_lab!$O13, dim_lab_sca_map!$G$2:$G$64, dim_lab_sca_map!$E$2:$E$64, 0 )} -> 27 | K13: =fact_lab!$E13*fact_lab!$I13 -> 72 | L13: =IF(fact_lab!$B13="SCA",fact_lab!$E13*fact_lab!$J13, fact_lab!$K13) -> 324 | M13: =IF(fact_lab!$H13="Missing Contract", 0, fact_lab!$L13-fact_lab!$K13) -> 252 | N13: =fact_lab!$D13&"|"&fact_lab!$F13 -> PCM|1 Hr | O13: =fact_lab!$H13&"|"&fact_lab!$N13 -> C000015869|PCM|1 Hr | P13: =fact_lab!$G13&"|"&fact_lab!$C13 -> LTS|Backgrounds | Q13: =TRIM(stg_lab_reports!$C13) -> 25S-010 | R13: {=XLOOKUP( TRIM(fact_lab!$Q13), dim_job!$B$2:$B$6, dim_job!$B$2:$B$6, "" )} -> 25S-010
... A38: {=XLOOKUP( TRIM(fact_lab!$Q38), dim_job!$B$2:$B$6, dim_job!$B$2:$B$6, "" )} -> 22S-029 | B38: =stg_lab_reports!$A38 -> SCA | C38: =stg_lab_reports!$F38 -> DAF | D38: {=XLOOKUP(fact_lab!$C38,dim_lab_sca_map!$C$2:$C$64, dim_lab_sca_map!$B$2:$B$64, 0)} -> PCM | E38: =stg_lab_reports!$G38 -> 7 | F38: {=XLOOKUP(fact_lab!$D38, dim_lab_sca_map!$B$2:$B$64, dim_lab_sca_map!$D$2:$D$64)} -> 1 Hr | G38: =stg_lab_reports!$I38 -> ALLAB | H38: {=XLOOKUP(fact_lab!$A38, dim_job!$B$2:$B$6, dim_job!$H$2:$H$6, "Missing Contract")} -> C000015869 | I38: {=XLOOKUP(fact_lab!$P38, dim_lab_vendor_rates!$A$2:$A$49, dim_lab_vendor_rates!$E$2:$E$49, "No Rate")} -> 5 | J38: {=XLOOKUP( fact_lab!$O38, dim_lab_sca_map!$G$2:$G$64, dim_lab_sca_map!$E$2:$E$64, 0 )} -> 27 | K38: =fact_lab!$E38*fact_lab!$I38 -> 35 | L38: =IF(fact_lab!$B38="SCA",fact_lab!$E38*fact_lab!$J38, fact_lab!$K38) -> 189 | M38: =IF(fact_lab!$H38="Missing Contract", 0, fact_lab!$L38-fact_lab!$K38) -> 154 | N38: =fact_lab!$D38&"|"&fact_lab!$F38 -> PCM|1 Hr | O38: =fact_lab!$H38&"|"&fact_lab!$N38 -> C000015869|PCM|1 Hr | P38: =fact_lab!$G38&"|"&fact_lab!$C38 -> ALLAB|DAF | Q38: =TRIM(stg_lab_reports!$C38) -> 22S-029 | R38: {=XLOOKUP( TRIM(fact_lab!$Q38), dim_job!$B$2:$B$6, dim_job!$B$2:$B$6, "" )} -> 22S-029

Sheet fact_job_profitability
A1: Job_Number | B1: Labor_Revenue | C1: Labor_Cost | D1: labor_jobs_count | E1: Labor_Margin | F1: Lab_Revenue | G1: Lab_Cost | H1: lab_jobs_count | I1: Lab_Margin | J1: Total_Profit | K1: Total_Cost | L1: Total_Revenue | M1: Profit_Margin_Pct
A2: 22S-079 | B2: =SUMIFS(fact_labor!$S$2:$S$29, fact_labor!$I$2:$I$29, A2) -> #N/A | C2: =SUMIFS(fact_labor!$R$2:$R$29, fact_labor!$K$2:$K$29, A2) -> #N/A | D2: =COUNTIFS(fact_labor!$I$2:$I$29,A2) -> 2 | E2: =fact_job_profitability!$B2-fact_job_profitability!$C2 -> #N/A | F2: =SUMIFS(fact_lab!$L$2:$L$38, fact_lab!$A$2:$A$38, A2) -> 216 | G2: =SUMIFS(fact_lab!$K$2:$K$38, fact_lab!$A$2:$A$38, A2) -> 40 | H2: =COUNTIFS(fact_lab!$A$2:$A$38, A2) -> 1 | I2: =fact_job_profitability!$F2-fact_job_profitability!$G2 -> 176 | J2: =fact_job_profitability!$E2+fact_job_profitability!$I2 -> #N/A | K2: =fact_job_profitability!$C2+fact_job_profitability!$G2 -> #N/A | L2: =fact_job_profitability!$B2+fact_job_profitability!$F2 -> #N/A | M2: =IF(fact_job_profitability!$J2>0,fact_job_profitability!$J2/fact_job_profitability!$L2,0) -> #N/A
A3: 22S-029 | B3: =SUMIFS(fact_labor!$S$2:$S$29, fact_labor!$I$2:$I$29, A3) -> #N/A | C3: =SUMIFS(fact_labor!$R$2:$R$29, fact_labor!$K$2:$K$29, A3) -> #N/A | D3: =COUNTIFS(fact_labor!$I$2:$I$29,A3) -> 2 | E3: =fact_job_profitability!$B3-fact_job_profitability!$C3 -> #N/A | F3: =SUMIFS(fact_lab!$L$2:$L$38, fact_lab!$A$2:$A$38, A3) -> 189 | G3: =SUMIFS(fact_lab!$K$2:$K$38, fact_lab!$A$2:$A$38, A3) -> 35 | H3: =COUNTIFS(fact_lab!$A$2:$A$38, A3) -> 1 | I3: =fact_job_profitability!$F3-fact_job_profitability!$G3 -> 154 | J3: =fact_job_profitability!$E3+fact_job_profitability!$I3 -> #N/A | K3: =fact_job_profitability!$C3+fact_job_profitability!$G3 -> #N/A | L3: =fact_job_profitability!$B3+fact_job_profitability!$F3 -> #N/A | M3: =IF(fact_job_profitability!$J3>0,fact_job_profitability!$J3/fact_job_profitability!$L3,0) -> #N/A
A4: 23S-056 | B4: =SUMIFS(fact_labor!$S$2:$S$29, fact_labor!$I$2:$I$29, A4) -> #N/A | C4: =SUMIFS(fact_labor!$R$2:$R$29, fact_labor!$K$2:$K$29, A4) -> #N/A | D4: =COUNTIFS(fact_labor!$I$2:$I$29,A4) -> 1 | E4: =fact_job_profitability!$B4-fact_job_profitability!$C4 -> #N/A | F4: =SUMIFS(fact_lab!$L$2:$L$38, fact_lab!$A$2:$A$38, A4) -> 81 | G4: =SUMIFS(fact_lab!$K$2:$K$38, fact_lab!$A$2:$A$38, A4) -> 18 | H4: =COUNTIFS(fact_lab!$A$2:$A$38, A4) -> 1 | I4: =fact_job_profitability!$F4-fact_job_profitability!$G4 -> 63 | J4: =fact_job_profitability!$E4+fact_job_profitability!$I4 -> #N/A | K4: =fact_job_profitability!$C4+fact_job_profitability!$G4 -> #N/A | L4: =fact_job_profitability!$B4+fact_job_profitability!$F4 -> #N/A | M4: =IF(fact_job_profitability!$J4>0,fact_job_profitability!$J4/fact_job_profitability!$L4,0) -> #N/A
A5: 24S-114 | B5: =SUMIFS(fact_labor!$S$2:$S$29, fact_labor!$I$2:$I$29, A5) -> #N/A | C5: =SUMIFS(fact_labor!$R$2:$R$29, fact_labor!$K$2:$K$29, A5) -> #N/A | D5: =COUNTIFS(fact_labor!$I$2:$I$29,A5) -> 2 | E5: =fact_job_profitability!$B5-fact_job_profitability!$C5 -> #N/A | F5: =SUMIFS(fact_lab!$L$2:$L$38, fact_lab!$A$2:$A$38, A5) -> 378 | G5: =SUMIFS(fact_lab!$K$2:$K$38, fact_lab!$A$2:$A$38, A5) -> 84 | H5: =COUNTIFS(fact_lab!$A$2:$A$38, A5) -> 2 | I5: =fact_job_profitability!$F5-fact_job_profitability!$G5 -> 294 | J5: =fact_job_profitability!$E5+fact_job_profitability!$I5 -> #N/A | K5: =fact_job_profitability!$C5+fact_job_profitability!$G5 -> #N/A | L5: =fact_job_profitability!$B5+fact_job_profitability!$F5 -> #N/A | M5: =IF(fact_job_profitability!$J5>0,fact_job_profitability!$J5/fact_job_profitability!$L5,0) -> #N/A
A6: 25S-010 | B6: =SUMIFS(fact_labor!$S$2:$S$29, fact_labor!$I$2:$I$29, A6) -> #N/A | C6: =SUMIFS(fact_labor!$R$2:$R$29, fact_labor!$K$2:$K$29, A6) -> #N/A | D6: =COUNTIFS(fact_labor!$I$2:$I$29,A6) -> 19 | E6: =fact_job_profitability!$B6-fact_job_profitability!$C6 -> #N/A | F6: =SUMIFS(fact_lab!$L$2:$L$38, fact_lab!$A$2:$A$38, A6) -> 12445 | G6: =SUMIFS(fact_lab!$K$2:$K$38, fact_lab!$A$2:$A$38, A6) -> 2890 | H6: =COUNTIFS(fact_lab!$A$2:$A$38, A6) -> 32 | I6: =fact_job_profitability!$F6-fact_job_profitability!$G6 -> 9555 | J6: =fact_job_profitability!$E6+fact_job_profitability!$I6 -> #N/A | K6: =fact_job_profitability!$C6+fact_job_profitability!$G6 -> #N/A | L6: =fact_job_profitability!$B6+fact_job_profitability!$F6 -> #N/A | M6: =IF(fact_job_profitability!$J6>0,fact_job_profitability!$J6/fact_job_profitability!$L6,0) -> #N/A

Sheet dim_building
A1: Building_ID | B1: BID_NAME | C1: BID_ADDRESS | D1: BID_BOUROUGH | E1: BID_STATE | F1: BID_ZIP | G1: BID_GEO
A2: K014 | B2: I.S. 14 | C2: 2424 BATCHELDER STREET | D2: BROOKLYN | E2: NY | F2: 11235 | G2: 22
A3: K016 | B3: P.S. 16 | C3: 157 WILSON STREET | D3: BROOKLYN | E3: NY | F3: 11211 | G3: 14
A4: K017 | B4: P.S. 17 | C4: 208 NORTH 5 STREET | D4: BROOKLYN | E4: NY | F4: 11211 | G4: 14
A5: K018 | B5: P.S. 18 | C5: 101 MAUJER STREET | D5: BROOKLYN | E5: NY | F5: 11206 | G5: 14
A6: K019 | B6: P.S. 19 | C6: 325 SOUTH 3 STREET | D6: BROOKLYN | E6: NY | F6: 11211 | G6: 14
A7: K027 | B7: P.S. 27 | C7: 27 HUNTINGTON STREET | D7: BROOKLYN | E7: NY | F7: 11231 | G7: 15
A8: K035 | B8: I.S. 35 | C8: 272 MACDONOUGH STREET | D8: BROOKLYN | E8: NY | F8: 11233 | G8: 16
A9: K043 | B9: I.S. 98 | C9: 1401 EMMONS AVENUE | D9: BROOKLYN | E9: NY | F9: 11235 | G9: 21
A10: K050 | B10: J.H.S. 50 | C10: 183 SOUTH 3 STREET | D10: BROOKLYN | E10: NY | F10: 11211 | G10: 14
A11: K051 | B11: I.S. 51 | C11: 350 5 AVENUE | D11: BROOKLYN | E11: NY | F11: 11215 | G11: 15
A12: K054 | B12: P.S. 54 | C12: 195 SANDFORD STREET | D12: BROOKLYN | E12: NY | F12: 11205 | G12: 13
A13: K055 | B13: I.S. 55 | C13: 2021 BERGEN STREET | D13: BROOKLYN | E13: NY | F13: 11233 | G13: 23
... A27: K128 | B27: P.S. 128 (TANDEM BROOKLYN STUDIO K721) | C27: 2075 84 STREET | D27: BROOKLYN | E27: NY | F27: 11214 | G27: 21
A28: K132 | B28: P.S. 132 | C28: 320 MANHATTAN AVENUE | D28: BROOKLYN | E28: NY | F28: 11211 | G28: 14
A29: K136 | B29: I.S. 136 | C29: 4004 4 AVENUE | D29: BROOKLYN | E29: NY | F29: 11232 | G29: 15
A30: K138 | B30: P.S. 138 | C30: 760 PROSPECT PLACE | D30: BROOKLYN | E30: NY | F30: 11216 | G30: 17
A31: K142 | B31: J.H.S. 142 | C31: 610 HENRY STREET | D31: BROOKLYN | E31: NY | F31: 11231 | G31: 15
A32: K145 | B32: P.S. 145 | C32: 100 NOLL STREET | D32: BROOKLYN | E32: NY | F32: 11206 | G32: 32
A33: K149 | B33: P.S. 149 | C33: 700 SUTTER AVENUE | D33: BROOKLYN | E33: NY | F33: 11207 | G33: 19
A34: K150 | B34: P.S. 150 | C34: 364 SACKMAN STREET | D34: BROOKLYN | E34: NY | F34: 11212 | G34: 23
A35: K151 | B35: P.S. 151 | C35: 763 KNICKERBOCKER AVENUE | D35: BROOKLYN | E35: NY | F35: 11207 | G35: 32
A36: K159 | B36: P.S. 159 | C36: 2781 PITKIN AVENUE | D36: BROOKLYN | E36: NY | F36: 11208 | G36: 19
A37: K160 | B37: P.S. 160 | C37: 5105 FORT HAMILTON PARKWAY | D37: BROOKLYN | E37: NY | F37: 11219 | G37: 20
A38: K162 | B38: I.S. 162 | C38: 1390 WILLOUGHBY AVENUE | D38: BROOKLYN | E38: NY | F38: 11237 | G38: 32
A39: K163 | B39: P.S. 163 | C39: 1664 BENSON AVENUE | D39: BROOKLYN | E39: NY | F39: 11214 | G39: 20
A40: K164 | B40: P.S. 164 | C40: 4211 14 AVENUE | D40: BROOKLYN | E40: NY | F40: 11219 | G40: 20
... A154: Q015 | B154: P.S. 15 | C154: 121-15 LUCAS STREET | D154: QUEENS | E154: NY | F154: 11413 | G154: 29
A155: Q020 | B155: P.S. 20 | C155: 142-30 BARCLAY AVENUE | D155: QUEENS | E155: NY | F155: 11355 | G155: 25
A156: Q021 | B156: P.S. 21 | C156: 147-36 26TH AVENUE | D156: QUEENS | E156: NY | F156: 11354 | G156: 25
A157: Q022 | B157: P.S. 22 | C157: 153-33 SANFORD AVENUE | D157: QUEENS | E157: NY | F157: 11355 | G157: 25
A158: Q023 | B158: QUEENS ACADEMY HS | C158: 138-11 35 AVENUE | D158: QUEENS | E158: NY | F158: 11354 | G158: 25
A159: Q024 | B159: P.S. 24 | C159: 45-57 UNION STREET | D159: QUEENS | E159: NY | F159: 11355 | G159: 25
A160: Q025 | B160: J.H.S. 25 | C160: 34-65 192 STREET | D160: QUEENS | E160: NY | F160: 11358 | G160: 25
A161: Q029 | B161: P.S. 29 | C161: 125-10 23 AVENUE | D161: QUEENS | E161: NY | F161: 11356 | G161: 25
A162: Q030 | B162: P.S. 30 | C162: 126-10 BEDELL STREET | D162: QUEENS | E162: NY | F162: 11434 | G162: 28
A163: Q035 | B163: P.S. 35 | C163: 191-02 90TH AVENUE | D163: QUEENS | E163: NY | F163: 11423 | G163: 29
A164: Q037 | B164: P.S. 37 | C164: 179-37 137 AVENUE | D164: QUEENS | E164: NY | F164: 11434 | G164: 29
A165: Q038 | B165: P.S. 38 | C165: 135-21 241 STREET | D165: QUEENS | E165: NY | F165: 11422 | G165: 29
A166: Q041 | B166: P.S. 41 | C166: 34-06 214 LANE | D166: QUEENS | E166: NY | F166: 11361 | G166: 26
A167: Q059 | B167: I.S. 59 | C167: 132-55 RIDGEDALE STREET | D167: QUEENS | E167: NY | F167: 11413 | G167: 29
... A216: Q490 | B216: CAMPUS MAGNET HS (JACKSON) | C216: 207-01 116 AVENUE | D216: QUEENS | E216: NY | F216: 11411 | G216: 29
A217: Q520 | B217: NOT FOUND | D217: QUEENS
A218: Q593 | B218: P.S. @ 140 BEACH 112 STREET | C218: 140 BEACH 112 STREET | D218: QUEENS | E218: NY | F218: 11694 | G218: 27
A219: Q725 | B219: HS FOR INFORMATION TECH | C219: 21-16 44TH ROAD | D219: QUEENS | E219: NY | F219: 11101 | G219: 30
A220: Q800 | B220: DOE ADMINISTRATIVE / STUDENT SERVICES | C220: 28-11 QUEENS PLAZA NORTH | D220: QUEENS | E220: NY | F220: 11101 | G220: 30
A221: Q801 | B221: OSSS / DSF | C221: 44-36 VERNON BOULEVARD | D221: QUEENS | E221: NY | F221: 11101 | G221: 30
A222: R001 | B222: P.S. 1 | C222: 58 SUMMIT STREET | D222: STATEN ISLAND | E222: NY | F222: 10307 | G222: 31
A223: R002 | B223: I.S. 2 | C223: 333 MIDLAND AVENUE | D223: STATEN ISLAND | E223: NY | F223: 10306 | G223: 31
A224: R005 | B224: P.S. 5 | C224: 348A DEISIUS STREET | D224: STATEN ISLAND | E224: NY | F224: 10312 | G224: 31
A225: R007 | B225: I.S. 7 | C225: 1270 HUGUENOT AVENUE | D225: STATEN ISLAND | E225: NY | F225: 10312 | G225: 31
A226: R008 | B226: P.S. 8 | C226: 112 LINDENWOOD ROAD | D226: STATEN ISLAND | E226: NY | F226: 10308 | G226: 31
A227: R013 | B227: P.S. 13 | C227: 191 VERMONT AVENUE | D227: STATEN ISLAND | E227: NY | F227: 10305 | G227: 31
A228: R014 | B228: P.S. 14 | C228: 100 TOMPKINS AVENUE | D228: STATEN ISLAND | E228: NY | F228: 10304 | G228: 31
A229: R018 | B229: P.S. 18 | C229: 221 BROADWAY | D229: STATEN ISLAND | E229: NY | F229: 10310 | G229: 31
... A271: X065 | B271: P.S. 65 | C271: 677 EAST 141 STREET | D271: BRONX | E271: NY | F271: 10454 | G271: 7
A272: X071 | B272: ROSE E SCALA SCHOOL | C272: 3040 ROBERTS AVENUE | D272: BRONX | E272: NY | F272: 10461 | G272: 8
A273: X074 | B273: I.S. 201 | C273: 730 BRYANT AVENUE | D273: BRONX | E273: NY | F273: 10474 | G273: 8
A274: X075 | B274: P.S. 75 | C274: 984 FAILE STREET | D274: BRONX | E274: NY | F274: 10459 | G274: 8
A275: X080 | B275: I.S. 80/P.S. 280 | C275: 149 EAST MOSHOLU PARKWAY NORTH | D275: BRONX | E275: NY | F275: 10467 | G275: 10
A276: X085 | B276: P.S. 85 | C276: 2400 MARION AVENUE | D276: BRONX | E276: NY | F276: 10458 | G276: 10
A277: X086 | B277: P.S. 86 | C277: 2756 RESERVOIR AVENUE | D277: BRONX | E277: NY | F277: 10468 | G277: 10
A278: X093 | B278: P.S. 93 | C278: 1535 STORY AVENUE | D278: BRONX | E278: NY | F278: 10473 | G278: 8
A279: X101 | B279: I.S. 101 | C279: 2750 LAFAYETTE AVENUE | D279: BRONX | E279: NY | F279: 10465 | G279: 8
A280: X102 | B280: P.S. 102 | C280: 1827 ARCHER STREET | D280: BRONX | E280: NY | F280: 10460 | G280: 12
A281: X107 | B281: P.S. 107 | C281: 1695 SEWARD AVENUE | D281: BRONX | E281: NY | F281: 10473 | G281: 8
A282: X120 | B282: I.S. 301 | C282: 890 CAULDWELL AVENUE | D282: BRONX | E282: NY | F282: 10456 | G282: 8
A283: X125 | B283: I.S. 125 | C283: 1111 PUGSLEY AVENUE | D283: BRONX | E283: NY | F283: 10472 | G283: 8
A284: X127 | B284: I.S. 127 | C284: 1560 PURDY STREET | D284: BRONX | E284: NY | F284: 10462 | G284: 11
A285: X131 | B285: I.S. 131 | C285: 885 BOLTON AVENUE | D285: BRONX | E285: NY | F285: 10473 | G285: 8
A286: X132 | B286: I.S. 132 | C286: 1245 WASHINGTON AVENUE | D286: BRONX | E286: NY | F286: 10456 | G286: 9
A287: X139 | B287: J.H.S. 222 | C287: 345 BROOK AVENUE | D287: BRONX | E287: NY | F287: 10454 | G287: 7
A288: X142 | B288: I.S. 142 | C288: 3750 BAYCHESTER AVENUE | D288: BRONX | E288: NY | F288: 10466 | G288: 11
A289: X146 | B289: P.S. 146 | C289: 968 CAULDWELL AVENUE | D289: BRONX | E289: NY | F289: 10456 | G289: 8
A290: X149 | B290: J.H.S. 149 | C290: 360 EAST 145 STREET | D290: BRONX | E290: NY | F290: 10454 | G290: 7
A291: X161 | B291: P.S. 161 | C291: 628 TINTON AVENUE | D291: BRONX | E291: NY | F291: 10455 | G291: 7
A292: X277 | B292: P.S. 277 | C292: 519 ST ANNS AVENUE | D292: BRONX | E292: NY | F292: 10455 | G292: 7
A293: X425 | B293: EVANDER CHILDS EDUCATIONAL COMPLEX | C293: 800 EAST GUN HILL ROAD | D293: BRONX | E293: NY | F293: 10467 | G293: 11
A294: X455 | B294: HARRY S. TRUMAN HS | C294: 750 BAYCHESTER AVENUE | D294: BRONX | E294: NY | F294: 10475 | G294: 11
... A300: X843 | B300: P.S. 246 (POE CENTER) | C300: 2641 GRAND CONCOURSE | D300: BRONX | E300: NY | F300: 10468 | G300: 10

Sheet dim_sca_contracts
A1: Contract_No | B1: SCA_Execution_Date | C1: Expiration_Date | D1: Contract_Value | E1: Home_Multiplier | F1: Field_Multiplier
A2: C000015128 | B2: 43424 | C2: 44519 | D2: 6000000 | E2: 2.51 | F2: 2.41
A3: C000015869 | B3: 44621 | C3: 45716 | D3: 6000000 | E3: 2.75 | F3: 2.54
A4: C000016435 | B4: 45728 | C4: 46823 | D4: 5000000 | E4: 3 | F4: 2.93

Sheet DASHBOARD
A1: Operations Command Center
A2: What Job Needs
A3: Total Revenue
A4: Total Cost
A5: Total Profit
A6: Profit Margin %
A8: Job-Level Breakdown
A9: Job ID | B9: Labor Revenue | C9: Lab Revenue | D9: Labor Cost | E9: Lab Cost | F9: Total Profit

Sheet Issues I Found
A2: Part of Phase 1 | B2: The Groysman's are the two top technicians that don't hand in their log books - they don't get paid either
A4: Phase 2 of this project | B4: We are paying (vendor - cost) far more for CHRYS and AMPH then we are being reimbursed for (sca - revenue).
A6: This is where this project started | B6: Only CA has been paid twice for the same job
A8: Stumbling Block | B8: Changes of Hourly Rates - between contract rates and raises, this was tough to get a handle on
A10: SCA Debug | B10: They had me listed as Sent to RCMS, using my data, RFP's for dim_assigned_job, these were paid and I found a bug in their system
B11: Corrections to numbers of labs were made after the "Create RFP" and this broke their system. Through this project, I was able to identify which job it was, what was changed, the amounts that were changed, basically where it went wrong. This should not have been possible, so bug found.
A14: Lost logs | B14: This helped me audit logs received and payroll to locate logs that were misfiled and thought lost. | C14: The real start of this project
A17: Project Monitor Rate | B17: We have been overpaying our technicians for Project Monitoring (Code 01)
A20: Based on Labor_Margin | B20: I was pulling from the wrong column in sca_rates. Only when I got to fact_job_summary did I see my issue, we were making no profit and that can't be right. I check a few jobs, the final RFP, and saw the hourly billing error.

Sheet Final Model
A1: DIMENSIONAL MODELING
A2: dim_technician
A3: EmpKey | B3: EmpName | C3: IsActive
A4: PK
A5: COR001 | B5: Cornel Albue | C5: 1
A8: dim_job_code
A9: JobCodeKey | B9: JobCode | C9: Job Title
A10: PK
A11: 1 | B11: 1 | C11: Asbestos Project Monitor
A14: dim_contract
A15: ContractKey | B15: ContractNo | C15: StartDate | D15: EndDate | E15: ContractGrp | F15: IsCurrent
A16: 1 | B16: C000015128 | C16: 43101 | D16: 44197 | E16: Previous | F16: 0
A17: 2 | B17: C000015869 | C17: 44927 | D17: 45727 | E17: Previous | F17: 0
A18: 3 | B18: C000016435 | C18: 45717 | D18: NULL | E18: Current | F18: 1
A19: 0 | B19: NULL | E19: NonSCA
A22: dim_job
A23: JobKey | B23: JobID | C23: BID | D23: Description | E23: ServiceID | F23: WA_No | G23: ContractNo
A24: PK
A27: dim emp rate hx | C27: SCD Type 2 Table
A28: Rate Key | B28: EmpKey | C28: JobCodeKey | D28: ContractGrp | E28: YrsExpTier | F28: HourlyRate | G28: RateStartDate | H28: RateEndDate
A29: PK | B29: FK | C29: FK
A31: Mine looks like this but doesn't use keys, uses names
A35: fact labor
A36: DateKey | B36: EmpKey | C36: JobKey | D36: JobCodeKey | E36: Hours | F36: HourlyRate | G36: LaborCost | H36: SCARate | I36: LaborRevenue
